package net.youmi.android.d.a;

class b
  implements Runnable
{
  b(a parama, String paramString) {}
  
  /* Error */
  public void run()
  {
    // Byte code:
    //   0: aload_0
    //   1: getfield 16	net/youmi/android/d/a/b:a	Ljava/lang/String;
    //   4: ifnull +75 -> 79
    //   7: aload_0
    //   8: getfield 16	net/youmi/android/d/a/b:a	Ljava/lang/String;
    //   11: ldc 25
    //   13: invokevirtual 31	java/lang/String:equals	(Ljava/lang/Object;)Z
    //   16: ifeq +4 -> 20
    //   19: return
    //   20: new 33	net/youmi/android/d/f/a
    //   23: dup
    //   24: aload_0
    //   25: getfield 14	net/youmi/android/d/a/b:b	Lnet/youmi/android/d/a/a;
    //   28: invokestatic 38	net/youmi/android/d/a/a:a	(Lnet/youmi/android/d/a/a;)Landroid/content/Context;
    //   31: invokespecial 41	net/youmi/android/d/f/a:<init>	(Landroid/content/Context;)V
    //   34: astore_3
    //   35: iconst_0
    //   36: istore_1
    //   37: aload_0
    //   38: getfield 14	net/youmi/android/d/a/b:b	Lnet/youmi/android/d/a/a;
    //   41: invokestatic 43	net/youmi/android/d/a/a:b	(Lnet/youmi/android/d/a/a;)Landroid/content/Context;
    //   44: invokestatic 48	net/youmi/android/c/k/d:a	(Landroid/content/Context;)Lnet/youmi/android/c/k/d;
    //   47: invokevirtual 51	net/youmi/android/c/k/d:b	()I
    //   50: istore_2
    //   51: iload_2
    //   52: i2d
    //   53: ldc2_w 52
    //   56: dmul
    //   57: d2i
    //   58: istore_1
    //   59: aload_3
    //   60: aload_0
    //   61: getfield 16	net/youmi/android/d/a/b:a	Ljava/lang/String;
    //   64: sipush 8000
    //   67: iload_1
    //   68: invokevirtual 56	net/youmi/android/d/f/a:a	(Ljava/lang/String;II)V
    //   71: return
    //   72: astore_3
    //   73: return
    //   74: astore 4
    //   76: goto -17 -> 59
    //   79: return
    // Local variable table:
    //   start	length	slot	name	signature
    //   0	80	0	this	b
    //   36	32	1	i	int
    //   50	2	2	j	int
    //   34	26	3	locala	net.youmi.android.d.f.a
    //   72	1	3	localThrowable1	java.lang.Throwable
    //   74	1	4	localThrowable2	java.lang.Throwable
    // Exception table:
    //   from	to	target	type
    //   0	19	72	java/lang/Throwable
    //   20	35	72	java/lang/Throwable
    //   59	71	72	java/lang/Throwable
    //   37	51	74	java/lang/Throwable
  }
}


/* Location:           C:\Users\guanghui\Desktop\软件安全\361\classes-dex2jar.jar
 * Qualified Name:     net.youmi.android.d.a.b
 * JD-Core Version:    0.7.0.1
 */