package net.youmi.android.a.h.b.a;

import net.youmi.android.a.h.b.d;

public final class f
  extends d
{
  /* Error */
  protected org.json.JSONObject a(net.youmi.android.a.h.e parame, net.youmi.android.a.h.b paramb, org.json.JSONObject paramJSONObject)
  {
    // Byte code:
    //   0: aload_1
    //   1: ifnonnull +8 -> 9
    //   4: iconst_3
    //   5: invokestatic 16	net/youmi/android/a/h/b/a/f:a	(I)Lorg/json/JSONObject;
    //   8: areturn
    //   9: aload_1
    //   10: invokeinterface 21 1 0
    //   15: astore_2
    //   16: aload_2
    //   17: ifnonnull +8 -> 25
    //   20: iconst_3
    //   21: invokestatic 16	net/youmi/android/a/h/b/a/f:a	(I)Lorg/json/JSONObject;
    //   24: areturn
    //   25: aload_3
    //   26: ldc 22
    //   28: aconst_null
    //   29: invokestatic 27	net/youmi/android/c/b/b:a	(Lorg/json/JSONObject;Ljava/lang/String;Ljava/lang/String;)Ljava/lang/String;
    //   32: astore 7
    //   34: aload 7
    //   36: ifnonnull +8 -> 44
    //   39: iconst_2
    //   40: invokestatic 16	net/youmi/android/a/h/b/a/f:a	(I)Lorg/json/JSONObject;
    //   43: areturn
    //   44: aload_3
    //   45: ldc 29
    //   47: iconst_1
    //   48: invokestatic 32	net/youmi/android/c/b/b:a	(Lorg/json/JSONObject;Ljava/lang/String;I)I
    //   51: istore 4
    //   53: iload 4
    //   55: ifeq +20 -> 75
    //   58: iload 4
    //   60: iconst_1
    //   61: if_icmpeq +14 -> 75
    //   64: iload 4
    //   66: iconst_2
    //   67: if_icmpeq +8 -> 75
    //   70: iconst_2
    //   71: invokestatic 16	net/youmi/android/a/h/b/a/f:a	(I)Lorg/json/JSONObject;
    //   74: areturn
    //   75: aload_3
    //   76: ldc 34
    //   78: iconst_0
    //   79: invokestatic 32	net/youmi/android/c/b/b:a	(Lorg/json/JSONObject;Ljava/lang/String;I)I
    //   82: istore 5
    //   84: new 36	net/youmi/android/a/h/j
    //   87: dup
    //   88: invokespecial 37	net/youmi/android/a/h/j:<init>	()V
    //   91: astore 8
    //   93: aload_3
    //   94: ldc 39
    //   96: aconst_null
    //   97: invokestatic 42	net/youmi/android/c/b/b:a	(Lorg/json/JSONObject;Ljava/lang/String;Lorg/json/JSONObject;)Lorg/json/JSONObject;
    //   100: astore 12
    //   102: aload 12
    //   104: ifnull +71 -> 175
    //   107: aload 12
    //   109: ldc 22
    //   111: aconst_null
    //   112: invokestatic 27	net/youmi/android/c/b/b:a	(Lorg/json/JSONObject;Ljava/lang/String;Ljava/lang/String;)Ljava/lang/String;
    //   115: astore 9
    //   117: aload 12
    //   119: ldc 29
    //   121: aconst_null
    //   122: invokestatic 27	net/youmi/android/c/b/b:a	(Lorg/json/JSONObject;Ljava/lang/String;Ljava/lang/String;)Ljava/lang/String;
    //   125: astore 10
    //   127: aload 12
    //   129: ldc 44
    //   131: aconst_null
    //   132: invokestatic 27	net/youmi/android/c/b/b:a	(Lorg/json/JSONObject;Ljava/lang/String;Ljava/lang/String;)Ljava/lang/String;
    //   135: astore 11
    //   137: aload 12
    //   139: ldc 34
    //   141: aconst_null
    //   142: invokestatic 27	net/youmi/android/c/b/b:a	(Lorg/json/JSONObject;Ljava/lang/String;Ljava/lang/String;)Ljava/lang/String;
    //   145: astore 12
    //   147: aload 8
    //   149: aload 9
    //   151: invokevirtual 47	net/youmi/android/a/h/j:a	(Ljava/lang/String;)V
    //   154: aload 8
    //   156: aload 10
    //   158: invokevirtual 49	net/youmi/android/a/h/j:b	(Ljava/lang/String;)V
    //   161: aload 8
    //   163: aload 11
    //   165: invokevirtual 51	net/youmi/android/a/h/j:c	(Ljava/lang/String;)V
    //   168: aload 8
    //   170: aload 12
    //   172: invokevirtual 53	net/youmi/android/a/h/j:d	(Ljava/lang/String;)V
    //   175: iload 4
    //   177: ifne +210 -> 387
    //   180: aload_3
    //   181: ldc 34
    //   183: invokevirtual 59	org/json/JSONObject:isNull	(Ljava/lang/String;)Z
    //   186: ifeq +69 -> 255
    //   189: aload_2
    //   190: aload 7
    //   192: invokestatic 64	net/youmi/android/c/k/f:b	(Landroid/content/Context;Ljava/lang/String;)Z
    //   195: istore 6
    //   197: iload 6
    //   199: ifeq +123 -> 322
    //   202: aload 8
    //   204: invokevirtual 67	net/youmi/android/a/h/j:e	()Z
    //   207: ifeq +13 -> 220
    //   210: aload_1
    //   211: iconst_4
    //   212: aload 8
    //   214: invokeinterface 70 3 0
    //   219: pop
    //   220: iconst_0
    //   221: invokestatic 16	net/youmi/android/a/h/b/a/f:a	(I)Lorg/json/JSONObject;
    //   224: astore_3
    //   225: new 55	org/json/JSONObject
    //   228: dup
    //   229: invokespecial 71	org/json/JSONObject:<init>	()V
    //   232: astore 9
    //   234: aload 9
    //   236: ldc 22
    //   238: iconst_1
    //   239: invokevirtual 75	org/json/JSONObject:put	(Ljava/lang/String;I)Lorg/json/JSONObject;
    //   242: pop
    //   243: aload_3
    //   244: ldc 34
    //   246: aload 9
    //   248: invokevirtual 78	org/json/JSONObject:put	(Ljava/lang/String;Ljava/lang/Object;)Lorg/json/JSONObject;
    //   251: pop
    //   252: aload_3
    //   253: areturn
    //   254: astore_3
    //   255: aload_2
    //   256: aload 7
    //   258: iload 5
    //   260: invokestatic 81	net/youmi/android/c/k/f:d	(Landroid/content/Context;Ljava/lang/String;I)Z
    //   263: istore 6
    //   265: iload 6
    //   267: ifeq +89 -> 356
    //   270: aload 8
    //   272: invokevirtual 67	net/youmi/android/a/h/j:e	()Z
    //   275: ifeq +13 -> 288
    //   278: aload_1
    //   279: iconst_4
    //   280: aload 8
    //   282: invokeinterface 70 3 0
    //   287: pop
    //   288: iconst_0
    //   289: invokestatic 16	net/youmi/android/a/h/b/a/f:a	(I)Lorg/json/JSONObject;
    //   292: astore_1
    //   293: new 55	org/json/JSONObject
    //   296: dup
    //   297: invokespecial 71	org/json/JSONObject:<init>	()V
    //   300: astore_2
    //   301: aload_2
    //   302: ldc 22
    //   304: iconst_1
    //   305: invokevirtual 75	org/json/JSONObject:put	(Ljava/lang/String;I)Lorg/json/JSONObject;
    //   308: pop
    //   309: aload_1
    //   310: ldc 34
    //   312: aload_2
    //   313: invokevirtual 78	org/json/JSONObject:put	(Ljava/lang/String;Ljava/lang/Object;)Lorg/json/JSONObject;
    //   316: pop
    //   317: aload_1
    //   318: areturn
    //   319: astore_1
    //   320: aconst_null
    //   321: areturn
    //   322: iconst_0
    //   323: invokestatic 16	net/youmi/android/a/h/b/a/f:a	(I)Lorg/json/JSONObject;
    //   326: astore_3
    //   327: new 55	org/json/JSONObject
    //   330: dup
    //   331: invokespecial 71	org/json/JSONObject:<init>	()V
    //   334: astore 9
    //   336: aload 9
    //   338: ldc 22
    //   340: iconst_0
    //   341: invokevirtual 75	org/json/JSONObject:put	(Ljava/lang/String;I)Lorg/json/JSONObject;
    //   344: pop
    //   345: aload_3
    //   346: ldc 34
    //   348: aload 9
    //   350: invokevirtual 78	org/json/JSONObject:put	(Ljava/lang/String;Ljava/lang/Object;)Lorg/json/JSONObject;
    //   353: pop
    //   354: aload_3
    //   355: areturn
    //   356: iconst_0
    //   357: invokestatic 16	net/youmi/android/a/h/b/a/f:a	(I)Lorg/json/JSONObject;
    //   360: astore_1
    //   361: new 55	org/json/JSONObject
    //   364: dup
    //   365: invokespecial 71	org/json/JSONObject:<init>	()V
    //   368: astore_2
    //   369: aload_2
    //   370: ldc 22
    //   372: iconst_0
    //   373: invokevirtual 75	org/json/JSONObject:put	(Ljava/lang/String;I)Lorg/json/JSONObject;
    //   376: pop
    //   377: aload_1
    //   378: ldc 34
    //   380: aload_2
    //   381: invokevirtual 78	org/json/JSONObject:put	(Ljava/lang/String;Ljava/lang/Object;)Lorg/json/JSONObject;
    //   384: pop
    //   385: aload_1
    //   386: areturn
    //   387: iload 4
    //   389: iconst_1
    //   390: if_icmpne +98 -> 488
    //   393: aload_2
    //   394: aload 7
    //   396: iload 5
    //   398: invokestatic 83	net/youmi/android/c/k/f:a	(Landroid/content/Context;Ljava/lang/String;I)Z
    //   401: istore 6
    //   403: iload 6
    //   405: ifeq +52 -> 457
    //   408: aload 8
    //   410: invokevirtual 67	net/youmi/android/a/h/j:e	()Z
    //   413: ifeq +13 -> 426
    //   416: aload_1
    //   417: iconst_4
    //   418: aload 8
    //   420: invokeinterface 70 3 0
    //   425: pop
    //   426: iconst_0
    //   427: invokestatic 16	net/youmi/android/a/h/b/a/f:a	(I)Lorg/json/JSONObject;
    //   430: astore_1
    //   431: new 55	org/json/JSONObject
    //   434: dup
    //   435: invokespecial 71	org/json/JSONObject:<init>	()V
    //   438: astore_2
    //   439: aload_2
    //   440: ldc 22
    //   442: iconst_1
    //   443: invokevirtual 75	org/json/JSONObject:put	(Ljava/lang/String;I)Lorg/json/JSONObject;
    //   446: pop
    //   447: aload_1
    //   448: ldc 34
    //   450: aload_2
    //   451: invokevirtual 78	org/json/JSONObject:put	(Ljava/lang/String;Ljava/lang/Object;)Lorg/json/JSONObject;
    //   454: pop
    //   455: aload_1
    //   456: areturn
    //   457: iconst_0
    //   458: invokestatic 16	net/youmi/android/a/h/b/a/f:a	(I)Lorg/json/JSONObject;
    //   461: astore_1
    //   462: new 55	org/json/JSONObject
    //   465: dup
    //   466: invokespecial 71	org/json/JSONObject:<init>	()V
    //   469: astore_2
    //   470: aload_2
    //   471: ldc 22
    //   473: iconst_0
    //   474: invokevirtual 75	org/json/JSONObject:put	(Ljava/lang/String;I)Lorg/json/JSONObject;
    //   477: pop
    //   478: aload_1
    //   479: ldc 34
    //   481: aload_2
    //   482: invokevirtual 78	org/json/JSONObject:put	(Ljava/lang/String;Ljava/lang/Object;)Lorg/json/JSONObject;
    //   485: pop
    //   486: aload_1
    //   487: areturn
    //   488: iload 4
    //   490: iconst_2
    //   491: if_icmpne -171 -> 320
    //   494: aload_2
    //   495: aload 7
    //   497: iload 5
    //   499: aload_3
    //   500: ldc 44
    //   502: ldc 85
    //   504: invokestatic 27	net/youmi/android/c/b/b:a	(Lorg/json/JSONObject;Ljava/lang/String;Ljava/lang/String;)Ljava/lang/String;
    //   507: invokestatic 88	net/youmi/android/c/k/f:a	(Landroid/content/Context;Ljava/lang/String;ILjava/lang/String;)Z
    //   510: istore 6
    //   512: iload 6
    //   514: ifeq +52 -> 566
    //   517: aload 8
    //   519: invokevirtual 67	net/youmi/android/a/h/j:e	()Z
    //   522: ifeq +13 -> 535
    //   525: aload_1
    //   526: iconst_4
    //   527: aload 8
    //   529: invokeinterface 70 3 0
    //   534: pop
    //   535: iconst_0
    //   536: invokestatic 16	net/youmi/android/a/h/b/a/f:a	(I)Lorg/json/JSONObject;
    //   539: astore_1
    //   540: new 55	org/json/JSONObject
    //   543: dup
    //   544: invokespecial 71	org/json/JSONObject:<init>	()V
    //   547: astore_2
    //   548: aload_2
    //   549: ldc 22
    //   551: iconst_1
    //   552: invokevirtual 75	org/json/JSONObject:put	(Ljava/lang/String;I)Lorg/json/JSONObject;
    //   555: pop
    //   556: aload_1
    //   557: ldc 34
    //   559: aload_2
    //   560: invokevirtual 78	org/json/JSONObject:put	(Ljava/lang/String;Ljava/lang/Object;)Lorg/json/JSONObject;
    //   563: pop
    //   564: aload_1
    //   565: areturn
    //   566: iconst_0
    //   567: invokestatic 16	net/youmi/android/a/h/b/a/f:a	(I)Lorg/json/JSONObject;
    //   570: astore_1
    //   571: new 55	org/json/JSONObject
    //   574: dup
    //   575: invokespecial 71	org/json/JSONObject:<init>	()V
    //   578: astore_2
    //   579: aload_2
    //   580: ldc 22
    //   582: iconst_0
    //   583: invokevirtual 75	org/json/JSONObject:put	(Ljava/lang/String;I)Lorg/json/JSONObject;
    //   586: pop
    //   587: aload_1
    //   588: ldc 34
    //   590: aload_2
    //   591: invokevirtual 78	org/json/JSONObject:put	(Ljava/lang/String;Ljava/lang/Object;)Lorg/json/JSONObject;
    //   594: pop
    //   595: aload_1
    //   596: areturn
    //   597: astore_1
    //   598: goto -63 -> 535
    //   601: astore_1
    //   602: goto -176 -> 426
    //   605: astore_1
    //   606: goto -318 -> 288
    //   609: astore_3
    //   610: goto -390 -> 220
    //   613: astore 9
    //   615: goto -440 -> 175
    // Local variable table:
    //   start	length	slot	name	signature
    //   0	618	0	this	f
    //   0	618	1	parame	net.youmi.android.a.h.e
    //   0	618	2	paramb	net.youmi.android.a.h.b
    //   0	618	3	paramJSONObject	org.json.JSONObject
    //   51	441	4	i	int
    //   82	416	5	j	int
    //   195	318	6	bool	boolean
    //   32	464	7	str1	java.lang.String
    //   91	437	8	localj	net.youmi.android.a.h.j
    //   115	234	9	localObject1	java.lang.Object
    //   613	1	9	localThrowable	java.lang.Throwable
    //   125	32	10	str2	java.lang.String
    //   135	29	11	str3	java.lang.String
    //   100	71	12	localObject2	java.lang.Object
    // Exception table:
    //   from	to	target	type
    //   180	197	254	java/lang/Throwable
    //   220	252	254	java/lang/Throwable
    //   322	354	254	java/lang/Throwable
    //   4	9	319	java/lang/Throwable
    //   9	16	319	java/lang/Throwable
    //   20	25	319	java/lang/Throwable
    //   25	34	319	java/lang/Throwable
    //   39	44	319	java/lang/Throwable
    //   44	53	319	java/lang/Throwable
    //   70	75	319	java/lang/Throwable
    //   75	93	319	java/lang/Throwable
    //   255	265	319	java/lang/Throwable
    //   288	317	319	java/lang/Throwable
    //   356	385	319	java/lang/Throwable
    //   393	403	319	java/lang/Throwable
    //   426	455	319	java/lang/Throwable
    //   457	486	319	java/lang/Throwable
    //   494	512	319	java/lang/Throwable
    //   535	564	319	java/lang/Throwable
    //   566	595	319	java/lang/Throwable
    //   517	535	597	java/lang/Throwable
    //   408	426	601	java/lang/Throwable
    //   270	288	605	java/lang/Throwable
    //   202	220	609	java/lang/Throwable
    //   93	102	613	java/lang/Throwable
    //   107	175	613	java/lang/Throwable
  }
}


/* Location:           C:\Users\guanghui\Desktop\软件安全\361\classes-dex2jar.jar
 * Qualified Name:     net.youmi.android.a.h.b.a.f
 * JD-Core Version:    0.7.0.1
 */