package net.youmi.android.a.a.a;

public class b
{
  /* Error */
  public static java.lang.String a(a parama)
  {
    // Byte code:
    //   0: iconst_0
    //   1: istore_2
    //   2: invokestatic 14	java/lang/System:currentTimeMillis	()J
    //   5: pop2
    //   6: new 16	org/json/JSONObject
    //   9: dup
    //   10: invokespecial 20	org/json/JSONObject:<init>	()V
    //   13: astore_3
    //   14: aload_3
    //   15: ldc 21
    //   17: aload_0
    //   18: invokevirtual 26	net/youmi/android/a/a/a/a:a	()I
    //   21: invokevirtual 30	org/json/JSONObject:put	(Ljava/lang/String;I)Lorg/json/JSONObject;
    //   24: pop
    //   25: aload_3
    //   26: ldc 32
    //   28: aload_0
    //   29: invokevirtual 34	net/youmi/android/a/a/a/a:b	()I
    //   32: invokevirtual 30	org/json/JSONObject:put	(Ljava/lang/String;I)Lorg/json/JSONObject;
    //   35: pop
    //   36: aload_3
    //   37: ldc 36
    //   39: aload_0
    //   40: invokevirtual 38	net/youmi/android/a/a/a/a:c	()J
    //   43: invokevirtual 41	org/json/JSONObject:put	(Ljava/lang/String;J)Lorg/json/JSONObject;
    //   46: pop
    //   47: aload_0
    //   48: invokevirtual 45	net/youmi/android/a/a/a/a:g	()Lnet/youmi/android/a/a/a/g;
    //   51: astore 4
    //   53: aload 4
    //   55: ifnull +137 -> 192
    //   58: aload 4
    //   60: invokevirtual 50	net/youmi/android/a/a/a/g:b	()Ljava/lang/String;
    //   63: ifnull +15 -> 78
    //   66: aload_3
    //   67: ldc 52
    //   69: aload 4
    //   71: invokevirtual 50	net/youmi/android/a/a/a/g:b	()Ljava/lang/String;
    //   74: invokevirtual 55	org/json/JSONObject:put	(Ljava/lang/String;Ljava/lang/Object;)Lorg/json/JSONObject;
    //   77: pop
    //   78: aload 4
    //   80: invokevirtual 57	net/youmi/android/a/a/a/g:c	()Ljava/lang/String;
    //   83: ifnull +15 -> 98
    //   86: aload_3
    //   87: ldc 59
    //   89: aload 4
    //   91: invokevirtual 57	net/youmi/android/a/a/a/g:c	()Ljava/lang/String;
    //   94: invokevirtual 55	org/json/JSONObject:put	(Ljava/lang/String;Ljava/lang/Object;)Lorg/json/JSONObject;
    //   97: pop
    //   98: aload 4
    //   100: invokevirtual 62	net/youmi/android/a/a/a/g:f	()Ljava/lang/String;
    //   103: ifnull +15 -> 118
    //   106: aload_3
    //   107: ldc 64
    //   109: aload 4
    //   111: invokevirtual 62	net/youmi/android/a/a/a/g:f	()Ljava/lang/String;
    //   114: invokevirtual 55	org/json/JSONObject:put	(Ljava/lang/String;Ljava/lang/Object;)Lorg/json/JSONObject;
    //   117: pop
    //   118: aload 4
    //   120: invokevirtual 67	net/youmi/android/a/a/a/g:d	()Ljava/lang/String;
    //   123: ifnull +15 -> 138
    //   126: aload_3
    //   127: ldc 69
    //   129: aload 4
    //   131: invokevirtual 67	net/youmi/android/a/a/a/g:d	()Ljava/lang/String;
    //   134: invokevirtual 55	org/json/JSONObject:put	(Ljava/lang/String;Ljava/lang/Object;)Lorg/json/JSONObject;
    //   137: pop
    //   138: aload 4
    //   140: invokevirtual 72	net/youmi/android/a/a/a/g:e	()Ljava/lang/String;
    //   143: ifnull +15 -> 158
    //   146: aload_3
    //   147: ldc 74
    //   149: aload 4
    //   151: invokevirtual 72	net/youmi/android/a/a/a/g:e	()Ljava/lang/String;
    //   154: invokevirtual 55	org/json/JSONObject:put	(Ljava/lang/String;Ljava/lang/Object;)Lorg/json/JSONObject;
    //   157: pop
    //   158: aload_3
    //   159: ldc 76
    //   161: aload 4
    //   163: invokevirtual 78	net/youmi/android/a/a/a/g:g	()I
    //   166: invokevirtual 30	org/json/JSONObject:put	(Ljava/lang/String;I)Lorg/json/JSONObject;
    //   169: pop
    //   170: aload 4
    //   172: invokevirtual 80	net/youmi/android/a/a/a/g:a	()J
    //   175: lconst_0
    //   176: lcmp
    //   177: iflt +15 -> 192
    //   180: aload_3
    //   181: ldc 82
    //   183: aload 4
    //   185: invokevirtual 80	net/youmi/android/a/a/a/g:a	()J
    //   188: invokevirtual 41	org/json/JSONObject:put	(Ljava/lang/String;J)Lorg/json/JSONObject;
    //   191: pop
    //   192: aload_0
    //   193: invokevirtual 85	net/youmi/android/a/a/a/a:f	()Lnet/youmi/android/a/a/a/c;
    //   196: astore 4
    //   198: aload 4
    //   200: ifnull +251 -> 451
    //   203: aload 4
    //   205: invokevirtual 88	net/youmi/android/a/a/a/c:f	()Ljava/lang/String;
    //   208: ifnull +15 -> 223
    //   211: aload_3
    //   212: ldc 90
    //   214: aload 4
    //   216: invokevirtual 88	net/youmi/android/a/a/a/c:f	()Ljava/lang/String;
    //   219: invokevirtual 55	org/json/JSONObject:put	(Ljava/lang/String;Ljava/lang/Object;)Lorg/json/JSONObject;
    //   222: pop
    //   223: aload 4
    //   225: invokevirtual 91	net/youmi/android/a/a/a/c:e	()Ljava/lang/String;
    //   228: ifnull +15 -> 243
    //   231: aload_3
    //   232: ldc 93
    //   234: aload 4
    //   236: invokevirtual 91	net/youmi/android/a/a/a/c:e	()Ljava/lang/String;
    //   239: invokevirtual 55	org/json/JSONObject:put	(Ljava/lang/String;Ljava/lang/Object;)Lorg/json/JSONObject;
    //   242: pop
    //   243: aload 4
    //   245: invokevirtual 94	net/youmi/android/a/a/a/c:c	()Ljava/lang/String;
    //   248: ifnull +15 -> 263
    //   251: aload_3
    //   252: ldc 96
    //   254: aload 4
    //   256: invokevirtual 94	net/youmi/android/a/a/a/c:c	()Ljava/lang/String;
    //   259: invokevirtual 55	org/json/JSONObject:put	(Ljava/lang/String;Ljava/lang/Object;)Lorg/json/JSONObject;
    //   262: pop
    //   263: aload 4
    //   265: invokevirtual 98	net/youmi/android/a/a/a/c:g	()Ljava/lang/String;
    //   268: ifnull +15 -> 283
    //   271: aload_3
    //   272: ldc 100
    //   274: aload 4
    //   276: invokevirtual 98	net/youmi/android/a/a/a/c:g	()Ljava/lang/String;
    //   279: invokevirtual 55	org/json/JSONObject:put	(Ljava/lang/String;Ljava/lang/Object;)Lorg/json/JSONObject;
    //   282: pop
    //   283: aload 4
    //   285: invokevirtual 101	net/youmi/android/a/a/a/c:b	()Ljava/lang/String;
    //   288: ifnull +15 -> 303
    //   291: aload_3
    //   292: ldc 103
    //   294: aload 4
    //   296: invokevirtual 101	net/youmi/android/a/a/a/c:b	()Ljava/lang/String;
    //   299: invokevirtual 55	org/json/JSONObject:put	(Ljava/lang/String;Ljava/lang/Object;)Lorg/json/JSONObject;
    //   302: pop
    //   303: aload 4
    //   305: invokevirtual 104	net/youmi/android/a/a/a/c:d	()Ljava/lang/String;
    //   308: ifnull +15 -> 323
    //   311: aload_3
    //   312: ldc 106
    //   314: aload 4
    //   316: invokevirtual 104	net/youmi/android/a/a/a/c:d	()Ljava/lang/String;
    //   319: invokevirtual 55	org/json/JSONObject:put	(Ljava/lang/String;Ljava/lang/Object;)Lorg/json/JSONObject;
    //   322: pop
    //   323: aload 4
    //   325: invokevirtual 109	net/youmi/android/a/a/a/c:h	()Ljava/lang/String;
    //   328: ifnull +15 -> 343
    //   331: aload_3
    //   332: ldc 111
    //   334: aload 4
    //   336: invokevirtual 109	net/youmi/android/a/a/a/c:h	()Ljava/lang/String;
    //   339: invokevirtual 55	org/json/JSONObject:put	(Ljava/lang/String;Ljava/lang/Object;)Lorg/json/JSONObject;
    //   342: pop
    //   343: aload 4
    //   345: invokevirtual 114	net/youmi/android/a/a/a/c:i	()Ljava/lang/String;
    //   348: ifnull +15 -> 363
    //   351: aload_3
    //   352: ldc 116
    //   354: aload 4
    //   356: invokevirtual 114	net/youmi/android/a/a/a/c:i	()Ljava/lang/String;
    //   359: invokevirtual 55	org/json/JSONObject:put	(Ljava/lang/String;Ljava/lang/Object;)Lorg/json/JSONObject;
    //   362: pop
    //   363: aload_3
    //   364: ldc 118
    //   366: aload 4
    //   368: invokevirtual 121	net/youmi/android/a/a/a/c:j	()J
    //   371: invokevirtual 41	org/json/JSONObject:put	(Ljava/lang/String;J)Lorg/json/JSONObject;
    //   374: pop
    //   375: aload 4
    //   377: invokevirtual 124	net/youmi/android/a/a/a/c:a	()Ljava/util/ArrayList;
    //   380: astore 4
    //   382: aload 4
    //   384: ifnull +67 -> 451
    //   387: aload 4
    //   389: invokevirtual 129	java/util/ArrayList:size	()I
    //   392: ifle +59 -> 451
    //   395: new 131	org/json/JSONArray
    //   398: dup
    //   399: invokespecial 132	org/json/JSONArray:<init>	()V
    //   402: astore 5
    //   404: iconst_0
    //   405: istore_1
    //   406: iload_1
    //   407: aload 4
    //   409: invokevirtual 129	java/util/ArrayList:size	()I
    //   412: if_icmpge +30 -> 442
    //   415: aload 4
    //   417: iload_1
    //   418: invokevirtual 136	java/util/ArrayList:get	(I)Ljava/lang/Object;
    //   421: checkcast 138	java/lang/String
    //   424: astore 6
    //   426: aload 6
    //   428: ifnull +374 -> 802
    //   431: aload 5
    //   433: aload 6
    //   435: invokevirtual 141	org/json/JSONArray:put	(Ljava/lang/Object;)Lorg/json/JSONArray;
    //   438: pop
    //   439: goto +363 -> 802
    //   442: aload_3
    //   443: ldc 143
    //   445: aload 5
    //   447: invokevirtual 55	org/json/JSONObject:put	(Ljava/lang/String;Ljava/lang/Object;)Lorg/json/JSONObject;
    //   450: pop
    //   451: aload_0
    //   452: invokevirtual 147	net/youmi/android/a/a/a/a:l	()Lnet/youmi/android/a/a/a/d;
    //   455: astore 4
    //   457: aload 4
    //   459: ifnull +79 -> 538
    //   462: aload 4
    //   464: invokevirtual 150	net/youmi/android/a/a/a/d:d	()Ljava/lang/String;
    //   467: ifnull +15 -> 482
    //   470: aload_3
    //   471: ldc 152
    //   473: aload 4
    //   475: invokevirtual 150	net/youmi/android/a/a/a/d:d	()Ljava/lang/String;
    //   478: invokevirtual 55	org/json/JSONObject:put	(Ljava/lang/String;Ljava/lang/Object;)Lorg/json/JSONObject;
    //   481: pop
    //   482: aload_3
    //   483: ldc 154
    //   485: aload 4
    //   487: invokevirtual 156	net/youmi/android/a/a/a/d:e	()I
    //   490: invokevirtual 30	org/json/JSONObject:put	(Ljava/lang/String;I)Lorg/json/JSONObject;
    //   493: pop
    //   494: aload 4
    //   496: invokevirtual 157	net/youmi/android/a/a/a/d:c	()Ljava/lang/String;
    //   499: ifnull +15 -> 514
    //   502: aload_3
    //   503: ldc 159
    //   505: aload 4
    //   507: invokevirtual 157	net/youmi/android/a/a/a/d:c	()Ljava/lang/String;
    //   510: invokevirtual 55	org/json/JSONObject:put	(Ljava/lang/String;Ljava/lang/Object;)Lorg/json/JSONObject;
    //   513: pop
    //   514: aload_3
    //   515: ldc 161
    //   517: aload 4
    //   519: invokevirtual 162	net/youmi/android/a/a/a/d:b	()I
    //   522: invokevirtual 30	org/json/JSONObject:put	(Ljava/lang/String;I)Lorg/json/JSONObject;
    //   525: pop
    //   526: aload_3
    //   527: ldc 164
    //   529: aload 4
    //   531: invokevirtual 165	net/youmi/android/a/a/a/d:a	()J
    //   534: invokevirtual 41	org/json/JSONObject:put	(Ljava/lang/String;J)Lorg/json/JSONObject;
    //   537: pop
    //   538: aload_0
    //   539: invokevirtual 169	net/youmi/android/a/a/a/a:k	()Lnet/youmi/android/a/a/a/e;
    //   542: astore 4
    //   544: aload 4
    //   546: ifnull +47 -> 593
    //   549: aload 4
    //   551: invokevirtual 172	net/youmi/android/a/a/a/e:c	()Ljava/lang/String;
    //   554: ifnull +15 -> 569
    //   557: aload_3
    //   558: ldc 174
    //   560: aload 4
    //   562: invokevirtual 172	net/youmi/android/a/a/a/e:c	()Ljava/lang/String;
    //   565: invokevirtual 55	org/json/JSONObject:put	(Ljava/lang/String;Ljava/lang/Object;)Lorg/json/JSONObject;
    //   568: pop
    //   569: aload_3
    //   570: ldc 176
    //   572: aload 4
    //   574: invokevirtual 178	net/youmi/android/a/a/a/e:b	()J
    //   577: invokevirtual 41	org/json/JSONObject:put	(Ljava/lang/String;J)Lorg/json/JSONObject;
    //   580: pop
    //   581: aload_3
    //   582: ldc 180
    //   584: aload 4
    //   586: invokevirtual 181	net/youmi/android/a/a/a/e:a	()J
    //   589: invokevirtual 41	org/json/JSONObject:put	(Ljava/lang/String;J)Lorg/json/JSONObject;
    //   592: pop
    //   593: aload_0
    //   594: invokevirtual 185	net/youmi/android/a/a/a/a:n	()Lnet/youmi/android/a/a/a/h;
    //   597: astore 4
    //   599: aload 4
    //   601: ifnull +27 -> 628
    //   604: aload_3
    //   605: ldc 187
    //   607: aload 4
    //   609: invokevirtual 190	net/youmi/android/a/a/a/h:b	()I
    //   612: invokevirtual 30	org/json/JSONObject:put	(Ljava/lang/String;I)Lorg/json/JSONObject;
    //   615: pop
    //   616: aload_3
    //   617: ldc 192
    //   619: aload 4
    //   621: invokevirtual 193	net/youmi/android/a/a/a/h:a	()J
    //   624: invokevirtual 41	org/json/JSONObject:put	(Ljava/lang/String;J)Lorg/json/JSONObject;
    //   627: pop
    //   628: aload_0
    //   629: invokevirtual 197	net/youmi/android/a/a/a/a:m	()Lnet/youmi/android/a/a/a/j;
    //   632: astore_0
    //   633: aload_0
    //   634: ifnull +146 -> 780
    //   637: aload_3
    //   638: ldc 199
    //   640: aload_0
    //   641: invokevirtual 202	net/youmi/android/a/a/a/j:a	()J
    //   644: invokevirtual 41	org/json/JSONObject:put	(Ljava/lang/String;J)Lorg/json/JSONObject;
    //   647: pop
    //   648: aload_0
    //   649: invokevirtual 205	net/youmi/android/a/a/a/j:b	()Ljava/util/List;
    //   652: astore_0
    //   653: aload_0
    //   654: ifnull +126 -> 780
    //   657: aload_0
    //   658: invokeinterface 208 1 0
    //   663: ifle +117 -> 780
    //   666: new 131	org/json/JSONArray
    //   669: dup
    //   670: invokespecial 132	org/json/JSONArray:<init>	()V
    //   673: astore 4
    //   675: iload_2
    //   676: istore_1
    //   677: iload_1
    //   678: aload_0
    //   679: invokeinterface 208 1 0
    //   684: if_icmpge +79 -> 763
    //   687: aload_0
    //   688: iload_1
    //   689: invokeinterface 209 2 0
    //   694: checkcast 211	net/youmi/android/a/a/a/i
    //   697: astore 5
    //   699: aload 5
    //   701: ifnull +108 -> 809
    //   704: new 16	org/json/JSONObject
    //   707: dup
    //   708: invokespecial 20	org/json/JSONObject:<init>	()V
    //   711: astore 6
    //   713: aload 6
    //   715: ldc 213
    //   717: aload 5
    //   719: invokevirtual 215	net/youmi/android/a/a/a/i:a	()Ljava/lang/String;
    //   722: invokevirtual 55	org/json/JSONObject:put	(Ljava/lang/String;Ljava/lang/Object;)Lorg/json/JSONObject;
    //   725: pop
    //   726: aload 6
    //   728: ldc 217
    //   730: aload 5
    //   732: invokevirtual 218	net/youmi/android/a/a/a/i:b	()I
    //   735: invokevirtual 30	org/json/JSONObject:put	(Ljava/lang/String;I)Lorg/json/JSONObject;
    //   738: pop
    //   739: aload 6
    //   741: ldc 220
    //   743: aload 5
    //   745: invokevirtual 222	net/youmi/android/a/a/a/i:c	()I
    //   748: invokevirtual 30	org/json/JSONObject:put	(Ljava/lang/String;I)Lorg/json/JSONObject;
    //   751: pop
    //   752: aload 4
    //   754: aload 6
    //   756: invokevirtual 141	org/json/JSONArray:put	(Ljava/lang/Object;)Lorg/json/JSONArray;
    //   759: pop
    //   760: goto +49 -> 809
    //   763: aload 4
    //   765: invokevirtual 225	org/json/JSONArray:length	()I
    //   768: ifle +12 -> 780
    //   771: aload_3
    //   772: ldc 227
    //   774: aload 4
    //   776: invokevirtual 55	org/json/JSONObject:put	(Ljava/lang/String;Ljava/lang/Object;)Lorg/json/JSONObject;
    //   779: pop
    //   780: aload_3
    //   781: invokevirtual 230	org/json/JSONObject:toString	()Ljava/lang/String;
    //   784: astore_0
    //   785: aload_0
    //   786: areturn
    //   787: astore_0
    //   788: aload_0
    //   789: athrow
    //   790: astore_0
    //   791: aconst_null
    //   792: areturn
    //   793: astore_0
    //   794: goto -14 -> 780
    //   797: astore 4
    //   799: goto -348 -> 451
    //   802: iload_1
    //   803: iconst_1
    //   804: iadd
    //   805: istore_1
    //   806: goto -400 -> 406
    //   809: iload_1
    //   810: iconst_1
    //   811: iadd
    //   812: istore_1
    //   813: goto -136 -> 677
    // Local variable table:
    //   start	length	slot	name	signature
    //   0	816	0	parama	a
    //   405	408	1	i	int
    //   1	675	2	j	int
    //   13	768	3	localJSONObject	org.json.JSONObject
    //   51	724	4	localObject1	Object
    //   797	1	4	localThrowable	java.lang.Throwable
    //   402	342	5	localObject2	Object
    //   424	331	6	localObject3	Object
    // Exception table:
    //   from	to	target	type
    //   6	53	787	finally
    //   58	78	787	finally
    //   78	98	787	finally
    //   98	118	787	finally
    //   118	138	787	finally
    //   138	158	787	finally
    //   158	192	787	finally
    //   192	198	787	finally
    //   203	223	787	finally
    //   223	243	787	finally
    //   243	263	787	finally
    //   263	283	787	finally
    //   283	303	787	finally
    //   303	323	787	finally
    //   323	343	787	finally
    //   343	363	787	finally
    //   363	375	787	finally
    //   375	382	787	finally
    //   387	404	787	finally
    //   406	426	787	finally
    //   431	439	787	finally
    //   442	451	787	finally
    //   451	457	787	finally
    //   462	482	787	finally
    //   482	514	787	finally
    //   514	538	787	finally
    //   538	544	787	finally
    //   549	569	787	finally
    //   569	593	787	finally
    //   593	599	787	finally
    //   604	628	787	finally
    //   628	633	787	finally
    //   637	653	787	finally
    //   657	675	787	finally
    //   677	699	787	finally
    //   704	760	787	finally
    //   763	780	787	finally
    //   780	785	787	finally
    //   6	53	790	java/lang/Throwable
    //   58	78	790	java/lang/Throwable
    //   78	98	790	java/lang/Throwable
    //   98	118	790	java/lang/Throwable
    //   118	138	790	java/lang/Throwable
    //   138	158	790	java/lang/Throwable
    //   158	192	790	java/lang/Throwable
    //   192	198	790	java/lang/Throwable
    //   203	223	790	java/lang/Throwable
    //   223	243	790	java/lang/Throwable
    //   243	263	790	java/lang/Throwable
    //   263	283	790	java/lang/Throwable
    //   283	303	790	java/lang/Throwable
    //   303	323	790	java/lang/Throwable
    //   323	343	790	java/lang/Throwable
    //   343	363	790	java/lang/Throwable
    //   363	375	790	java/lang/Throwable
    //   451	457	790	java/lang/Throwable
    //   462	482	790	java/lang/Throwable
    //   482	514	790	java/lang/Throwable
    //   514	538	790	java/lang/Throwable
    //   538	544	790	java/lang/Throwable
    //   549	569	790	java/lang/Throwable
    //   569	593	790	java/lang/Throwable
    //   593	599	790	java/lang/Throwable
    //   604	628	790	java/lang/Throwable
    //   780	785	790	java/lang/Throwable
    //   628	633	793	java/lang/Throwable
    //   637	653	793	java/lang/Throwable
    //   657	675	793	java/lang/Throwable
    //   677	699	793	java/lang/Throwable
    //   704	760	793	java/lang/Throwable
    //   763	780	793	java/lang/Throwable
    //   375	382	797	java/lang/Throwable
    //   387	404	797	java/lang/Throwable
    //   406	426	797	java/lang/Throwable
    //   431	439	797	java/lang/Throwable
    //   442	451	797	java/lang/Throwable
  }
  
  /* Error */
  public static boolean a(a parama, java.lang.String paramString)
  {
    // Byte code:
    //   0: invokestatic 14	java/lang/System:currentTimeMillis	()J
    //   3: pop2
    //   4: aload_1
    //   5: ifnonnull +5 -> 10
    //   8: iconst_0
    //   9: ireturn
    //   10: aload_1
    //   11: invokestatic 237	net/youmi/android/c/b/b:a	(Ljava/lang/String;)Lorg/json/JSONObject;
    //   14: astore_1
    //   15: aload_1
    //   16: ifnonnull +5 -> 21
    //   19: iconst_0
    //   20: ireturn
    //   21: aload_1
    //   22: ldc 21
    //   24: iconst_m1
    //   25: invokestatic 240	net/youmi/android/c/b/b:a	(Lorg/json/JSONObject;Ljava/lang/String;I)I
    //   28: istore_2
    //   29: aload_1
    //   30: ldc 32
    //   32: iconst_m1
    //   33: invokestatic 240	net/youmi/android/c/b/b:a	(Lorg/json/JSONObject;Ljava/lang/String;I)I
    //   36: istore_3
    //   37: iload_2
    //   38: iflt +7 -> 45
    //   41: iload_3
    //   42: ifge +5 -> 47
    //   45: iconst_0
    //   46: ireturn
    //   47: aload_0
    //   48: aload_1
    //   49: ldc 36
    //   51: lconst_0
    //   52: invokestatic 243	net/youmi/android/c/b/b:a	(Lorg/json/JSONObject;Ljava/lang/String;J)J
    //   55: invokevirtual 246	net/youmi/android/a/a/a/a:a	(J)V
    //   58: aload_1
    //   59: ldc 52
    //   61: aconst_null
    //   62: invokestatic 249	net/youmi/android/c/b/b:a	(Lorg/json/JSONObject;Ljava/lang/String;Ljava/lang/String;)Ljava/lang/String;
    //   65: astore 9
    //   67: aload_1
    //   68: ldc 64
    //   70: aconst_null
    //   71: invokestatic 249	net/youmi/android/c/b/b:a	(Lorg/json/JSONObject;Ljava/lang/String;Ljava/lang/String;)Ljava/lang/String;
    //   74: astore 10
    //   76: aload_1
    //   77: ldc 69
    //   79: aconst_null
    //   80: invokestatic 249	net/youmi/android/c/b/b:a	(Lorg/json/JSONObject;Ljava/lang/String;Ljava/lang/String;)Ljava/lang/String;
    //   83: astore 11
    //   85: aload_1
    //   86: ldc 59
    //   88: aconst_null
    //   89: invokestatic 249	net/youmi/android/c/b/b:a	(Lorg/json/JSONObject;Ljava/lang/String;Ljava/lang/String;)Ljava/lang/String;
    //   92: astore 12
    //   94: aload_1
    //   95: ldc 74
    //   97: aconst_null
    //   98: invokestatic 249	net/youmi/android/c/b/b:a	(Lorg/json/JSONObject;Ljava/lang/String;Ljava/lang/String;)Ljava/lang/String;
    //   101: astore 13
    //   103: aload_1
    //   104: ldc 76
    //   106: iconst_0
    //   107: invokestatic 240	net/youmi/android/c/b/b:a	(Lorg/json/JSONObject;Ljava/lang/String;I)I
    //   110: istore_2
    //   111: aload_1
    //   112: ldc 82
    //   114: lconst_0
    //   115: invokestatic 243	net/youmi/android/c/b/b:a	(Lorg/json/JSONObject;Ljava/lang/String;J)J
    //   118: lstore 5
    //   120: aload 9
    //   122: ifnonnull +27 -> 149
    //   125: aload 11
    //   127: ifnonnull +22 -> 149
    //   130: aload 12
    //   132: ifnonnull +17 -> 149
    //   135: aload 13
    //   137: ifnonnull +12 -> 149
    //   140: aload 10
    //   142: ifnonnull +7 -> 149
    //   145: iload_2
    //   146: ifle +66 -> 212
    //   149: new 47	net/youmi/android/a/a/a/g
    //   152: dup
    //   153: invokespecial 250	net/youmi/android/a/a/a/g:<init>	()V
    //   156: astore 14
    //   158: aload 14
    //   160: aload 9
    //   162: invokevirtual 253	net/youmi/android/a/a/a/g:a	(Ljava/lang/String;)V
    //   165: aload 14
    //   167: aload 10
    //   169: invokevirtual 255	net/youmi/android/a/a/a/g:e	(Ljava/lang/String;)V
    //   172: aload 14
    //   174: aload 11
    //   176: invokevirtual 257	net/youmi/android/a/a/a/g:c	(Ljava/lang/String;)V
    //   179: aload 14
    //   181: aload 12
    //   183: invokevirtual 259	net/youmi/android/a/a/a/g:b	(Ljava/lang/String;)V
    //   186: aload 14
    //   188: aload 13
    //   190: invokevirtual 261	net/youmi/android/a/a/a/g:d	(Ljava/lang/String;)V
    //   193: aload 14
    //   195: lload 5
    //   197: invokevirtual 262	net/youmi/android/a/a/a/g:a	(J)V
    //   200: aload 14
    //   202: iload_2
    //   203: invokevirtual 265	net/youmi/android/a/a/a/g:a	(I)V
    //   206: aload_0
    //   207: aload 14
    //   209: invokevirtual 268	net/youmi/android/a/a/a/a:a	(Lnet/youmi/android/a/a/a/g;)V
    //   212: aload_1
    //   213: ldc 90
    //   215: aconst_null
    //   216: invokestatic 249	net/youmi/android/c/b/b:a	(Lorg/json/JSONObject;Ljava/lang/String;Ljava/lang/String;)Ljava/lang/String;
    //   219: astore 11
    //   221: aload_1
    //   222: ldc 93
    //   224: aconst_null
    //   225: invokestatic 249	net/youmi/android/c/b/b:a	(Lorg/json/JSONObject;Ljava/lang/String;Ljava/lang/String;)Ljava/lang/String;
    //   228: astore 12
    //   230: aload_1
    //   231: ldc 96
    //   233: aconst_null
    //   234: invokestatic 249	net/youmi/android/c/b/b:a	(Lorg/json/JSONObject;Ljava/lang/String;Ljava/lang/String;)Ljava/lang/String;
    //   237: astore 13
    //   239: aload_1
    //   240: ldc 100
    //   242: aconst_null
    //   243: invokestatic 249	net/youmi/android/c/b/b:a	(Lorg/json/JSONObject;Ljava/lang/String;Ljava/lang/String;)Ljava/lang/String;
    //   246: astore 14
    //   248: aload_1
    //   249: ldc 103
    //   251: aconst_null
    //   252: invokestatic 249	net/youmi/android/c/b/b:a	(Lorg/json/JSONObject;Ljava/lang/String;Ljava/lang/String;)Ljava/lang/String;
    //   255: astore 15
    //   257: aload_1
    //   258: ldc 106
    //   260: aconst_null
    //   261: invokestatic 249	net/youmi/android/c/b/b:a	(Lorg/json/JSONObject;Ljava/lang/String;Ljava/lang/String;)Ljava/lang/String;
    //   264: astore 16
    //   266: aload_1
    //   267: ldc 111
    //   269: aconst_null
    //   270: invokestatic 249	net/youmi/android/c/b/b:a	(Lorg/json/JSONObject;Ljava/lang/String;Ljava/lang/String;)Ljava/lang/String;
    //   273: astore 17
    //   275: aload_1
    //   276: ldc 118
    //   278: lconst_0
    //   279: invokestatic 243	net/youmi/android/c/b/b:a	(Lorg/json/JSONObject;Ljava/lang/String;J)J
    //   282: lstore 5
    //   284: aload_1
    //   285: ldc 116
    //   287: aconst_null
    //   288: invokestatic 249	net/youmi/android/c/b/b:a	(Lorg/json/JSONObject;Ljava/lang/String;Ljava/lang/String;)Ljava/lang/String;
    //   291: astore 18
    //   293: aload_1
    //   294: ldc 143
    //   296: aconst_null
    //   297: invokestatic 271	net/youmi/android/c/b/b:a	(Lorg/json/JSONObject;Ljava/lang/String;Lorg/json/JSONArray;)Lorg/json/JSONArray;
    //   300: astore 9
    //   302: aload 11
    //   304: ifnonnull +51 -> 355
    //   307: aload 12
    //   309: ifnonnull +46 -> 355
    //   312: aload 13
    //   314: ifnonnull +41 -> 355
    //   317: aload 14
    //   319: ifnonnull +36 -> 355
    //   322: aload 15
    //   324: ifnonnull +31 -> 355
    //   327: aload 16
    //   329: ifnonnull +26 -> 355
    //   332: aload 17
    //   334: ifnonnull +21 -> 355
    //   337: aload 18
    //   339: ifnonnull +16 -> 355
    //   342: aload 9
    //   344: ifnull +137 -> 481
    //   347: aload 9
    //   349: invokevirtual 225	org/json/JSONArray:length	()I
    //   352: ifle +129 -> 481
    //   355: new 87	net/youmi/android/a/a/a/c
    //   358: dup
    //   359: invokespecial 272	net/youmi/android/a/a/a/c:<init>	()V
    //   362: astore 10
    //   364: aload 10
    //   366: aload 11
    //   368: invokevirtual 274	net/youmi/android/a/a/a/c:f	(Ljava/lang/String;)V
    //   371: aload 10
    //   373: aload 12
    //   375: invokevirtual 275	net/youmi/android/a/a/a/c:e	(Ljava/lang/String;)V
    //   378: aload 10
    //   380: aload 13
    //   382: invokevirtual 276	net/youmi/android/a/a/a/c:c	(Ljava/lang/String;)V
    //   385: aload 10
    //   387: aload 14
    //   389: invokevirtual 278	net/youmi/android/a/a/a/c:g	(Ljava/lang/String;)V
    //   392: aload 10
    //   394: aload 15
    //   396: invokevirtual 279	net/youmi/android/a/a/a/c:b	(Ljava/lang/String;)V
    //   399: aload 10
    //   401: aload 16
    //   403: invokevirtual 280	net/youmi/android/a/a/a/c:d	(Ljava/lang/String;)V
    //   406: aload 10
    //   408: aload 17
    //   410: invokevirtual 282	net/youmi/android/a/a/a/c:h	(Ljava/lang/String;)V
    //   413: aload 10
    //   415: lload 5
    //   417: invokevirtual 283	net/youmi/android/a/a/a/c:a	(J)V
    //   420: aload 10
    //   422: aload 18
    //   424: invokevirtual 285	net/youmi/android/a/a/a/c:i	(Ljava/lang/String;)V
    //   427: aload 9
    //   429: ifnull +46 -> 475
    //   432: aload 9
    //   434: invokevirtual 225	org/json/JSONArray:length	()I
    //   437: ifle +38 -> 475
    //   440: iconst_0
    //   441: istore_2
    //   442: iload_2
    //   443: aload 9
    //   445: invokevirtual 225	org/json/JSONArray:length	()I
    //   448: if_icmpge +27 -> 475
    //   451: aload 9
    //   453: iload_2
    //   454: aconst_null
    //   455: invokestatic 288	net/youmi/android/c/b/b:a	(Lorg/json/JSONArray;ILjava/lang/String;)Ljava/lang/String;
    //   458: astore 11
    //   460: aload 11
    //   462: ifnull +413 -> 875
    //   465: aload 10
    //   467: aload 11
    //   469: invokevirtual 289	net/youmi/android/a/a/a/c:a	(Ljava/lang/String;)V
    //   472: goto +403 -> 875
    //   475: aload_0
    //   476: aload 10
    //   478: invokevirtual 292	net/youmi/android/a/a/a/a:a	(Lnet/youmi/android/a/a/a/c;)V
    //   481: aload_1
    //   482: ldc 159
    //   484: aconst_null
    //   485: invokestatic 249	net/youmi/android/c/b/b:a	(Lorg/json/JSONObject;Ljava/lang/String;Ljava/lang/String;)Ljava/lang/String;
    //   488: astore 9
    //   490: aload_1
    //   491: ldc 152
    //   493: aconst_null
    //   494: invokestatic 249	net/youmi/android/c/b/b:a	(Lorg/json/JSONObject;Ljava/lang/String;Ljava/lang/String;)Ljava/lang/String;
    //   497: astore 10
    //   499: aload_1
    //   500: ldc 154
    //   502: iconst_0
    //   503: invokestatic 240	net/youmi/android/c/b/b:a	(Lorg/json/JSONObject;Ljava/lang/String;I)I
    //   506: istore_2
    //   507: aload_1
    //   508: ldc 164
    //   510: lconst_0
    //   511: invokestatic 243	net/youmi/android/c/b/b:a	(Lorg/json/JSONObject;Ljava/lang/String;J)J
    //   514: lstore 5
    //   516: aload_1
    //   517: ldc 161
    //   519: iconst_0
    //   520: invokestatic 240	net/youmi/android/c/b/b:a	(Lorg/json/JSONObject;Ljava/lang/String;I)I
    //   523: istore_3
    //   524: aload 9
    //   526: ifnonnull +8 -> 534
    //   529: aload 10
    //   531: ifnull +51 -> 582
    //   534: new 149	net/youmi/android/a/a/a/d
    //   537: dup
    //   538: invokespecial 293	net/youmi/android/a/a/a/d:<init>	()V
    //   541: astore 11
    //   543: aload 11
    //   545: aload 9
    //   547: invokevirtual 294	net/youmi/android/a/a/a/d:a	(Ljava/lang/String;)V
    //   550: aload 11
    //   552: aload 10
    //   554: invokevirtual 295	net/youmi/android/a/a/a/d:b	(Ljava/lang/String;)V
    //   557: aload 11
    //   559: iload_2
    //   560: invokevirtual 297	net/youmi/android/a/a/a/d:b	(I)V
    //   563: aload 11
    //   565: lload 5
    //   567: invokevirtual 298	net/youmi/android/a/a/a/d:a	(J)V
    //   570: aload 11
    //   572: iload_3
    //   573: invokevirtual 299	net/youmi/android/a/a/a/d:a	(I)V
    //   576: aload_0
    //   577: aload 11
    //   579: invokevirtual 302	net/youmi/android/a/a/a/a:a	(Lnet/youmi/android/a/a/a/d;)V
    //   582: aload_1
    //   583: ldc 174
    //   585: aconst_null
    //   586: invokestatic 249	net/youmi/android/c/b/b:a	(Lorg/json/JSONObject;Ljava/lang/String;Ljava/lang/String;)Ljava/lang/String;
    //   589: astore 9
    //   591: aload_1
    //   592: ldc 176
    //   594: lconst_0
    //   595: invokestatic 243	net/youmi/android/c/b/b:a	(Lorg/json/JSONObject;Ljava/lang/String;J)J
    //   598: lstore 5
    //   600: aload_1
    //   601: ldc 180
    //   603: lconst_0
    //   604: invokestatic 243	net/youmi/android/c/b/b:a	(Lorg/json/JSONObject;Ljava/lang/String;J)J
    //   607: lstore 7
    //   609: aload 9
    //   611: ifnonnull +10 -> 621
    //   614: lload 5
    //   616: lconst_0
    //   617: lcmp
    //   618: ifle +39 -> 657
    //   621: new 171	net/youmi/android/a/a/a/e
    //   624: dup
    //   625: invokespecial 303	net/youmi/android/a/a/a/e:<init>	()V
    //   628: astore 10
    //   630: aload 10
    //   632: aload 9
    //   634: invokevirtual 304	net/youmi/android/a/a/a/e:a	(Ljava/lang/String;)V
    //   637: aload 10
    //   639: lload 5
    //   641: invokevirtual 306	net/youmi/android/a/a/a/e:b	(J)V
    //   644: aload 10
    //   646: lload 7
    //   648: invokevirtual 307	net/youmi/android/a/a/a/e:a	(J)V
    //   651: aload_0
    //   652: aload 10
    //   654: invokevirtual 310	net/youmi/android/a/a/a/a:a	(Lnet/youmi/android/a/a/a/e;)V
    //   657: aload_1
    //   658: ldc 187
    //   660: iconst_0
    //   661: invokestatic 240	net/youmi/android/c/b/b:a	(Lorg/json/JSONObject;Ljava/lang/String;I)I
    //   664: istore_2
    //   665: aload_1
    //   666: ldc 192
    //   668: lconst_0
    //   669: invokestatic 243	net/youmi/android/c/b/b:a	(Lorg/json/JSONObject;Ljava/lang/String;J)J
    //   672: lstore 5
    //   674: new 189	net/youmi/android/a/a/a/h
    //   677: dup
    //   678: invokespecial 311	net/youmi/android/a/a/a/h:<init>	()V
    //   681: astore 9
    //   683: aload 9
    //   685: iload_2
    //   686: invokevirtual 312	net/youmi/android/a/a/a/h:a	(I)V
    //   689: aload 9
    //   691: lload 5
    //   693: invokevirtual 313	net/youmi/android/a/a/a/h:a	(J)V
    //   696: aload_0
    //   697: aload 9
    //   699: invokevirtual 316	net/youmi/android/a/a/a/a:a	(Lnet/youmi/android/a/a/a/h;)V
    //   702: aload_1
    //   703: ldc 199
    //   705: lconst_0
    //   706: invokestatic 243	net/youmi/android/c/b/b:a	(Lorg/json/JSONObject;Ljava/lang/String;J)J
    //   709: lstore 5
    //   711: aload_1
    //   712: ldc 227
    //   714: aconst_null
    //   715: invokestatic 271	net/youmi/android/c/b/b:a	(Lorg/json/JSONObject;Ljava/lang/String;Lorg/json/JSONArray;)Lorg/json/JSONArray;
    //   718: astore_1
    //   719: aload_1
    //   720: ifnull +142 -> 862
    //   723: aload_1
    //   724: invokevirtual 225	org/json/JSONArray:length	()I
    //   727: ifle +135 -> 862
    //   730: new 201	net/youmi/android/a/a/a/j
    //   733: dup
    //   734: invokespecial 317	net/youmi/android/a/a/a/j:<init>	()V
    //   737: astore 9
    //   739: aload 9
    //   741: lload 5
    //   743: invokevirtual 318	net/youmi/android/a/a/a/j:a	(J)V
    //   746: aload_0
    //   747: aload 9
    //   749: invokevirtual 321	net/youmi/android/a/a/a/a:a	(Lnet/youmi/android/a/a/a/j;)V
    //   752: aload_1
    //   753: ifnull +109 -> 862
    //   756: iconst_0
    //   757: istore_2
    //   758: iload_2
    //   759: aload_1
    //   760: invokevirtual 225	org/json/JSONArray:length	()I
    //   763: if_icmpge +99 -> 862
    //   766: aload_1
    //   767: iload_2
    //   768: aconst_null
    //   769: invokestatic 324	net/youmi/android/c/b/b:a	(Lorg/json/JSONArray;ILorg/json/JSONObject;)Lorg/json/JSONObject;
    //   772: astore 10
    //   774: aload 10
    //   776: ifnull +79 -> 855
    //   779: aload 10
    //   781: ldc 213
    //   783: aconst_null
    //   784: invokestatic 249	net/youmi/android/c/b/b:a	(Lorg/json/JSONObject;Ljava/lang/String;Ljava/lang/String;)Ljava/lang/String;
    //   787: astore_0
    //   788: aload 10
    //   790: ldc 217
    //   792: iconst_m1
    //   793: invokestatic 240	net/youmi/android/c/b/b:a	(Lorg/json/JSONObject;Ljava/lang/String;I)I
    //   796: istore_3
    //   797: aload 10
    //   799: ldc 220
    //   801: iconst_m1
    //   802: invokestatic 240	net/youmi/android/c/b/b:a	(Lorg/json/JSONObject;Ljava/lang/String;I)I
    //   805: istore 4
    //   807: aload_0
    //   808: ifnonnull +12 -> 820
    //   811: iload_3
    //   812: ifge +8 -> 820
    //   815: iload 4
    //   817: ifle +38 -> 855
    //   820: new 211	net/youmi/android/a/a/a/i
    //   823: dup
    //   824: invokespecial 325	net/youmi/android/a/a/a/i:<init>	()V
    //   827: astore 10
    //   829: aload 10
    //   831: aload_0
    //   832: invokevirtual 326	net/youmi/android/a/a/a/i:a	(Ljava/lang/String;)V
    //   835: aload 10
    //   837: iload_3
    //   838: invokevirtual 327	net/youmi/android/a/a/a/i:a	(I)V
    //   841: aload 10
    //   843: iload 4
    //   845: invokevirtual 328	net/youmi/android/a/a/a/i:b	(I)V
    //   848: aload 9
    //   850: aload 10
    //   852: invokevirtual 331	net/youmi/android/a/a/a/j:a	(Lnet/youmi/android/a/a/a/i;)V
    //   855: iload_2
    //   856: iconst_1
    //   857: iadd
    //   858: istore_2
    //   859: goto -101 -> 758
    //   862: iconst_1
    //   863: ireturn
    //   864: astore_0
    //   865: aload_0
    //   866: athrow
    //   867: astore_0
    //   868: iconst_0
    //   869: ireturn
    //   870: astore 9
    //   872: goto -814 -> 58
    //   875: iload_2
    //   876: iconst_1
    //   877: iadd
    //   878: istore_2
    //   879: goto -437 -> 442
    // Local variable table:
    //   start	length	slot	name	signature
    //   0	882	0	parama	a
    //   0	882	1	paramString	java.lang.String
    //   28	851	2	i	int
    //   36	802	3	j	int
    //   805	39	4	k	int
    //   118	624	5	l1	long
    //   607	40	7	l2	long
    //   65	784	9	localObject1	Object
    //   870	1	9	localThrowable	java.lang.Throwable
    //   74	777	10	localObject2	Object
    //   83	495	11	localObject3	Object
    //   92	282	12	str1	java.lang.String
    //   101	280	13	str2	java.lang.String
    //   156	232	14	localObject4	Object
    //   255	140	15	str3	java.lang.String
    //   264	138	16	str4	java.lang.String
    //   273	136	17	str5	java.lang.String
    //   291	132	18	str6	java.lang.String
    // Exception table:
    //   from	to	target	type
    //   10	15	864	finally
    //   21	37	864	finally
    //   47	58	864	finally
    //   58	120	864	finally
    //   149	212	864	finally
    //   212	302	864	finally
    //   347	355	864	finally
    //   355	427	864	finally
    //   432	440	864	finally
    //   442	460	864	finally
    //   465	472	864	finally
    //   475	481	864	finally
    //   481	524	864	finally
    //   534	582	864	finally
    //   582	609	864	finally
    //   621	657	864	finally
    //   657	719	864	finally
    //   723	752	864	finally
    //   758	774	864	finally
    //   779	807	864	finally
    //   820	855	864	finally
    //   10	15	867	java/lang/Throwable
    //   21	37	867	java/lang/Throwable
    //   58	120	867	java/lang/Throwable
    //   149	212	867	java/lang/Throwable
    //   212	302	867	java/lang/Throwable
    //   347	355	867	java/lang/Throwable
    //   355	427	867	java/lang/Throwable
    //   432	440	867	java/lang/Throwable
    //   442	460	867	java/lang/Throwable
    //   465	472	867	java/lang/Throwable
    //   475	481	867	java/lang/Throwable
    //   481	524	867	java/lang/Throwable
    //   534	582	867	java/lang/Throwable
    //   582	609	867	java/lang/Throwable
    //   621	657	867	java/lang/Throwable
    //   657	719	867	java/lang/Throwable
    //   723	752	867	java/lang/Throwable
    //   758	774	867	java/lang/Throwable
    //   779	807	867	java/lang/Throwable
    //   820	855	867	java/lang/Throwable
    //   47	58	870	java/lang/Throwable
  }
}


/* Location:           C:\Users\guanghui\Desktop\软件安全\38\classes-dex2jar.jar
 * Qualified Name:     net.youmi.android.a.a.a.b
 * JD-Core Version:    0.7.0.1
 */