package net.youmi.android.a.a;

public class e
{
  /* Error */
  public static void a(android.content.Context paramContext, net.youmi.android.a.h.e parame, java.util.List paramList)
  {
    // Byte code:
    //   0: aload_0
    //   1: invokevirtual 14	android/content/Context:getApplicationContext	()Landroid/content/Context;
    //   4: astore 10
    //   6: aconst_null
    //   7: astore_0
    //   8: aconst_null
    //   9: astore 9
    //   11: aconst_null
    //   12: astore 8
    //   14: aload 10
    //   16: ifnonnull +16 -> 32
    //   19: iconst_0
    //   20: ifeq +11 -> 31
    //   23: new 16	java/lang/NullPointerException
    //   26: dup
    //   27: invokespecial 20	java/lang/NullPointerException:<init>	()V
    //   30: athrow
    //   31: return
    //   32: aload_2
    //   33: ifnonnull +17 -> 50
    //   36: iconst_0
    //   37: ifeq -6 -> 31
    //   40: new 16	java/lang/NullPointerException
    //   43: dup
    //   44: invokespecial 20	java/lang/NullPointerException:<init>	()V
    //   47: athrow
    //   48: astore_0
    //   49: return
    //   50: aload_0
    //   51: astore 7
    //   53: aload 9
    //   55: astore 6
    //   57: aload_2
    //   58: invokeinterface 26 1 0
    //   63: istore_3
    //   64: iload_3
    //   65: ifne +17 -> 82
    //   68: iconst_0
    //   69: ifeq -38 -> 31
    //   72: new 16	java/lang/NullPointerException
    //   75: dup
    //   76: invokespecial 20	java/lang/NullPointerException:<init>	()V
    //   79: athrow
    //   80: astore_0
    //   81: return
    //   82: aload_0
    //   83: astore 7
    //   85: aload 9
    //   87: astore 6
    //   89: aload_2
    //   90: invokeinterface 26 1 0
    //   95: istore 4
    //   97: iconst_0
    //   98: istore_3
    //   99: aload 8
    //   101: astore_0
    //   102: iload_3
    //   103: iload 4
    //   105: if_icmpge +201 -> 306
    //   108: aload_0
    //   109: astore 7
    //   111: aload_0
    //   112: astore 6
    //   114: aload_2
    //   115: iload_3
    //   116: invokeinterface 30 2 0
    //   121: checkcast 32	net/youmi/android/a/a/a/a
    //   124: astore 8
    //   126: aload 8
    //   128: ifnonnull +16 -> 144
    //   131: aload_0
    //   132: astore 7
    //   134: iload_3
    //   135: iconst_1
    //   136: iadd
    //   137: istore_3
    //   138: aload 7
    //   140: astore_0
    //   141: goto -39 -> 102
    //   144: aload_0
    //   145: astore 7
    //   147: aload_0
    //   148: astore 6
    //   150: aload 8
    //   152: invokevirtual 36	net/youmi/android/a/a/a/a:g	()Lnet/youmi/android/a/a/a/g;
    //   155: ifnull -21 -> 134
    //   158: aload_0
    //   159: astore 7
    //   161: aload_0
    //   162: astore 6
    //   164: aload 8
    //   166: invokevirtual 36	net/youmi/android/a/a/a/a:g	()Lnet/youmi/android/a/a/a/g;
    //   169: invokevirtual 42	net/youmi/android/a/a/a/g:c	()Ljava/lang/String;
    //   172: ifnull -38 -> 134
    //   175: aload_0
    //   176: astore 6
    //   178: aload 8
    //   180: invokevirtual 46	net/youmi/android/a/a/a/a:e	()Lnet/youmi/android/a/a/a/f;
    //   183: ifnonnull +18 -> 201
    //   186: aload_0
    //   187: astore 6
    //   189: aload 8
    //   191: new 48	net/youmi/android/a/a/a/f
    //   194: dup
    //   195: invokespecial 49	net/youmi/android/a/a/a/f:<init>	()V
    //   198: invokevirtual 52	net/youmi/android/a/a/a/a:a	(Lnet/youmi/android/a/a/a/f;)V
    //   201: aload_0
    //   202: astore 6
    //   204: aload 8
    //   206: invokevirtual 46	net/youmi/android/a/a/a/a:e	()Lnet/youmi/android/a/a/a/f;
    //   209: aload 10
    //   211: aload 8
    //   213: invokevirtual 36	net/youmi/android/a/a/a/a:g	()Lnet/youmi/android/a/a/a/g;
    //   216: invokevirtual 42	net/youmi/android/a/a/a/g:c	()Ljava/lang/String;
    //   219: invokevirtual 55	net/youmi/android/a/a/a/f:a	(Landroid/content/Context;Ljava/lang/String;)Z
    //   222: istore 5
    //   224: aload_0
    //   225: astore 7
    //   227: iload 5
    //   229: ifeq -95 -> 134
    //   232: aload_0
    //   233: astore 7
    //   235: aload_0
    //   236: astore 6
    //   238: aload 8
    //   240: invokevirtual 46	net/youmi/android/a/a/a/a:e	()Lnet/youmi/android/a/a/a/f;
    //   243: invokevirtual 59	net/youmi/android/a/a/a/f:b	()Z
    //   246: ifeq -112 -> 134
    //   249: aload_0
    //   250: astore 7
    //   252: aload_0
    //   253: astore 6
    //   255: aload 8
    //   257: invokevirtual 46	net/youmi/android/a/a/a/a:e	()Lnet/youmi/android/a/a/a/f;
    //   260: invokevirtual 61	net/youmi/android/a/a/a/f:a	()Z
    //   263: ifne -129 -> 134
    //   266: aload_0
    //   267: ifnonnull +154 -> 421
    //   270: aload_0
    //   271: astore 6
    //   273: new 63	java/util/ArrayList
    //   276: dup
    //   277: bipush 25
    //   279: invokespecial 66	java/util/ArrayList:<init>	(I)V
    //   282: astore 7
    //   284: aload 7
    //   286: astore_0
    //   287: aload_0
    //   288: aload 8
    //   290: invokevirtual 36	net/youmi/android/a/a/a/a:g	()Lnet/youmi/android/a/a/a/g;
    //   293: invokevirtual 42	net/youmi/android/a/a/a/g:c	()Ljava/lang/String;
    //   296: invokevirtual 70	java/util/ArrayList:add	(Ljava/lang/Object;)Z
    //   299: pop
    //   300: aload_0
    //   301: astore 7
    //   303: goto -169 -> 134
    //   306: aload_0
    //   307: ifnull -276 -> 31
    //   310: aload_0
    //   311: invokevirtual 71	java/util/ArrayList:size	()I
    //   314: ifle -283 -> 31
    //   317: aload_1
    //   318: aload 10
    //   320: aload_0
    //   321: invokeinterface 76 3 0
    //   326: pop
    //   327: return
    //   328: astore_0
    //   329: return
    //   330: astore_0
    //   331: aload 7
    //   333: ifnull -302 -> 31
    //   336: aload 7
    //   338: invokevirtual 71	java/util/ArrayList:size	()I
    //   341: ifle -310 -> 31
    //   344: aload_1
    //   345: aload 10
    //   347: aload 7
    //   349: invokeinterface 76 3 0
    //   354: pop
    //   355: return
    //   356: astore_0
    //   357: return
    //   358: astore_0
    //   359: aload 6
    //   361: ifnull +22 -> 383
    //   364: aload 6
    //   366: invokevirtual 71	java/util/ArrayList:size	()I
    //   369: ifle +14 -> 383
    //   372: aload_1
    //   373: aload 10
    //   375: aload 6
    //   377: invokeinterface 76 3 0
    //   382: pop
    //   383: aload_0
    //   384: athrow
    //   385: astore_1
    //   386: goto -3 -> 383
    //   389: astore_2
    //   390: aload_0
    //   391: astore 6
    //   393: aload_2
    //   394: astore_0
    //   395: goto -36 -> 359
    //   398: astore 6
    //   400: aload_0
    //   401: astore 7
    //   403: goto -269 -> 134
    //   406: astore 6
    //   408: aload_0
    //   409: astore 7
    //   411: goto -277 -> 134
    //   414: astore 6
    //   416: goto -184 -> 232
    //   419: astore_0
    //   420: return
    //   421: goto -134 -> 287
    // Local variable table:
    //   start	length	slot	name	signature
    //   0	424	0	paramContext	android.content.Context
    //   0	424	1	parame	net.youmi.android.a.h.e
    //   0	424	2	paramList	java.util.List
    //   63	75	3	i	int
    //   95	11	4	j	int
    //   222	6	5	bool	boolean
    //   55	337	6	localObject1	Object
    //   398	1	6	localThrowable1	java.lang.Throwable
    //   406	1	6	localThrowable2	java.lang.Throwable
    //   414	1	6	localThrowable3	java.lang.Throwable
    //   51	359	7	localObject2	Object
    //   12	277	8	locala	net.youmi.android.a.a.a.a
    //   9	77	9	localObject3	Object
    //   4	370	10	localContext	android.content.Context
    // Exception table:
    //   from	to	target	type
    //   40	48	48	java/lang/Throwable
    //   72	80	80	java/lang/Throwable
    //   310	327	328	java/lang/Throwable
    //   57	64	330	java/lang/Throwable
    //   89	97	330	java/lang/Throwable
    //   114	126	330	java/lang/Throwable
    //   336	355	356	java/lang/Throwable
    //   57	64	358	finally
    //   89	97	358	finally
    //   114	126	358	finally
    //   150	158	358	finally
    //   164	175	358	finally
    //   178	186	358	finally
    //   189	201	358	finally
    //   204	224	358	finally
    //   238	249	358	finally
    //   255	266	358	finally
    //   273	284	358	finally
    //   364	383	385	java/lang/Throwable
    //   287	300	389	finally
    //   287	300	398	java/lang/Throwable
    //   238	249	406	java/lang/Throwable
    //   255	266	406	java/lang/Throwable
    //   273	284	406	java/lang/Throwable
    //   150	158	414	java/lang/Throwable
    //   164	175	414	java/lang/Throwable
    //   178	186	414	java/lang/Throwable
    //   189	201	414	java/lang/Throwable
    //   204	224	414	java/lang/Throwable
    //   23	31	419	java/lang/Throwable
  }
}


/* Location:           C:\Users\guanghui\Desktop\软件安全\37\classes-dex2jar.jar
 * Qualified Name:     net.youmi.android.a.a.e
 * JD-Core Version:    0.7.0.1
 */