package net.youmi.android.d.b;

import android.content.Context;
import net.youmi.android.c.c.g;
import net.youmi.android.c.g.c;
import net.youmi.android.c.g.d;

public class a
{
  private static String a()
  {
    try
    {
      String str = g.b("0d4d40490d1c17164303471757144d4b5c105d084d5c01101b46551958590841", "yKl76nGU1e7a");
      return str;
    }
    catch (Throwable localThrowable) {}
    return null;
  }
  
  /* Error */
  public static String a(Context paramContext)
  {
    // Byte code:
    //   0: iconst_3
    //   1: istore_1
    //   2: aload_0
    //   3: ifnonnull +5 -> 8
    //   6: aconst_null
    //   7: areturn
    //   8: aload_0
    //   9: invokestatic 26	net/youmi/android/b/b/a:c	(Landroid/content/Context;)Z
    //   12: ifne +5 -> 17
    //   15: aconst_null
    //   16: areturn
    //   17: new 28	net/youmi/android/b/a/b
    //   20: dup
    //   21: aload_0
    //   22: invokespecial 32	net/youmi/android/b/a/b:<init>	(Landroid/content/Context;)V
    //   25: astore 8
    //   27: aload_0
    //   28: invokestatic 34	net/youmi/android/b/b/a:a	(Landroid/content/Context;)Ljava/lang/String;
    //   31: astore 5
    //   33: ldc 36
    //   35: astore 4
    //   37: aload 5
    //   39: ifnull +769 -> 808
    //   42: aload 5
    //   44: ldc 36
    //   46: invokevirtual 42	java/lang/String:equals	(Ljava/lang/Object;)Z
    //   49: istore_3
    //   50: iload_3
    //   51: ifne +757 -> 808
    //   54: new 44	java/lang/StringBuilder
    //   57: dup
    //   58: invokespecial 47	java/lang/StringBuilder:<init>	()V
    //   61: aload 5
    //   63: iconst_0
    //   64: iconst_1
    //   65: invokevirtual 51	java/lang/String:substring	(II)Ljava/lang/String;
    //   68: invokevirtual 55	java/lang/StringBuilder:append	(Ljava/lang/String;)Ljava/lang/StringBuilder;
    //   71: aload 5
    //   73: iconst_1
    //   74: invokevirtual 58	java/lang/String:substring	(I)Ljava/lang/String;
    //   77: invokestatic 63	net/youmi/android/b/a/a:a	(Ljava/lang/String;)Ljava/lang/String;
    //   80: invokevirtual 55	java/lang/StringBuilder:append	(Ljava/lang/String;)Ljava/lang/StringBuilder;
    //   83: invokevirtual 66	java/lang/StringBuilder:toString	()Ljava/lang/String;
    //   86: astore 5
    //   88: aload 5
    //   90: astore 4
    //   92: invokestatic 68	net/youmi/android/d/b/a:a	()Ljava/lang/String;
    //   95: astore 7
    //   97: aload 7
    //   99: ifnonnull +5 -> 104
    //   102: aconst_null
    //   103: areturn
    //   104: iconst_4
    //   105: invokestatic 70	net/youmi/android/b/a/a:a	(I)Ljava/lang/String;
    //   108: astore 6
    //   110: new 72	java/lang/StringBuffer
    //   113: dup
    //   114: sipush 512
    //   117: invokespecial 75	java/lang/StringBuffer:<init>	(I)V
    //   120: astore 5
    //   122: aload 5
    //   124: aload 7
    //   126: invokevirtual 78	java/lang/StringBuffer:append	(Ljava/lang/String;)Ljava/lang/StringBuffer;
    //   129: pop
    //   130: aload 5
    //   132: ldc 80
    //   134: invokevirtual 78	java/lang/StringBuffer:append	(Ljava/lang/String;)Ljava/lang/StringBuffer;
    //   137: pop
    //   138: aload 5
    //   140: ldc 82
    //   142: invokevirtual 78	java/lang/StringBuffer:append	(Ljava/lang/String;)Ljava/lang/StringBuffer;
    //   145: pop
    //   146: aload 5
    //   148: iconst_3
    //   149: invokevirtual 85	java/lang/StringBuffer:append	(I)Ljava/lang/StringBuffer;
    //   152: pop
    //   153: aload 5
    //   155: aload 4
    //   157: invokevirtual 78	java/lang/StringBuffer:append	(Ljava/lang/String;)Ljava/lang/StringBuffer;
    //   160: pop
    //   161: aload 5
    //   163: aload 6
    //   165: invokevirtual 78	java/lang/StringBuffer:append	(Ljava/lang/String;)Ljava/lang/StringBuffer;
    //   168: pop
    //   169: new 87	java/io/ByteArrayOutputStream
    //   172: dup
    //   173: sipush 512
    //   176: invokespecial 88	java/io/ByteArrayOutputStream:<init>	(I)V
    //   179: astore 7
    //   181: ldc 90
    //   183: aload 7
    //   185: invokestatic 95	net/youmi/android/b/a/c:a	(Ljava/lang/String;Ljava/io/ByteArrayOutputStream;)V
    //   188: aload 7
    //   190: bipush 38
    //   192: invokevirtual 98	java/io/ByteArrayOutputStream:write	(I)V
    //   195: aload_0
    //   196: invokestatic 102	net/youmi/android/c/a:b	(Landroid/content/Context;)Ljava/lang/String;
    //   199: aload 7
    //   201: invokestatic 95	net/youmi/android/b/a/c:a	(Ljava/lang/String;Ljava/io/ByteArrayOutputStream;)V
    //   204: aload 7
    //   206: bipush 38
    //   208: invokevirtual 98	java/io/ByteArrayOutputStream:write	(I)V
    //   211: aload_0
    //   212: invokestatic 105	net/youmi/android/c/a:g	(Landroid/content/Context;)Ljava/lang/String;
    //   215: aload 7
    //   217: invokestatic 95	net/youmi/android/b/a/c:a	(Ljava/lang/String;Ljava/io/ByteArrayOutputStream;)V
    //   220: aload 7
    //   222: bipush 38
    //   224: invokevirtual 98	java/io/ByteArrayOutputStream:write	(I)V
    //   227: aload 8
    //   229: invokevirtual 106	net/youmi/android/b/a/b:a	()Ljava/lang/String;
    //   232: aload 7
    //   234: invokestatic 95	net/youmi/android/b/a/c:a	(Ljava/lang/String;Ljava/io/ByteArrayOutputStream;)V
    //   237: aload 7
    //   239: bipush 38
    //   241: invokevirtual 98	java/io/ByteArrayOutputStream:write	(I)V
    //   244: aload 8
    //   246: invokevirtual 108	net/youmi/android/b/a/b:b	()Ljava/lang/String;
    //   249: aload 7
    //   251: invokestatic 95	net/youmi/android/b/a/c:a	(Ljava/lang/String;Ljava/io/ByteArrayOutputStream;)V
    //   254: aload 7
    //   256: bipush 38
    //   258: invokevirtual 98	java/io/ByteArrayOutputStream:write	(I)V
    //   261: invokestatic 111	net/youmi/android/c/a:d	()Ljava/lang/String;
    //   264: aload 7
    //   266: invokestatic 95	net/youmi/android/b/a/c:a	(Ljava/lang/String;Ljava/io/ByteArrayOutputStream;)V
    //   269: aload 7
    //   271: bipush 38
    //   273: invokevirtual 98	java/io/ByteArrayOutputStream:write	(I)V
    //   276: invokestatic 112	net/youmi/android/c/a:b	()Ljava/lang/String;
    //   279: aload 7
    //   281: invokestatic 95	net/youmi/android/b/a/c:a	(Ljava/lang/String;Ljava/io/ByteArrayOutputStream;)V
    //   284: aload 7
    //   286: bipush 38
    //   288: invokevirtual 98	java/io/ByteArrayOutputStream:write	(I)V
    //   291: aload 8
    //   293: invokevirtual 113	net/youmi/android/b/a/b:d	()Ljava/lang/String;
    //   296: aload 7
    //   298: invokestatic 95	net/youmi/android/b/a/c:a	(Ljava/lang/String;Ljava/io/ByteArrayOutputStream;)V
    //   301: aload 7
    //   303: bipush 38
    //   305: invokevirtual 98	java/io/ByteArrayOutputStream:write	(I)V
    //   308: invokestatic 115	net/youmi/android/c/a:c	()Ljava/lang/String;
    //   311: aload 7
    //   313: invokestatic 95	net/youmi/android/b/a/c:a	(Ljava/lang/String;Ljava/io/ByteArrayOutputStream;)V
    //   316: aload 7
    //   318: bipush 38
    //   320: invokevirtual 98	java/io/ByteArrayOutputStream:write	(I)V
    //   323: aload 8
    //   325: invokevirtual 116	net/youmi/android/b/a/b:c	()Ljava/lang/String;
    //   328: aload 7
    //   330: invokestatic 95	net/youmi/android/b/a/c:a	(Ljava/lang/String;Ljava/io/ByteArrayOutputStream;)V
    //   333: aload 7
    //   335: bipush 38
    //   337: invokevirtual 98	java/io/ByteArrayOutputStream:write	(I)V
    //   340: aload 7
    //   342: bipush 38
    //   344: invokevirtual 98	java/io/ByteArrayOutputStream:write	(I)V
    //   347: invokestatic 122	java/util/Locale:getDefault	()Ljava/util/Locale;
    //   350: invokevirtual 125	java/util/Locale:getCountry	()Ljava/lang/String;
    //   353: aload 7
    //   355: invokestatic 95	net/youmi/android/b/a/c:a	(Ljava/lang/String;Ljava/io/ByteArrayOutputStream;)V
    //   358: aload 7
    //   360: bipush 38
    //   362: invokevirtual 98	java/io/ByteArrayOutputStream:write	(I)V
    //   365: invokestatic 122	java/util/Locale:getDefault	()Ljava/util/Locale;
    //   368: invokevirtual 128	java/util/Locale:getLanguage	()Ljava/lang/String;
    //   371: aload 7
    //   373: invokestatic 95	net/youmi/android/b/a/c:a	(Ljava/lang/String;Ljava/io/ByteArrayOutputStream;)V
    //   376: aload 7
    //   378: bipush 38
    //   380: invokevirtual 98	java/io/ByteArrayOutputStream:write	(I)V
    //   383: aload_0
    //   384: invokestatic 133	net/youmi/android/c/k/d:a	(Landroid/content/Context;)Lnet/youmi/android/c/k/d;
    //   387: invokevirtual 136	net/youmi/android/c/k/d:b	()I
    //   390: invokestatic 139	java/lang/String:valueOf	(I)Ljava/lang/String;
    //   393: aload 7
    //   395: invokestatic 95	net/youmi/android/b/a/c:a	(Ljava/lang/String;Ljava/io/ByteArrayOutputStream;)V
    //   398: aload 7
    //   400: bipush 38
    //   402: invokevirtual 98	java/io/ByteArrayOutputStream:write	(I)V
    //   405: aload_0
    //   406: invokestatic 133	net/youmi/android/c/k/d:a	(Landroid/content/Context;)Lnet/youmi/android/c/k/d;
    //   409: invokevirtual 141	net/youmi/android/c/k/d:c	()I
    //   412: invokestatic 139	java/lang/String:valueOf	(I)Ljava/lang/String;
    //   415: aload 7
    //   417: invokestatic 95	net/youmi/android/b/a/c:a	(Ljava/lang/String;Ljava/io/ByteArrayOutputStream;)V
    //   420: aload 7
    //   422: bipush 38
    //   424: invokevirtual 98	java/io/ByteArrayOutputStream:write	(I)V
    //   427: aload_0
    //   428: invokestatic 133	net/youmi/android/c/k/d:a	(Landroid/content/Context;)Lnet/youmi/android/c/k/d;
    //   431: invokevirtual 143	net/youmi/android/c/k/d:d	()I
    //   434: invokestatic 139	java/lang/String:valueOf	(I)Ljava/lang/String;
    //   437: aload 7
    //   439: invokestatic 95	net/youmi/android/b/a/c:a	(Ljava/lang/String;Ljava/io/ByteArrayOutputStream;)V
    //   442: aload 7
    //   444: bipush 38
    //   446: invokevirtual 98	java/io/ByteArrayOutputStream:write	(I)V
    //   449: aload_0
    //   450: invokestatic 147	net/youmi/android/c/k/k:a	(Landroid/content/Context;)Z
    //   453: ifeq +219 -> 672
    //   456: ldc 149
    //   458: astore 4
    //   460: aload 4
    //   462: aload 7
    //   464: invokestatic 95	net/youmi/android/b/a/c:a	(Ljava/lang/String;Ljava/io/ByteArrayOutputStream;)V
    //   467: aload 7
    //   469: bipush 38
    //   471: invokevirtual 98	java/io/ByteArrayOutputStream:write	(I)V
    //   474: aload_0
    //   475: invokestatic 152	net/youmi/android/c/k/j:a	(Landroid/content/Context;)Z
    //   478: istore_3
    //   479: iload_3
    //   480: ifeq +199 -> 679
    //   483: aload_0
    //   484: invokestatic 157	net/youmi/android/a/i/a:a	(Landroid/content/Context;)Lnet/youmi/android/a/i/a;
    //   487: invokevirtual 160	net/youmi/android/a/i/a:a	()Landroid/location/Location;
    //   490: astore 4
    //   492: iload_1
    //   493: istore_2
    //   494: aload 4
    //   496: ifnull +7 -> 503
    //   499: iload_1
    //   500: iconst_4
    //   501: ior
    //   502: istore_2
    //   503: aload_0
    //   504: invokestatic 163	net/youmi/android/c/h/b:a	(Landroid/content/Context;)Ljava/lang/String;
    //   507: ldc 165
    //   509: invokevirtual 42	java/lang/String:equals	(Ljava/lang/Object;)Z
    //   512: ifeq +3 -> 515
    //   515: iconst_0
    //   516: invokestatic 169	java/lang/Integer:toString	(I)Ljava/lang/String;
    //   519: aload 7
    //   521: invokestatic 95	net/youmi/android/b/a/c:a	(Ljava/lang/String;Ljava/io/ByteArrayOutputStream;)V
    //   524: aload 7
    //   526: bipush 38
    //   528: invokevirtual 98	java/io/ByteArrayOutputStream:write	(I)V
    //   531: aload_0
    //   532: invokestatic 170	net/youmi/android/b/b/a:g	(Landroid/content/Context;)Ljava/lang/String;
    //   535: astore 4
    //   537: aload 4
    //   539: ifnull +10 -> 549
    //   542: aload 4
    //   544: aload 7
    //   546: invokestatic 95	net/youmi/android/b/a/c:a	(Ljava/lang/String;Ljava/io/ByteArrayOutputStream;)V
    //   549: aload 7
    //   551: bipush 38
    //   553: invokevirtual 98	java/io/ByteArrayOutputStream:write	(I)V
    //   556: getstatic 176	android/os/Build:BOARD	Ljava/lang/String;
    //   559: aload 7
    //   561: invokestatic 95	net/youmi/android/b/a/c:a	(Ljava/lang/String;Ljava/io/ByteArrayOutputStream;)V
    //   564: aload 7
    //   566: bipush 38
    //   568: invokevirtual 98	java/io/ByteArrayOutputStream:write	(I)V
    //   571: getstatic 179	android/os/Build:BRAND	Ljava/lang/String;
    //   574: aload 7
    //   576: invokestatic 95	net/youmi/android/b/a/c:a	(Ljava/lang/String;Ljava/io/ByteArrayOutputStream;)V
    //   579: aload 7
    //   581: bipush 38
    //   583: invokevirtual 98	java/io/ByteArrayOutputStream:write	(I)V
    //   586: getstatic 182	android/os/Build:DEVICE	Ljava/lang/String;
    //   589: aload 7
    //   591: invokestatic 95	net/youmi/android/b/a/c:a	(Ljava/lang/String;Ljava/io/ByteArrayOutputStream;)V
    //   594: aload 7
    //   596: bipush 38
    //   598: invokevirtual 98	java/io/ByteArrayOutputStream:write	(I)V
    //   601: invokestatic 188	java/lang/System:currentTimeMillis	()J
    //   604: ldc2_w 189
    //   607: ldiv
    //   608: invokestatic 193	java/lang/String:valueOf	(J)Ljava/lang/String;
    //   611: aload 7
    //   613: invokestatic 95	net/youmi/android/b/a/c:a	(Ljava/lang/String;Ljava/io/ByteArrayOutputStream;)V
    //   616: new 44	java/lang/StringBuilder
    //   619: dup
    //   620: invokespecial 47	java/lang/StringBuilder:<init>	()V
    //   623: ldc 195
    //   625: invokevirtual 55	java/lang/StringBuilder:append	(Ljava/lang/String;)Ljava/lang/StringBuilder;
    //   628: aload_0
    //   629: invokestatic 196	net/youmi/android/b/b/a:b	(Landroid/content/Context;)Ljava/lang/String;
    //   632: invokevirtual 55	java/lang/StringBuilder:append	(Ljava/lang/String;)Ljava/lang/StringBuilder;
    //   635: aload 6
    //   637: invokevirtual 55	java/lang/StringBuilder:append	(Ljava/lang/String;)Ljava/lang/StringBuilder;
    //   640: invokevirtual 66	java/lang/StringBuilder:toString	()Ljava/lang/String;
    //   643: invokestatic 199	net/youmi/android/c/c/e:a	(Ljava/lang/String;)Ljava/lang/String;
    //   646: astore_0
    //   647: aload 5
    //   649: aload 7
    //   651: invokevirtual 203	java/io/ByteArrayOutputStream:toByteArray	()[B
    //   654: aload_0
    //   655: ldc 204
    //   657: invokestatic 207	net/youmi/android/b/a/a:a	([BLjava/lang/String;I)Ljava/lang/String;
    //   660: invokevirtual 78	java/lang/StringBuffer:append	(Ljava/lang/String;)Ljava/lang/StringBuffer;
    //   663: pop
    //   664: aload 5
    //   666: invokevirtual 208	java/lang/StringBuffer:toString	()Ljava/lang/String;
    //   669: astore_0
    //   670: aload_0
    //   671: areturn
    //   672: ldc 210
    //   674: astore 4
    //   676: goto -216 -> 460
    //   679: iconst_0
    //   680: istore_1
    //   681: goto -198 -> 483
    //   684: astore_0
    //   685: aconst_null
    //   686: areturn
    //   687: astore_0
    //   688: goto -24 -> 664
    //   691: astore 4
    //   693: goto -77 -> 616
    //   696: astore 4
    //   698: goto -104 -> 594
    //   701: astore 4
    //   703: goto -124 -> 579
    //   706: astore 4
    //   708: goto -144 -> 564
    //   711: astore 4
    //   713: goto -164 -> 549
    //   716: astore 4
    //   718: goto -194 -> 524
    //   721: astore 4
    //   723: iload_1
    //   724: istore_2
    //   725: goto -222 -> 503
    //   728: astore 4
    //   730: goto -263 -> 467
    //   733: astore 4
    //   735: goto -293 -> 442
    //   738: astore 4
    //   740: goto -320 -> 420
    //   743: astore 4
    //   745: goto -347 -> 398
    //   748: astore 4
    //   750: goto -374 -> 376
    //   753: astore 4
    //   755: goto -397 -> 358
    //   758: astore 4
    //   760: goto -427 -> 333
    //   763: astore 4
    //   765: goto -449 -> 316
    //   768: astore 4
    //   770: goto -469 -> 301
    //   773: astore 4
    //   775: goto -491 -> 284
    //   778: astore 4
    //   780: goto -511 -> 269
    //   783: astore 4
    //   785: goto -531 -> 254
    //   788: astore 4
    //   790: goto -553 -> 237
    //   793: astore 4
    //   795: goto -575 -> 220
    //   798: astore 4
    //   800: goto -596 -> 204
    //   803: astore 5
    //   805: goto -713 -> 92
    //   808: aconst_null
    //   809: areturn
    // Local variable table:
    //   start	length	slot	name	signature
    //   0	810	0	paramContext	Context
    //   1	723	1	i	int
    //   493	232	2	j	int
    //   49	431	3	bool	boolean
    //   35	640	4	localObject1	Object
    //   691	1	4	localThrowable1	Throwable
    //   696	1	4	localThrowable2	Throwable
    //   701	1	4	localThrowable3	Throwable
    //   706	1	4	localThrowable4	Throwable
    //   711	1	4	localThrowable5	Throwable
    //   716	1	4	localThrowable6	Throwable
    //   721	1	4	localThrowable7	Throwable
    //   728	1	4	localThrowable8	Throwable
    //   733	1	4	localThrowable9	Throwable
    //   738	1	4	localThrowable10	Throwable
    //   743	1	4	localThrowable11	Throwable
    //   748	1	4	localThrowable12	Throwable
    //   753	1	4	localThrowable13	Throwable
    //   758	1	4	localThrowable14	Throwable
    //   763	1	4	localThrowable15	Throwable
    //   768	1	4	localThrowable16	Throwable
    //   773	1	4	localThrowable17	Throwable
    //   778	1	4	localThrowable18	Throwable
    //   783	1	4	localThrowable19	Throwable
    //   788	1	4	localThrowable20	Throwable
    //   793	1	4	localThrowable21	Throwable
    //   798	1	4	localThrowable22	Throwable
    //   31	634	5	localObject2	Object
    //   803	1	5	localThrowable23	Throwable
    //   108	528	6	str	String
    //   95	555	7	localObject3	Object
    //   25	299	8	localb	net.youmi.android.b.a.b
    // Exception table:
    //   from	to	target	type
    //   8	15	684	java/lang/Throwable
    //   17	33	684	java/lang/Throwable
    //   42	50	684	java/lang/Throwable
    //   92	97	684	java/lang/Throwable
    //   104	195	684	java/lang/Throwable
    //   204	211	684	java/lang/Throwable
    //   220	227	684	java/lang/Throwable
    //   237	244	684	java/lang/Throwable
    //   254	261	684	java/lang/Throwable
    //   269	276	684	java/lang/Throwable
    //   284	291	684	java/lang/Throwable
    //   301	308	684	java/lang/Throwable
    //   316	323	684	java/lang/Throwable
    //   333	347	684	java/lang/Throwable
    //   358	365	684	java/lang/Throwable
    //   376	383	684	java/lang/Throwable
    //   398	405	684	java/lang/Throwable
    //   420	427	684	java/lang/Throwable
    //   442	449	684	java/lang/Throwable
    //   467	474	684	java/lang/Throwable
    //   524	531	684	java/lang/Throwable
    //   549	556	684	java/lang/Throwable
    //   564	571	684	java/lang/Throwable
    //   579	586	684	java/lang/Throwable
    //   594	601	684	java/lang/Throwable
    //   616	647	684	java/lang/Throwable
    //   664	670	684	java/lang/Throwable
    //   647	664	687	java/lang/Throwable
    //   601	616	691	java/lang/Throwable
    //   586	594	696	java/lang/Throwable
    //   571	579	701	java/lang/Throwable
    //   556	564	706	java/lang/Throwable
    //   531	537	711	java/lang/Throwable
    //   542	549	711	java/lang/Throwable
    //   474	479	716	java/lang/Throwable
    //   503	515	716	java/lang/Throwable
    //   515	524	716	java/lang/Throwable
    //   483	492	721	java/lang/Throwable
    //   449	456	728	java/lang/Throwable
    //   460	467	728	java/lang/Throwable
    //   427	442	733	java/lang/Throwable
    //   405	420	738	java/lang/Throwable
    //   383	398	743	java/lang/Throwable
    //   365	376	748	java/lang/Throwable
    //   347	358	753	java/lang/Throwable
    //   323	333	758	java/lang/Throwable
    //   308	316	763	java/lang/Throwable
    //   291	301	768	java/lang/Throwable
    //   276	284	773	java/lang/Throwable
    //   261	269	778	java/lang/Throwable
    //   244	254	783	java/lang/Throwable
    //   227	237	788	java/lang/Throwable
    //   211	220	793	java/lang/Throwable
    //   195	204	798	java/lang/Throwable
    //   54	88	803	java/lang/Throwable
  }
  
  /* Error */
  public static String a(Context paramContext, int paramInt, String paramString)
  {
    // Byte code:
    //   0: aload_2
    //   1: ifnonnull +5 -> 6
    //   4: aconst_null
    //   5: areturn
    //   6: new 44	java/lang/StringBuilder
    //   9: dup
    //   10: sipush 512
    //   13: invokespecial 212	java/lang/StringBuilder:<init>	(I)V
    //   16: astore 6
    //   18: invokestatic 188	java/lang/System:currentTimeMillis	()J
    //   21: ldc2_w 189
    //   24: ldiv
    //   25: lstore_3
    //   26: iconst_4
    //   27: invokestatic 70	net/youmi/android/b/a/a:a	(I)Ljava/lang/String;
    //   30: astore 8
    //   32: aload 6
    //   34: ldc 82
    //   36: invokevirtual 55	java/lang/StringBuilder:append	(Ljava/lang/String;)Ljava/lang/StringBuilder;
    //   39: pop
    //   40: aload 6
    //   42: iconst_3
    //   43: invokevirtual 215	java/lang/StringBuilder:append	(I)Ljava/lang/StringBuilder;
    //   46: pop
    //   47: aload 6
    //   49: aload_0
    //   50: invokestatic 34	net/youmi/android/b/b/a:a	(Landroid/content/Context;)Ljava/lang/String;
    //   53: invokevirtual 55	java/lang/StringBuilder:append	(Ljava/lang/String;)Ljava/lang/StringBuilder;
    //   56: pop
    //   57: aload 6
    //   59: aload 8
    //   61: invokevirtual 55	java/lang/StringBuilder:append	(Ljava/lang/String;)Ljava/lang/StringBuilder;
    //   64: pop
    //   65: new 87	java/io/ByteArrayOutputStream
    //   68: dup
    //   69: sipush 512
    //   72: invokespecial 88	java/io/ByteArrayOutputStream:<init>	(I)V
    //   75: astore 7
    //   77: new 28	net/youmi/android/b/a/b
    //   80: dup
    //   81: aload_0
    //   82: invokespecial 32	net/youmi/android/b/a/b:<init>	(Landroid/content/Context;)V
    //   85: astore 9
    //   87: ldc 217
    //   89: aload 7
    //   91: invokestatic 95	net/youmi/android/b/a/c:a	(Ljava/lang/String;Ljava/io/ByteArrayOutputStream;)V
    //   94: aload 7
    //   96: bipush 38
    //   98: invokevirtual 98	java/io/ByteArrayOutputStream:write	(I)V
    //   101: aload 9
    //   103: invokevirtual 221	net/youmi/android/b/a/b:e	()Z
    //   106: ifeq +199 -> 305
    //   109: ldc 149
    //   111: astore 5
    //   113: aload 5
    //   115: aload 7
    //   117: invokestatic 95	net/youmi/android/b/a/c:a	(Ljava/lang/String;Ljava/io/ByteArrayOutputStream;)V
    //   120: aload 7
    //   122: bipush 38
    //   124: invokevirtual 98	java/io/ByteArrayOutputStream:write	(I)V
    //   127: aload 9
    //   129: invokevirtual 113	net/youmi/android/b/a/b:d	()Ljava/lang/String;
    //   132: aload 7
    //   134: invokestatic 95	net/youmi/android/b/a/c:a	(Ljava/lang/String;Ljava/io/ByteArrayOutputStream;)V
    //   137: aload 7
    //   139: bipush 38
    //   141: invokevirtual 98	java/io/ByteArrayOutputStream:write	(I)V
    //   144: aload 9
    //   146: invokevirtual 116	net/youmi/android/b/a/b:c	()Ljava/lang/String;
    //   149: aload 7
    //   151: invokestatic 95	net/youmi/android/b/a/c:a	(Ljava/lang/String;Ljava/io/ByteArrayOutputStream;)V
    //   154: aload 7
    //   156: bipush 38
    //   158: invokevirtual 98	java/io/ByteArrayOutputStream:write	(I)V
    //   161: aload 9
    //   163: invokevirtual 108	net/youmi/android/b/a/b:b	()Ljava/lang/String;
    //   166: aload 7
    //   168: invokestatic 95	net/youmi/android/b/a/c:a	(Ljava/lang/String;Ljava/io/ByteArrayOutputStream;)V
    //   171: aload 7
    //   173: bipush 38
    //   175: invokevirtual 98	java/io/ByteArrayOutputStream:write	(I)V
    //   178: aload 9
    //   180: invokevirtual 106	net/youmi/android/b/a/b:a	()Ljava/lang/String;
    //   183: aload 7
    //   185: invokestatic 95	net/youmi/android/b/a/c:a	(Ljava/lang/String;Ljava/io/ByteArrayOutputStream;)V
    //   188: aload 7
    //   190: bipush 38
    //   192: invokevirtual 98	java/io/ByteArrayOutputStream:write	(I)V
    //   195: aload_0
    //   196: invokestatic 102	net/youmi/android/c/a:b	(Landroid/content/Context;)Ljava/lang/String;
    //   199: aload 7
    //   201: invokestatic 95	net/youmi/android/b/a/c:a	(Ljava/lang/String;Ljava/io/ByteArrayOutputStream;)V
    //   204: aload 7
    //   206: bipush 38
    //   208: invokevirtual 98	java/io/ByteArrayOutputStream:write	(I)V
    //   211: aload_0
    //   212: invokestatic 105	net/youmi/android/c/a:g	(Landroid/content/Context;)Ljava/lang/String;
    //   215: aload 7
    //   217: invokestatic 95	net/youmi/android/b/a/c:a	(Ljava/lang/String;Ljava/io/ByteArrayOutputStream;)V
    //   220: aload 7
    //   222: bipush 38
    //   224: invokevirtual 98	java/io/ByteArrayOutputStream:write	(I)V
    //   227: iload_1
    //   228: invokestatic 169	java/lang/Integer:toString	(I)Ljava/lang/String;
    //   231: aload 7
    //   233: invokestatic 95	net/youmi/android/b/a/c:a	(Ljava/lang/String;Ljava/io/ByteArrayOutputStream;)V
    //   236: aload 7
    //   238: bipush 38
    //   240: invokevirtual 98	java/io/ByteArrayOutputStream:write	(I)V
    //   243: aload_2
    //   244: aload 7
    //   246: invokestatic 95	net/youmi/android/b/a/c:a	(Ljava/lang/String;Ljava/io/ByteArrayOutputStream;)V
    //   249: new 44	java/lang/StringBuilder
    //   252: dup
    //   253: invokespecial 47	java/lang/StringBuilder:<init>	()V
    //   256: ldc 195
    //   258: invokevirtual 55	java/lang/StringBuilder:append	(Ljava/lang/String;)Ljava/lang/StringBuilder;
    //   261: aload_0
    //   262: invokestatic 196	net/youmi/android/b/b/a:b	(Landroid/content/Context;)Ljava/lang/String;
    //   265: invokevirtual 55	java/lang/StringBuilder:append	(Ljava/lang/String;)Ljava/lang/StringBuilder;
    //   268: aload 8
    //   270: invokevirtual 55	java/lang/StringBuilder:append	(Ljava/lang/String;)Ljava/lang/StringBuilder;
    //   273: invokevirtual 66	java/lang/StringBuilder:toString	()Ljava/lang/String;
    //   276: invokestatic 199	net/youmi/android/c/c/e:a	(Ljava/lang/String;)Ljava/lang/String;
    //   279: astore_0
    //   280: aload 6
    //   282: aload 7
    //   284: invokevirtual 203	java/io/ByteArrayOutputStream:toByteArray	()[B
    //   287: aload_0
    //   288: ldc 204
    //   290: invokestatic 207	net/youmi/android/b/a/a:a	([BLjava/lang/String;I)Ljava/lang/String;
    //   293: invokevirtual 55	java/lang/StringBuilder:append	(Ljava/lang/String;)Ljava/lang/StringBuilder;
    //   296: pop
    //   297: aload 6
    //   299: invokevirtual 66	java/lang/StringBuilder:toString	()Ljava/lang/String;
    //   302: astore_0
    //   303: aload_0
    //   304: areturn
    //   305: ldc 210
    //   307: astore 5
    //   309: goto -196 -> 113
    //   312: astore_2
    //   313: goto -64 -> 249
    //   316: astore_0
    //   317: aconst_null
    //   318: areturn
    //   319: astore_0
    //   320: goto -23 -> 297
    //   323: astore 5
    //   325: goto -89 -> 236
    //   328: astore 5
    //   330: goto -110 -> 220
    //   333: astore 5
    //   335: goto -131 -> 204
    //   338: astore 5
    //   340: goto -152 -> 188
    //   343: astore 5
    //   345: goto -174 -> 171
    //   348: astore 5
    //   350: goto -196 -> 154
    //   353: astore 5
    //   355: goto -218 -> 137
    //   358: astore 5
    //   360: goto -240 -> 120
    // Local variable table:
    //   start	length	slot	name	signature
    //   0	363	0	paramContext	Context
    //   0	363	1	paramInt	int
    //   0	363	2	paramString	String
    //   25	1	3	l	long
    //   111	197	5	str1	String
    //   323	1	5	localThrowable1	Throwable
    //   328	1	5	localThrowable2	Throwable
    //   333	1	5	localThrowable3	Throwable
    //   338	1	5	localThrowable4	Throwable
    //   343	1	5	localThrowable5	Throwable
    //   348	1	5	localThrowable6	Throwable
    //   353	1	5	localThrowable7	Throwable
    //   358	1	5	localThrowable8	Throwable
    //   16	282	6	localStringBuilder	java.lang.StringBuilder
    //   75	208	7	localByteArrayOutputStream	java.io.ByteArrayOutputStream
    //   30	239	8	str2	String
    //   85	94	9	localb	net.youmi.android.b.a.b
    // Exception table:
    //   from	to	target	type
    //   243	249	312	java/lang/Throwable
    //   6	101	316	java/lang/Throwable
    //   120	127	316	java/lang/Throwable
    //   137	144	316	java/lang/Throwable
    //   154	161	316	java/lang/Throwable
    //   171	178	316	java/lang/Throwable
    //   188	195	316	java/lang/Throwable
    //   204	211	316	java/lang/Throwable
    //   220	227	316	java/lang/Throwable
    //   236	243	316	java/lang/Throwable
    //   249	280	316	java/lang/Throwable
    //   297	303	316	java/lang/Throwable
    //   280	297	319	java/lang/Throwable
    //   227	236	323	java/lang/Throwable
    //   211	220	328	java/lang/Throwable
    //   195	204	333	java/lang/Throwable
    //   178	188	338	java/lang/Throwable
    //   161	171	343	java/lang/Throwable
    //   144	154	348	java/lang/Throwable
    //   127	137	353	java/lang/Throwable
    //   101	109	358	java/lang/Throwable
    //   113	120	358	java/lang/Throwable
  }
  
  public static String a(Context paramContext, String paramString)
  {
    if ((paramContext == null) || (paramString == null)) {
      return null;
    }
    try
    {
      c localc = new c();
      localc.a(paramString);
      paramContext = new d(paramContext, localc);
      paramContext.c();
      paramContext = paramContext.d();
      return paramContext;
    }
    catch (Throwable paramContext) {}
    return null;
  }
  
  /* Error */
  public static String a(Context paramContext, String paramString1, String paramString2, int paramInt)
  {
    // Byte code:
    //   0: aload_1
    //   1: ifnonnull +5 -> 6
    //   4: aconst_null
    //   5: areturn
    //   6: aload_0
    //   7: invokestatic 26	net/youmi/android/b/b/a:c	(Landroid/content/Context;)Z
    //   10: ifeq -6 -> 4
    //   13: new 44	java/lang/StringBuilder
    //   16: dup
    //   17: sipush 512
    //   20: invokespecial 212	java/lang/StringBuilder:<init>	(I)V
    //   23: astore 6
    //   25: invokestatic 188	java/lang/System:currentTimeMillis	()J
    //   28: ldc2_w 189
    //   31: ldiv
    //   32: lstore 4
    //   34: iconst_4
    //   35: invokestatic 70	net/youmi/android/b/a/a:a	(I)Ljava/lang/String;
    //   38: astore 7
    //   40: new 28	net/youmi/android/b/a/b
    //   43: dup
    //   44: aload_0
    //   45: invokespecial 32	net/youmi/android/b/a/b:<init>	(Landroid/content/Context;)V
    //   48: astore 11
    //   50: aload_0
    //   51: invokestatic 133	net/youmi/android/c/k/d:a	(Landroid/content/Context;)Lnet/youmi/android/c/k/d;
    //   54: astore 10
    //   56: aload_0
    //   57: invokestatic 157	net/youmi/android/a/i/a:a	(Landroid/content/Context;)Lnet/youmi/android/a/i/a;
    //   60: invokevirtual 160	net/youmi/android/a/i/a:a	()Landroid/location/Location;
    //   63: astore 9
    //   65: aload 6
    //   67: aload_1
    //   68: invokevirtual 55	java/lang/StringBuilder:append	(Ljava/lang/String;)Ljava/lang/StringBuilder;
    //   71: ldc 80
    //   73: invokevirtual 55	java/lang/StringBuilder:append	(Ljava/lang/String;)Ljava/lang/StringBuilder;
    //   76: pop
    //   77: aload 6
    //   79: ldc 82
    //   81: invokevirtual 55	java/lang/StringBuilder:append	(Ljava/lang/String;)Ljava/lang/StringBuilder;
    //   84: pop
    //   85: aload 6
    //   87: iconst_3
    //   88: invokevirtual 215	java/lang/StringBuilder:append	(I)Ljava/lang/StringBuilder;
    //   91: pop
    //   92: aload 6
    //   94: aload_0
    //   95: invokestatic 34	net/youmi/android/b/b/a:a	(Landroid/content/Context;)Ljava/lang/String;
    //   98: invokevirtual 55	java/lang/StringBuilder:append	(Ljava/lang/String;)Ljava/lang/StringBuilder;
    //   101: pop
    //   102: aload 6
    //   104: aload 7
    //   106: invokevirtual 55	java/lang/StringBuilder:append	(Ljava/lang/String;)Ljava/lang/StringBuilder;
    //   109: pop
    //   110: new 87	java/io/ByteArrayOutputStream
    //   113: dup
    //   114: sipush 512
    //   117: invokespecial 88	java/io/ByteArrayOutputStream:<init>	(I)V
    //   120: astore 8
    //   122: ldc 239
    //   124: aload 8
    //   126: invokestatic 95	net/youmi/android/b/a/c:a	(Ljava/lang/String;Ljava/io/ByteArrayOutputStream;)V
    //   129: aload 8
    //   131: bipush 38
    //   133: invokevirtual 98	java/io/ByteArrayOutputStream:write	(I)V
    //   136: aload 11
    //   138: invokevirtual 113	net/youmi/android/b/a/b:d	()Ljava/lang/String;
    //   141: aload 8
    //   143: invokestatic 95	net/youmi/android/b/a/c:a	(Ljava/lang/String;Ljava/io/ByteArrayOutputStream;)V
    //   146: aload 8
    //   148: bipush 38
    //   150: invokevirtual 98	java/io/ByteArrayOutputStream:write	(I)V
    //   153: aload 11
    //   155: invokevirtual 116	net/youmi/android/b/a/b:c	()Ljava/lang/String;
    //   158: aload 8
    //   160: invokestatic 95	net/youmi/android/b/a/c:a	(Ljava/lang/String;Ljava/io/ByteArrayOutputStream;)V
    //   163: aload 8
    //   165: bipush 38
    //   167: invokevirtual 98	java/io/ByteArrayOutputStream:write	(I)V
    //   170: aload 11
    //   172: invokevirtual 108	net/youmi/android/b/a/b:b	()Ljava/lang/String;
    //   175: aload 8
    //   177: invokestatic 95	net/youmi/android/b/a/c:a	(Ljava/lang/String;Ljava/io/ByteArrayOutputStream;)V
    //   180: aload 8
    //   182: bipush 38
    //   184: invokevirtual 98	java/io/ByteArrayOutputStream:write	(I)V
    //   187: aload 11
    //   189: invokevirtual 106	net/youmi/android/b/a/b:a	()Ljava/lang/String;
    //   192: aload 8
    //   194: invokestatic 95	net/youmi/android/b/a/c:a	(Ljava/lang/String;Ljava/io/ByteArrayOutputStream;)V
    //   197: aload 8
    //   199: bipush 38
    //   201: invokevirtual 98	java/io/ByteArrayOutputStream:write	(I)V
    //   204: aload_0
    //   205: invokestatic 102	net/youmi/android/c/a:b	(Landroid/content/Context;)Ljava/lang/String;
    //   208: aload 8
    //   210: invokestatic 95	net/youmi/android/b/a/c:a	(Ljava/lang/String;Ljava/io/ByteArrayOutputStream;)V
    //   213: aload 8
    //   215: bipush 38
    //   217: invokevirtual 98	java/io/ByteArrayOutputStream:write	(I)V
    //   220: aload_0
    //   221: invokestatic 105	net/youmi/android/c/a:g	(Landroid/content/Context;)Ljava/lang/String;
    //   224: aload 8
    //   226: invokestatic 95	net/youmi/android/b/a/c:a	(Ljava/lang/String;Ljava/io/ByteArrayOutputStream;)V
    //   229: aload 8
    //   231: bipush 38
    //   233: invokevirtual 98	java/io/ByteArrayOutputStream:write	(I)V
    //   236: invokestatic 111	net/youmi/android/c/a:d	()Ljava/lang/String;
    //   239: aload 8
    //   241: invokestatic 95	net/youmi/android/b/a/c:a	(Ljava/lang/String;Ljava/io/ByteArrayOutputStream;)V
    //   244: aload 8
    //   246: bipush 38
    //   248: invokevirtual 98	java/io/ByteArrayOutputStream:write	(I)V
    //   251: invokestatic 112	net/youmi/android/c/a:b	()Ljava/lang/String;
    //   254: aload 8
    //   256: invokestatic 95	net/youmi/android/b/a/c:a	(Ljava/lang/String;Ljava/io/ByteArrayOutputStream;)V
    //   259: aload 8
    //   261: bipush 38
    //   263: invokevirtual 98	java/io/ByteArrayOutputStream:write	(I)V
    //   266: invokestatic 115	net/youmi/android/c/a:c	()Ljava/lang/String;
    //   269: aload 8
    //   271: invokestatic 95	net/youmi/android/b/a/c:a	(Ljava/lang/String;Ljava/io/ByteArrayOutputStream;)V
    //   274: aload 8
    //   276: bipush 38
    //   278: invokevirtual 98	java/io/ByteArrayOutputStream:write	(I)V
    //   281: getstatic 176	android/os/Build:BOARD	Ljava/lang/String;
    //   284: aload 8
    //   286: invokestatic 95	net/youmi/android/b/a/c:a	(Ljava/lang/String;Ljava/io/ByteArrayOutputStream;)V
    //   289: aload 8
    //   291: bipush 38
    //   293: invokevirtual 98	java/io/ByteArrayOutputStream:write	(I)V
    //   296: getstatic 179	android/os/Build:BRAND	Ljava/lang/String;
    //   299: aload 8
    //   301: invokestatic 95	net/youmi/android/b/a/c:a	(Ljava/lang/String;Ljava/io/ByteArrayOutputStream;)V
    //   304: aload 8
    //   306: bipush 38
    //   308: invokevirtual 98	java/io/ByteArrayOutputStream:write	(I)V
    //   311: getstatic 182	android/os/Build:DEVICE	Ljava/lang/String;
    //   314: aload 8
    //   316: invokestatic 95	net/youmi/android/b/a/c:a	(Ljava/lang/String;Ljava/io/ByteArrayOutputStream;)V
    //   319: aload 8
    //   321: bipush 38
    //   323: invokevirtual 98	java/io/ByteArrayOutputStream:write	(I)V
    //   326: aload 11
    //   328: invokevirtual 221	net/youmi/android/b/a/b:e	()Z
    //   331: ifeq +440 -> 771
    //   334: ldc 149
    //   336: astore_1
    //   337: aload_1
    //   338: aload 8
    //   340: invokestatic 95	net/youmi/android/b/a/c:a	(Ljava/lang/String;Ljava/io/ByteArrayOutputStream;)V
    //   343: aload 8
    //   345: bipush 38
    //   347: invokevirtual 98	java/io/ByteArrayOutputStream:write	(I)V
    //   350: aload 10
    //   352: invokevirtual 241	net/youmi/android/c/k/d:g	()I
    //   355: invokestatic 169	java/lang/Integer:toString	(I)Ljava/lang/String;
    //   358: aload 8
    //   360: invokestatic 95	net/youmi/android/b/a/c:a	(Ljava/lang/String;Ljava/io/ByteArrayOutputStream;)V
    //   363: aload 8
    //   365: bipush 38
    //   367: invokevirtual 98	java/io/ByteArrayOutputStream:write	(I)V
    //   370: aload 10
    //   372: invokevirtual 244	net/youmi/android/c/k/d:h	()I
    //   375: invokestatic 169	java/lang/Integer:toString	(I)Ljava/lang/String;
    //   378: aload 8
    //   380: invokestatic 95	net/youmi/android/b/a/c:a	(Ljava/lang/String;Ljava/io/ByteArrayOutputStream;)V
    //   383: aload 8
    //   385: bipush 38
    //   387: invokevirtual 98	java/io/ByteArrayOutputStream:write	(I)V
    //   390: aload 10
    //   392: invokevirtual 246	net/youmi/android/c/k/d:e	()I
    //   395: invokestatic 169	java/lang/Integer:toString	(I)Ljava/lang/String;
    //   398: aload 8
    //   400: invokestatic 95	net/youmi/android/b/a/c:a	(Ljava/lang/String;Ljava/io/ByteArrayOutputStream;)V
    //   403: aload 8
    //   405: bipush 38
    //   407: invokevirtual 98	java/io/ByteArrayOutputStream:write	(I)V
    //   410: iload_3
    //   411: invokestatic 169	java/lang/Integer:toString	(I)Ljava/lang/String;
    //   414: aload 8
    //   416: invokestatic 95	net/youmi/android/b/a/c:a	(Ljava/lang/String;Ljava/io/ByteArrayOutputStream;)V
    //   419: aload 8
    //   421: bipush 38
    //   423: invokevirtual 98	java/io/ByteArrayOutputStream:write	(I)V
    //   426: aload_0
    //   427: invokevirtual 251	android/content/Context:getPackageName	()Ljava/lang/String;
    //   430: aload 8
    //   432: invokestatic 95	net/youmi/android/b/a/c:a	(Ljava/lang/String;Ljava/io/ByteArrayOutputStream;)V
    //   435: aload 8
    //   437: bipush 38
    //   439: invokevirtual 98	java/io/ByteArrayOutputStream:write	(I)V
    //   442: aload_0
    //   443: invokestatic 253	net/youmi/android/b/b/a:d	(Landroid/content/Context;)Ljava/lang/String;
    //   446: aload 8
    //   448: invokestatic 95	net/youmi/android/b/a/c:a	(Ljava/lang/String;Ljava/io/ByteArrayOutputStream;)V
    //   451: aload 8
    //   453: bipush 38
    //   455: invokevirtual 98	java/io/ByteArrayOutputStream:write	(I)V
    //   458: aload_0
    //   459: invokestatic 256	net/youmi/android/b/b/a:e	(Landroid/content/Context;)I
    //   462: invokestatic 169	java/lang/Integer:toString	(I)Ljava/lang/String;
    //   465: aload 8
    //   467: invokestatic 95	net/youmi/android/b/a/c:a	(Ljava/lang/String;Ljava/io/ByteArrayOutputStream;)V
    //   470: aload 8
    //   472: bipush 38
    //   474: invokevirtual 98	java/io/ByteArrayOutputStream:write	(I)V
    //   477: aload_0
    //   478: invokestatic 259	net/youmi/android/b/b/a:f	(Landroid/content/Context;)I
    //   481: invokestatic 169	java/lang/Integer:toString	(I)Ljava/lang/String;
    //   484: aload 8
    //   486: invokestatic 95	net/youmi/android/b/a/c:a	(Ljava/lang/String;Ljava/io/ByteArrayOutputStream;)V
    //   489: aload 8
    //   491: bipush 38
    //   493: invokevirtual 98	java/io/ByteArrayOutputStream:write	(I)V
    //   496: aload_0
    //   497: invokestatic 170	net/youmi/android/b/b/a:g	(Landroid/content/Context;)Ljava/lang/String;
    //   500: astore_1
    //   501: aload_1
    //   502: ifnull +9 -> 511
    //   505: aload_1
    //   506: aload 8
    //   508: invokestatic 95	net/youmi/android/b/a/c:a	(Ljava/lang/String;Ljava/io/ByteArrayOutputStream;)V
    //   511: aload 8
    //   513: bipush 38
    //   515: invokevirtual 98	java/io/ByteArrayOutputStream:write	(I)V
    //   518: aload_0
    //   519: invokestatic 163	net/youmi/android/c/h/b:a	(Landroid/content/Context;)Ljava/lang/String;
    //   522: aload 8
    //   524: invokestatic 95	net/youmi/android/b/a/c:a	(Ljava/lang/String;Ljava/io/ByteArrayOutputStream;)V
    //   527: aload 8
    //   529: bipush 38
    //   531: invokevirtual 98	java/io/ByteArrayOutputStream:write	(I)V
    //   534: aload_0
    //   535: invokestatic 262	net/youmi/android/c/a:i	(Landroid/content/Context;)Ljava/lang/String;
    //   538: aload 8
    //   540: invokestatic 95	net/youmi/android/b/a/c:a	(Ljava/lang/String;Ljava/io/ByteArrayOutputStream;)V
    //   543: aload 8
    //   545: bipush 38
    //   547: invokevirtual 98	java/io/ByteArrayOutputStream:write	(I)V
    //   550: aload 9
    //   552: ifnull +16 -> 568
    //   555: aload 9
    //   557: invokevirtual 268	android/location/Location:getLatitude	()D
    //   560: invokestatic 273	java/lang/Double:toString	(D)Ljava/lang/String;
    //   563: aload 8
    //   565: invokestatic 95	net/youmi/android/b/a/c:a	(Ljava/lang/String;Ljava/io/ByteArrayOutputStream;)V
    //   568: aload 8
    //   570: bipush 38
    //   572: invokevirtual 98	java/io/ByteArrayOutputStream:write	(I)V
    //   575: aload 9
    //   577: ifnull +16 -> 593
    //   580: aload 9
    //   582: invokevirtual 276	android/location/Location:getLongitude	()D
    //   585: invokestatic 273	java/lang/Double:toString	(D)Ljava/lang/String;
    //   588: aload 8
    //   590: invokestatic 95	net/youmi/android/b/a/c:a	(Ljava/lang/String;Ljava/io/ByteArrayOutputStream;)V
    //   593: aload 8
    //   595: bipush 38
    //   597: invokevirtual 98	java/io/ByteArrayOutputStream:write	(I)V
    //   600: aload 8
    //   602: bipush 38
    //   604: invokevirtual 98	java/io/ByteArrayOutputStream:write	(I)V
    //   607: aload_0
    //   608: invokestatic 147	net/youmi/android/c/k/k:a	(Landroid/content/Context;)Z
    //   611: ifeq +166 -> 777
    //   614: ldc 149
    //   616: astore_1
    //   617: aload_1
    //   618: aload 8
    //   620: invokestatic 95	net/youmi/android/b/a/c:a	(Ljava/lang/String;Ljava/io/ByteArrayOutputStream;)V
    //   623: aload 8
    //   625: bipush 38
    //   627: invokevirtual 98	java/io/ByteArrayOutputStream:write	(I)V
    //   630: lload 4
    //   632: invokestatic 280	java/lang/Long:toString	(J)Ljava/lang/String;
    //   635: aload 8
    //   637: invokestatic 95	net/youmi/android/b/a/c:a	(Ljava/lang/String;Ljava/io/ByteArrayOutputStream;)V
    //   640: aload 8
    //   642: bipush 38
    //   644: invokevirtual 98	java/io/ByteArrayOutputStream:write	(I)V
    //   647: invokestatic 122	java/util/Locale:getDefault	()Ljava/util/Locale;
    //   650: invokevirtual 125	java/util/Locale:getCountry	()Ljava/lang/String;
    //   653: aload 8
    //   655: invokestatic 95	net/youmi/android/b/a/c:a	(Ljava/lang/String;Ljava/io/ByteArrayOutputStream;)V
    //   658: aload 8
    //   660: bipush 38
    //   662: invokevirtual 98	java/io/ByteArrayOutputStream:write	(I)V
    //   665: invokestatic 122	java/util/Locale:getDefault	()Ljava/util/Locale;
    //   668: invokevirtual 128	java/util/Locale:getLanguage	()Ljava/lang/String;
    //   671: aload 8
    //   673: invokestatic 95	net/youmi/android/b/a/c:a	(Ljava/lang/String;Ljava/io/ByteArrayOutputStream;)V
    //   676: aload 8
    //   678: bipush 38
    //   680: invokevirtual 98	java/io/ByteArrayOutputStream:write	(I)V
    //   683: invokestatic 282	net/youmi/android/b/b/a:b	()Z
    //   686: ifeq +97 -> 783
    //   689: ldc 149
    //   691: astore_1
    //   692: aload_1
    //   693: aload 8
    //   695: invokestatic 95	net/youmi/android/b/a/c:a	(Ljava/lang/String;Ljava/io/ByteArrayOutputStream;)V
    //   698: aload 8
    //   700: bipush 38
    //   702: invokevirtual 98	java/io/ByteArrayOutputStream:write	(I)V
    //   705: aload_2
    //   706: ifnull +9 -> 715
    //   709: aload_2
    //   710: aload 8
    //   712: invokestatic 95	net/youmi/android/b/a/c:a	(Ljava/lang/String;Ljava/io/ByteArrayOutputStream;)V
    //   715: new 44	java/lang/StringBuilder
    //   718: dup
    //   719: invokespecial 47	java/lang/StringBuilder:<init>	()V
    //   722: ldc 195
    //   724: invokevirtual 55	java/lang/StringBuilder:append	(Ljava/lang/String;)Ljava/lang/StringBuilder;
    //   727: aload_0
    //   728: invokestatic 196	net/youmi/android/b/b/a:b	(Landroid/content/Context;)Ljava/lang/String;
    //   731: invokevirtual 55	java/lang/StringBuilder:append	(Ljava/lang/String;)Ljava/lang/StringBuilder;
    //   734: aload 7
    //   736: invokevirtual 55	java/lang/StringBuilder:append	(Ljava/lang/String;)Ljava/lang/StringBuilder;
    //   739: invokevirtual 66	java/lang/StringBuilder:toString	()Ljava/lang/String;
    //   742: invokestatic 199	net/youmi/android/c/c/e:a	(Ljava/lang/String;)Ljava/lang/String;
    //   745: astore_0
    //   746: aload 6
    //   748: aload 8
    //   750: invokevirtual 203	java/io/ByteArrayOutputStream:toByteArray	()[B
    //   753: aload_0
    //   754: ldc 204
    //   756: invokestatic 207	net/youmi/android/b/a/a:a	([BLjava/lang/String;I)Ljava/lang/String;
    //   759: invokevirtual 55	java/lang/StringBuilder:append	(Ljava/lang/String;)Ljava/lang/StringBuilder;
    //   762: pop
    //   763: aload 6
    //   765: invokevirtual 66	java/lang/StringBuilder:toString	()Ljava/lang/String;
    //   768: astore_0
    //   769: aload_0
    //   770: areturn
    //   771: ldc 210
    //   773: astore_1
    //   774: goto -437 -> 337
    //   777: ldc 210
    //   779: astore_1
    //   780: goto -163 -> 617
    //   783: ldc 210
    //   785: astore_1
    //   786: goto -94 -> 692
    //   789: astore_0
    //   790: aload_0
    //   791: athrow
    //   792: astore_1
    //   793: goto -78 -> 715
    //   796: astore_0
    //   797: aconst_null
    //   798: areturn
    //   799: astore_0
    //   800: goto -37 -> 763
    //   803: astore_1
    //   804: goto -106 -> 698
    //   807: astore_1
    //   808: goto -132 -> 676
    //   811: astore_1
    //   812: goto -154 -> 658
    //   815: astore_1
    //   816: goto -176 -> 640
    //   819: astore_1
    //   820: goto -197 -> 623
    //   823: astore_1
    //   824: goto -231 -> 593
    //   827: astore_1
    //   828: goto -260 -> 568
    //   831: astore_1
    //   832: goto -289 -> 543
    //   835: astore_1
    //   836: goto -309 -> 527
    //   839: astore_1
    //   840: goto -329 -> 511
    //   843: astore_1
    //   844: goto -355 -> 489
    //   847: astore_1
    //   848: goto -378 -> 470
    //   851: astore_1
    //   852: goto -401 -> 451
    //   855: astore_1
    //   856: goto -421 -> 435
    //   859: astore_1
    //   860: goto -441 -> 419
    //   863: astore_1
    //   864: goto -461 -> 403
    //   867: astore_1
    //   868: goto -485 -> 383
    //   871: astore_1
    //   872: goto -509 -> 363
    //   875: astore_1
    //   876: goto -533 -> 343
    //   879: astore_1
    //   880: goto -561 -> 319
    //   883: astore_1
    //   884: goto -580 -> 304
    //   887: astore_1
    //   888: goto -599 -> 289
    //   891: astore_1
    //   892: goto -618 -> 274
    //   895: astore_1
    //   896: goto -637 -> 259
    //   899: astore_1
    //   900: goto -656 -> 244
    //   903: astore_1
    //   904: goto -675 -> 229
    //   907: astore_1
    //   908: goto -695 -> 213
    //   911: astore_1
    //   912: goto -715 -> 197
    //   915: astore_1
    //   916: goto -736 -> 180
    //   919: astore_1
    //   920: goto -757 -> 163
    //   923: astore_1
    //   924: goto -778 -> 146
    // Local variable table:
    //   start	length	slot	name	signature
    //   0	927	0	paramContext	Context
    //   0	927	1	paramString1	String
    //   0	927	2	paramString2	String
    //   0	927	3	paramInt	int
    //   32	599	4	l	long
    //   23	741	6	localStringBuilder	java.lang.StringBuilder
    //   38	697	7	str	String
    //   120	629	8	localByteArrayOutputStream	java.io.ByteArrayOutputStream
    //   63	518	9	localLocation	android.location.Location
    //   54	337	10	locald	net.youmi.android.c.k.d
    //   48	279	11	localb	net.youmi.android.b.a.b
    // Exception table:
    //   from	to	target	type
    //   6	136	789	finally
    //   136	146	789	finally
    //   146	153	789	finally
    //   153	163	789	finally
    //   163	170	789	finally
    //   170	180	789	finally
    //   180	187	789	finally
    //   187	197	789	finally
    //   197	204	789	finally
    //   204	213	789	finally
    //   213	220	789	finally
    //   220	229	789	finally
    //   229	236	789	finally
    //   236	244	789	finally
    //   244	251	789	finally
    //   251	259	789	finally
    //   259	266	789	finally
    //   266	274	789	finally
    //   274	281	789	finally
    //   281	289	789	finally
    //   289	296	789	finally
    //   296	304	789	finally
    //   304	311	789	finally
    //   311	319	789	finally
    //   319	326	789	finally
    //   326	334	789	finally
    //   337	343	789	finally
    //   343	350	789	finally
    //   350	363	789	finally
    //   363	370	789	finally
    //   370	383	789	finally
    //   383	390	789	finally
    //   390	403	789	finally
    //   403	410	789	finally
    //   410	419	789	finally
    //   419	426	789	finally
    //   426	435	789	finally
    //   435	442	789	finally
    //   442	451	789	finally
    //   451	458	789	finally
    //   458	470	789	finally
    //   470	477	789	finally
    //   477	489	789	finally
    //   489	496	789	finally
    //   496	501	789	finally
    //   505	511	789	finally
    //   511	518	789	finally
    //   518	527	789	finally
    //   527	534	789	finally
    //   534	543	789	finally
    //   543	550	789	finally
    //   555	568	789	finally
    //   568	575	789	finally
    //   580	593	789	finally
    //   593	607	789	finally
    //   607	614	789	finally
    //   617	623	789	finally
    //   623	630	789	finally
    //   630	640	789	finally
    //   640	647	789	finally
    //   647	658	789	finally
    //   658	665	789	finally
    //   665	676	789	finally
    //   676	683	789	finally
    //   683	689	789	finally
    //   692	698	789	finally
    //   698	705	789	finally
    //   709	715	789	finally
    //   715	746	789	finally
    //   746	763	789	finally
    //   763	769	789	finally
    //   709	715	792	java/lang/Throwable
    //   6	136	796	java/lang/Throwable
    //   146	153	796	java/lang/Throwable
    //   163	170	796	java/lang/Throwable
    //   180	187	796	java/lang/Throwable
    //   197	204	796	java/lang/Throwable
    //   213	220	796	java/lang/Throwable
    //   229	236	796	java/lang/Throwable
    //   244	251	796	java/lang/Throwable
    //   259	266	796	java/lang/Throwable
    //   274	281	796	java/lang/Throwable
    //   289	296	796	java/lang/Throwable
    //   304	311	796	java/lang/Throwable
    //   319	326	796	java/lang/Throwable
    //   343	350	796	java/lang/Throwable
    //   363	370	796	java/lang/Throwable
    //   383	390	796	java/lang/Throwable
    //   403	410	796	java/lang/Throwable
    //   419	426	796	java/lang/Throwable
    //   435	442	796	java/lang/Throwable
    //   451	458	796	java/lang/Throwable
    //   470	477	796	java/lang/Throwable
    //   489	496	796	java/lang/Throwable
    //   511	518	796	java/lang/Throwable
    //   527	534	796	java/lang/Throwable
    //   543	550	796	java/lang/Throwable
    //   568	575	796	java/lang/Throwable
    //   593	607	796	java/lang/Throwable
    //   623	630	796	java/lang/Throwable
    //   640	647	796	java/lang/Throwable
    //   658	665	796	java/lang/Throwable
    //   676	683	796	java/lang/Throwable
    //   698	705	796	java/lang/Throwable
    //   715	746	796	java/lang/Throwable
    //   763	769	796	java/lang/Throwable
    //   746	763	799	java/lang/Throwable
    //   683	689	803	java/lang/Throwable
    //   692	698	803	java/lang/Throwable
    //   665	676	807	java/lang/Throwable
    //   647	658	811	java/lang/Throwable
    //   630	640	815	java/lang/Throwable
    //   607	614	819	java/lang/Throwable
    //   617	623	819	java/lang/Throwable
    //   580	593	823	java/lang/Throwable
    //   555	568	827	java/lang/Throwable
    //   534	543	831	java/lang/Throwable
    //   518	527	835	java/lang/Throwable
    //   496	501	839	java/lang/Throwable
    //   505	511	839	java/lang/Throwable
    //   477	489	843	java/lang/Throwable
    //   458	470	847	java/lang/Throwable
    //   442	451	851	java/lang/Throwable
    //   426	435	855	java/lang/Throwable
    //   410	419	859	java/lang/Throwable
    //   390	403	863	java/lang/Throwable
    //   370	383	867	java/lang/Throwable
    //   350	363	871	java/lang/Throwable
    //   326	334	875	java/lang/Throwable
    //   337	343	875	java/lang/Throwable
    //   311	319	879	java/lang/Throwable
    //   296	304	883	java/lang/Throwable
    //   281	289	887	java/lang/Throwable
    //   266	274	891	java/lang/Throwable
    //   251	259	895	java/lang/Throwable
    //   236	244	899	java/lang/Throwable
    //   220	229	903	java/lang/Throwable
    //   204	213	907	java/lang/Throwable
    //   187	197	911	java/lang/Throwable
    //   170	180	915	java/lang/Throwable
    //   153	163	919	java/lang/Throwable
    //   136	146	923	java/lang/Throwable
  }
  
  /* Error */
  public static String a(Context paramContext, net.youmi.android.a.h.j paramj)
  {
    // Byte code:
    //   0: aload_1
    //   1: ifnonnull +5 -> 6
    //   4: aconst_null
    //   5: areturn
    //   6: aload_1
    //   7: invokevirtual 286	net/youmi/android/a/h/j:e	()Z
    //   10: ifeq -6 -> 4
    //   13: aload_0
    //   14: invokestatic 26	net/youmi/android/b/b/a:c	(Landroid/content/Context;)Z
    //   17: ifeq -13 -> 4
    //   20: new 44	java/lang/StringBuilder
    //   23: dup
    //   24: sipush 512
    //   27: invokespecial 212	java/lang/StringBuilder:<init>	(I)V
    //   30: astore 4
    //   32: invokestatic 188	java/lang/System:currentTimeMillis	()J
    //   35: ldc2_w 189
    //   38: ldiv
    //   39: lstore_2
    //   40: aload 4
    //   42: aload_1
    //   43: invokevirtual 287	net/youmi/android/a/h/j:a	()Ljava/lang/String;
    //   46: invokevirtual 55	java/lang/StringBuilder:append	(Ljava/lang/String;)Ljava/lang/StringBuilder;
    //   49: ldc 80
    //   51: invokevirtual 55	java/lang/StringBuilder:append	(Ljava/lang/String;)Ljava/lang/StringBuilder;
    //   54: pop
    //   55: aload 4
    //   57: ldc 82
    //   59: invokevirtual 55	java/lang/StringBuilder:append	(Ljava/lang/String;)Ljava/lang/StringBuilder;
    //   62: pop
    //   63: aload 4
    //   65: iconst_3
    //   66: invokevirtual 215	java/lang/StringBuilder:append	(I)Ljava/lang/StringBuilder;
    //   69: pop
    //   70: aload 4
    //   72: aload_0
    //   73: invokestatic 34	net/youmi/android/b/b/a:a	(Landroid/content/Context;)Ljava/lang/String;
    //   76: invokevirtual 55	java/lang/StringBuilder:append	(Ljava/lang/String;)Ljava/lang/StringBuilder;
    //   79: pop
    //   80: aload 4
    //   82: aload_1
    //   83: invokevirtual 288	net/youmi/android/a/h/j:b	()Ljava/lang/String;
    //   86: invokevirtual 55	java/lang/StringBuilder:append	(Ljava/lang/String;)Ljava/lang/StringBuilder;
    //   89: pop
    //   90: new 87	java/io/ByteArrayOutputStream
    //   93: dup
    //   94: sipush 512
    //   97: invokespecial 88	java/io/ByteArrayOutputStream:<init>	(I)V
    //   100: astore 5
    //   102: ldc_w 290
    //   105: aload 5
    //   107: invokestatic 95	net/youmi/android/b/a/c:a	(Ljava/lang/String;Ljava/io/ByteArrayOutputStream;)V
    //   110: aload 5
    //   112: bipush 38
    //   114: invokevirtual 98	java/io/ByteArrayOutputStream:write	(I)V
    //   117: lload_2
    //   118: invokestatic 280	java/lang/Long:toString	(J)Ljava/lang/String;
    //   121: aload 5
    //   123: invokestatic 95	net/youmi/android/b/a/c:a	(Ljava/lang/String;Ljava/io/ByteArrayOutputStream;)V
    //   126: aload 5
    //   128: bipush 38
    //   130: invokevirtual 98	java/io/ByteArrayOutputStream:write	(I)V
    //   133: aload_1
    //   134: invokevirtual 291	net/youmi/android/a/h/j:d	()Ljava/lang/String;
    //   137: ifnull +12 -> 149
    //   140: aload_1
    //   141: invokevirtual 291	net/youmi/android/a/h/j:d	()Ljava/lang/String;
    //   144: aload 5
    //   146: invokestatic 95	net/youmi/android/b/a/c:a	(Ljava/lang/String;Ljava/io/ByteArrayOutputStream;)V
    //   149: new 44	java/lang/StringBuilder
    //   152: dup
    //   153: invokespecial 47	java/lang/StringBuilder:<init>	()V
    //   156: ldc 195
    //   158: invokevirtual 55	java/lang/StringBuilder:append	(Ljava/lang/String;)Ljava/lang/StringBuilder;
    //   161: aload_0
    //   162: invokestatic 196	net/youmi/android/b/b/a:b	(Landroid/content/Context;)Ljava/lang/String;
    //   165: invokevirtual 55	java/lang/StringBuilder:append	(Ljava/lang/String;)Ljava/lang/StringBuilder;
    //   168: aload_1
    //   169: invokevirtual 288	net/youmi/android/a/h/j:b	()Ljava/lang/String;
    //   172: invokevirtual 55	java/lang/StringBuilder:append	(Ljava/lang/String;)Ljava/lang/StringBuilder;
    //   175: invokevirtual 66	java/lang/StringBuilder:toString	()Ljava/lang/String;
    //   178: invokestatic 199	net/youmi/android/c/c/e:a	(Ljava/lang/String;)Ljava/lang/String;
    //   181: astore_0
    //   182: aload 4
    //   184: aload 5
    //   186: invokevirtual 203	java/io/ByteArrayOutputStream:toByteArray	()[B
    //   189: aload_0
    //   190: ldc 204
    //   192: invokestatic 207	net/youmi/android/b/a/a:a	([BLjava/lang/String;I)Ljava/lang/String;
    //   195: invokevirtual 55	java/lang/StringBuilder:append	(Ljava/lang/String;)Ljava/lang/StringBuilder;
    //   198: pop
    //   199: aload 4
    //   201: bipush 44
    //   203: invokevirtual 294	java/lang/StringBuilder:append	(C)Ljava/lang/StringBuilder;
    //   206: pop
    //   207: aload 4
    //   209: aload_1
    //   210: invokevirtual 295	net/youmi/android/a/h/j:c	()Ljava/lang/String;
    //   213: invokevirtual 55	java/lang/StringBuilder:append	(Ljava/lang/String;)Ljava/lang/StringBuilder;
    //   216: pop
    //   217: aload 4
    //   219: invokevirtual 66	java/lang/StringBuilder:toString	()Ljava/lang/String;
    //   222: astore_0
    //   223: aload_0
    //   224: areturn
    //   225: astore_0
    //   226: aconst_null
    //   227: areturn
    //   228: astore_0
    //   229: goto -12 -> 217
    //   232: astore 6
    //   234: goto -85 -> 149
    //   237: astore 6
    //   239: goto -113 -> 126
    // Local variable table:
    //   start	length	slot	name	signature
    //   0	242	0	paramContext	Context
    //   0	242	1	paramj	net.youmi.android.a.h.j
    //   39	79	2	l	long
    //   30	188	4	localStringBuilder	java.lang.StringBuilder
    //   100	85	5	localByteArrayOutputStream	java.io.ByteArrayOutputStream
    //   232	1	6	localThrowable1	Throwable
    //   237	1	6	localThrowable2	Throwable
    // Exception table:
    //   from	to	target	type
    //   6	117	225	java/lang/Throwable
    //   126	133	225	java/lang/Throwable
    //   149	182	225	java/lang/Throwable
    //   217	223	225	java/lang/Throwable
    //   182	217	228	java/lang/Throwable
    //   133	149	232	java/lang/Throwable
    //   117	126	237	java/lang/Throwable
  }
  
  /* Error */
  public static String a(Context paramContext, net.youmi.android.a.h.j paramj, int paramInt)
  {
    // Byte code:
    //   0: aload_1
    //   1: ifnonnull +5 -> 6
    //   4: aconst_null
    //   5: areturn
    //   6: aload_1
    //   7: invokevirtual 286	net/youmi/android/a/h/j:e	()Z
    //   10: ifeq -6 -> 4
    //   13: aload_0
    //   14: invokestatic 26	net/youmi/android/b/b/a:c	(Landroid/content/Context;)Z
    //   17: ifeq -13 -> 4
    //   20: new 44	java/lang/StringBuilder
    //   23: dup
    //   24: sipush 512
    //   27: invokespecial 212	java/lang/StringBuilder:<init>	(I)V
    //   30: astore 5
    //   32: invokestatic 188	java/lang/System:currentTimeMillis	()J
    //   35: ldc2_w 189
    //   38: ldiv
    //   39: lstore_3
    //   40: aload 5
    //   42: aload_1
    //   43: invokevirtual 287	net/youmi/android/a/h/j:a	()Ljava/lang/String;
    //   46: invokevirtual 55	java/lang/StringBuilder:append	(Ljava/lang/String;)Ljava/lang/StringBuilder;
    //   49: ldc 80
    //   51: invokevirtual 55	java/lang/StringBuilder:append	(Ljava/lang/String;)Ljava/lang/StringBuilder;
    //   54: pop
    //   55: aload 5
    //   57: ldc 82
    //   59: invokevirtual 55	java/lang/StringBuilder:append	(Ljava/lang/String;)Ljava/lang/StringBuilder;
    //   62: pop
    //   63: aload 5
    //   65: iconst_3
    //   66: invokevirtual 215	java/lang/StringBuilder:append	(I)Ljava/lang/StringBuilder;
    //   69: pop
    //   70: aload 5
    //   72: aload_0
    //   73: invokestatic 34	net/youmi/android/b/b/a:a	(Landroid/content/Context;)Ljava/lang/String;
    //   76: invokevirtual 55	java/lang/StringBuilder:append	(Ljava/lang/String;)Ljava/lang/StringBuilder;
    //   79: pop
    //   80: aload 5
    //   82: aload_1
    //   83: invokevirtual 288	net/youmi/android/a/h/j:b	()Ljava/lang/String;
    //   86: invokevirtual 55	java/lang/StringBuilder:append	(Ljava/lang/String;)Ljava/lang/StringBuilder;
    //   89: pop
    //   90: new 87	java/io/ByteArrayOutputStream
    //   93: dup
    //   94: sipush 512
    //   97: invokespecial 88	java/io/ByteArrayOutputStream:<init>	(I)V
    //   100: astore 6
    //   102: ldc_w 298
    //   105: aload 6
    //   107: invokestatic 95	net/youmi/android/b/a/c:a	(Ljava/lang/String;Ljava/io/ByteArrayOutputStream;)V
    //   110: aload 6
    //   112: bipush 38
    //   114: invokevirtual 98	java/io/ByteArrayOutputStream:write	(I)V
    //   117: lload_3
    //   118: invokestatic 280	java/lang/Long:toString	(J)Ljava/lang/String;
    //   121: aload 6
    //   123: invokestatic 95	net/youmi/android/b/a/c:a	(Ljava/lang/String;Ljava/io/ByteArrayOutputStream;)V
    //   126: aload 6
    //   128: bipush 38
    //   130: invokevirtual 98	java/io/ByteArrayOutputStream:write	(I)V
    //   133: iload_2
    //   134: invokestatic 169	java/lang/Integer:toString	(I)Ljava/lang/String;
    //   137: aload 6
    //   139: invokestatic 95	net/youmi/android/b/a/c:a	(Ljava/lang/String;Ljava/io/ByteArrayOutputStream;)V
    //   142: aload 6
    //   144: bipush 38
    //   146: invokevirtual 98	java/io/ByteArrayOutputStream:write	(I)V
    //   149: aload_1
    //   150: invokevirtual 291	net/youmi/android/a/h/j:d	()Ljava/lang/String;
    //   153: ifnull +12 -> 165
    //   156: aload_1
    //   157: invokevirtual 291	net/youmi/android/a/h/j:d	()Ljava/lang/String;
    //   160: aload 6
    //   162: invokestatic 95	net/youmi/android/b/a/c:a	(Ljava/lang/String;Ljava/io/ByteArrayOutputStream;)V
    //   165: new 44	java/lang/StringBuilder
    //   168: dup
    //   169: invokespecial 47	java/lang/StringBuilder:<init>	()V
    //   172: ldc 195
    //   174: invokevirtual 55	java/lang/StringBuilder:append	(Ljava/lang/String;)Ljava/lang/StringBuilder;
    //   177: aload_0
    //   178: invokestatic 196	net/youmi/android/b/b/a:b	(Landroid/content/Context;)Ljava/lang/String;
    //   181: invokevirtual 55	java/lang/StringBuilder:append	(Ljava/lang/String;)Ljava/lang/StringBuilder;
    //   184: aload_1
    //   185: invokevirtual 288	net/youmi/android/a/h/j:b	()Ljava/lang/String;
    //   188: invokevirtual 55	java/lang/StringBuilder:append	(Ljava/lang/String;)Ljava/lang/StringBuilder;
    //   191: invokevirtual 66	java/lang/StringBuilder:toString	()Ljava/lang/String;
    //   194: invokestatic 199	net/youmi/android/c/c/e:a	(Ljava/lang/String;)Ljava/lang/String;
    //   197: astore_0
    //   198: aload 5
    //   200: aload 6
    //   202: invokevirtual 203	java/io/ByteArrayOutputStream:toByteArray	()[B
    //   205: aload_0
    //   206: ldc 204
    //   208: invokestatic 207	net/youmi/android/b/a/a:a	([BLjava/lang/String;I)Ljava/lang/String;
    //   211: invokevirtual 55	java/lang/StringBuilder:append	(Ljava/lang/String;)Ljava/lang/StringBuilder;
    //   214: pop
    //   215: aload 5
    //   217: bipush 44
    //   219: invokevirtual 294	java/lang/StringBuilder:append	(C)Ljava/lang/StringBuilder;
    //   222: pop
    //   223: aload 5
    //   225: aload_1
    //   226: invokevirtual 295	net/youmi/android/a/h/j:c	()Ljava/lang/String;
    //   229: invokevirtual 55	java/lang/StringBuilder:append	(Ljava/lang/String;)Ljava/lang/StringBuilder;
    //   232: pop
    //   233: aload 5
    //   235: invokevirtual 66	java/lang/StringBuilder:toString	()Ljava/lang/String;
    //   238: astore_0
    //   239: aload_0
    //   240: areturn
    //   241: astore_0
    //   242: aconst_null
    //   243: areturn
    //   244: astore_0
    //   245: goto -12 -> 233
    //   248: astore 7
    //   250: goto -85 -> 165
    //   253: astore 7
    //   255: goto -113 -> 142
    //   258: astore 7
    //   260: goto -134 -> 126
    // Local variable table:
    //   start	length	slot	name	signature
    //   0	263	0	paramContext	Context
    //   0	263	1	paramj	net.youmi.android.a.h.j
    //   0	263	2	paramInt	int
    //   39	79	3	l	long
    //   30	204	5	localStringBuilder	java.lang.StringBuilder
    //   100	101	6	localByteArrayOutputStream	java.io.ByteArrayOutputStream
    //   248	1	7	localThrowable1	Throwable
    //   253	1	7	localThrowable2	Throwable
    //   258	1	7	localThrowable3	Throwable
    // Exception table:
    //   from	to	target	type
    //   6	117	241	java/lang/Throwable
    //   126	133	241	java/lang/Throwable
    //   142	149	241	java/lang/Throwable
    //   165	198	241	java/lang/Throwable
    //   233	239	241	java/lang/Throwable
    //   198	233	244	java/lang/Throwable
    //   149	165	248	java/lang/Throwable
    //   133	142	253	java/lang/Throwable
    //   117	126	258	java/lang/Throwable
  }
}


/* Location:           C:\Users\guanghui\Desktop\\37\classes-dex2jar.jar
 * Qualified Name:     net.youmi.android.d.b.a
 * JD-Core Version:    0.7.0.1
 */