package net.youmi.android.a.h.c.b;

import android.content.Context;
import java.util.ArrayList;
import net.youmi.android.a.h.e;
import org.json.JSONArray;

public class d
  implements Runnable
{
  Context a;
  JSONArray b;
  private ArrayList c;
  private String d;
  private long e;
  private String f;
  private e g;
  
  public d(Context paramContext, e parame, ArrayList paramArrayList, String paramString1, long paramLong, String paramString2)
  {
    this.a = paramContext;
    this.c = paramArrayList;
    this.d = paramString1;
    this.e = paramLong;
    this.f = paramString2;
    this.g = parame;
  }
  
  /* Error */
  public void run()
  {
    // Byte code:
    //   0: aload_0
    //   1: getfield 26	net/youmi/android/a/h/c/b/d:a	Landroid/content/Context;
    //   4: astore 4
    //   6: aload 4
    //   8: ifnonnull +110 -> 118
    //   11: aload_0
    //   12: getfield 30	net/youmi/android/a/h/c/b/d:d	Ljava/lang/String;
    //   15: ifnull +102 -> 117
    //   18: aload_0
    //   19: getfield 42	net/youmi/android/a/h/c/b/d:b	Lorg/json/JSONArray;
    //   22: ifnull +95 -> 117
    //   25: aload_0
    //   26: getfield 42	net/youmi/android/a/h/c/b/d:b	Lorg/json/JSONArray;
    //   29: invokevirtual 48	org/json/JSONArray:length	()I
    //   32: ifle +85 -> 117
    //   35: aload_0
    //   36: getfield 42	net/youmi/android/a/h/c/b/d:b	Lorg/json/JSONArray;
    //   39: invokevirtual 52	org/json/JSONArray:toString	()Ljava/lang/String;
    //   42: astore 4
    //   44: new 54	java/lang/StringBuilder
    //   47: dup
    //   48: aload 4
    //   50: invokevirtual 57	java/lang/String:length	()I
    //   53: iconst_2
    //   54: imul
    //   55: invokespecial 60	java/lang/StringBuilder:<init>	(I)V
    //   58: astore 5
    //   60: aload 5
    //   62: ldc 62
    //   64: invokevirtual 66	java/lang/StringBuilder:append	(Ljava/lang/String;)Ljava/lang/StringBuilder;
    //   67: aload_0
    //   68: getfield 30	net/youmi/android/a/h/c/b/d:d	Ljava/lang/String;
    //   71: invokevirtual 66	java/lang/StringBuilder:append	(Ljava/lang/String;)Ljava/lang/StringBuilder;
    //   74: ldc 68
    //   76: invokevirtual 66	java/lang/StringBuilder:append	(Ljava/lang/String;)Ljava/lang/StringBuilder;
    //   79: aload_0
    //   80: getfield 32	net/youmi/android/a/h/c/b/d:e	J
    //   83: invokevirtual 71	java/lang/StringBuilder:append	(J)Ljava/lang/StringBuilder;
    //   86: ldc 73
    //   88: invokevirtual 66	java/lang/StringBuilder:append	(Ljava/lang/String;)Ljava/lang/StringBuilder;
    //   91: aload 4
    //   93: invokevirtual 66	java/lang/StringBuilder:append	(Ljava/lang/String;)Ljava/lang/StringBuilder;
    //   96: ldc 75
    //   98: invokevirtual 66	java/lang/StringBuilder:append	(Ljava/lang/String;)Ljava/lang/StringBuilder;
    //   101: pop
    //   102: invokestatic 80	net/youmi/android/a/h/c/b/a:a	()Lnet/youmi/android/a/h/c/b/a;
    //   105: aload_0
    //   106: getfield 34	net/youmi/android/a/h/c/b/d:f	Ljava/lang/String;
    //   109: aload 5
    //   111: invokevirtual 81	java/lang/StringBuilder:toString	()Ljava/lang/String;
    //   114: invokevirtual 84	net/youmi/android/a/h/c/b/a:a	(Ljava/lang/String;Ljava/lang/String;)V
    //   117: return
    //   118: aload_0
    //   119: getfield 28	net/youmi/android/a/h/c/b/d:c	Ljava/util/ArrayList;
    //   122: astore 4
    //   124: aload 4
    //   126: ifnonnull +113 -> 239
    //   129: aload_0
    //   130: getfield 30	net/youmi/android/a/h/c/b/d:d	Ljava/lang/String;
    //   133: ifnull -16 -> 117
    //   136: aload_0
    //   137: getfield 42	net/youmi/android/a/h/c/b/d:b	Lorg/json/JSONArray;
    //   140: ifnull -23 -> 117
    //   143: aload_0
    //   144: getfield 42	net/youmi/android/a/h/c/b/d:b	Lorg/json/JSONArray;
    //   147: invokevirtual 48	org/json/JSONArray:length	()I
    //   150: ifle -33 -> 117
    //   153: aload_0
    //   154: getfield 42	net/youmi/android/a/h/c/b/d:b	Lorg/json/JSONArray;
    //   157: invokevirtual 52	org/json/JSONArray:toString	()Ljava/lang/String;
    //   160: astore 4
    //   162: new 54	java/lang/StringBuilder
    //   165: dup
    //   166: aload 4
    //   168: invokevirtual 57	java/lang/String:length	()I
    //   171: iconst_2
    //   172: imul
    //   173: invokespecial 60	java/lang/StringBuilder:<init>	(I)V
    //   176: astore 5
    //   178: aload 5
    //   180: ldc 62
    //   182: invokevirtual 66	java/lang/StringBuilder:append	(Ljava/lang/String;)Ljava/lang/StringBuilder;
    //   185: aload_0
    //   186: getfield 30	net/youmi/android/a/h/c/b/d:d	Ljava/lang/String;
    //   189: invokevirtual 66	java/lang/StringBuilder:append	(Ljava/lang/String;)Ljava/lang/StringBuilder;
    //   192: ldc 68
    //   194: invokevirtual 66	java/lang/StringBuilder:append	(Ljava/lang/String;)Ljava/lang/StringBuilder;
    //   197: aload_0
    //   198: getfield 32	net/youmi/android/a/h/c/b/d:e	J
    //   201: invokevirtual 71	java/lang/StringBuilder:append	(J)Ljava/lang/StringBuilder;
    //   204: ldc 73
    //   206: invokevirtual 66	java/lang/StringBuilder:append	(Ljava/lang/String;)Ljava/lang/StringBuilder;
    //   209: aload 4
    //   211: invokevirtual 66	java/lang/StringBuilder:append	(Ljava/lang/String;)Ljava/lang/StringBuilder;
    //   214: ldc 75
    //   216: invokevirtual 66	java/lang/StringBuilder:append	(Ljava/lang/String;)Ljava/lang/StringBuilder;
    //   219: pop
    //   220: invokestatic 80	net/youmi/android/a/h/c/b/a:a	()Lnet/youmi/android/a/h/c/b/a;
    //   223: aload_0
    //   224: getfield 34	net/youmi/android/a/h/c/b/d:f	Ljava/lang/String;
    //   227: aload 5
    //   229: invokevirtual 81	java/lang/StringBuilder:toString	()Ljava/lang/String;
    //   232: invokevirtual 84	net/youmi/android/a/h/c/b/a:a	(Ljava/lang/String;Ljava/lang/String;)V
    //   235: return
    //   236: astore 4
    //   238: return
    //   239: aload_0
    //   240: getfield 28	net/youmi/android/a/h/c/b/d:c	Ljava/util/ArrayList;
    //   243: invokevirtual 89	java/util/ArrayList:size	()I
    //   246: istore_1
    //   247: iload_1
    //   248: ifne +113 -> 361
    //   251: aload_0
    //   252: getfield 30	net/youmi/android/a/h/c/b/d:d	Ljava/lang/String;
    //   255: ifnull -138 -> 117
    //   258: aload_0
    //   259: getfield 42	net/youmi/android/a/h/c/b/d:b	Lorg/json/JSONArray;
    //   262: ifnull -145 -> 117
    //   265: aload_0
    //   266: getfield 42	net/youmi/android/a/h/c/b/d:b	Lorg/json/JSONArray;
    //   269: invokevirtual 48	org/json/JSONArray:length	()I
    //   272: ifle -155 -> 117
    //   275: aload_0
    //   276: getfield 42	net/youmi/android/a/h/c/b/d:b	Lorg/json/JSONArray;
    //   279: invokevirtual 52	org/json/JSONArray:toString	()Ljava/lang/String;
    //   282: astore 4
    //   284: new 54	java/lang/StringBuilder
    //   287: dup
    //   288: aload 4
    //   290: invokevirtual 57	java/lang/String:length	()I
    //   293: iconst_2
    //   294: imul
    //   295: invokespecial 60	java/lang/StringBuilder:<init>	(I)V
    //   298: astore 5
    //   300: aload 5
    //   302: ldc 62
    //   304: invokevirtual 66	java/lang/StringBuilder:append	(Ljava/lang/String;)Ljava/lang/StringBuilder;
    //   307: aload_0
    //   308: getfield 30	net/youmi/android/a/h/c/b/d:d	Ljava/lang/String;
    //   311: invokevirtual 66	java/lang/StringBuilder:append	(Ljava/lang/String;)Ljava/lang/StringBuilder;
    //   314: ldc 68
    //   316: invokevirtual 66	java/lang/StringBuilder:append	(Ljava/lang/String;)Ljava/lang/StringBuilder;
    //   319: aload_0
    //   320: getfield 32	net/youmi/android/a/h/c/b/d:e	J
    //   323: invokevirtual 71	java/lang/StringBuilder:append	(J)Ljava/lang/StringBuilder;
    //   326: ldc 73
    //   328: invokevirtual 66	java/lang/StringBuilder:append	(Ljava/lang/String;)Ljava/lang/StringBuilder;
    //   331: aload 4
    //   333: invokevirtual 66	java/lang/StringBuilder:append	(Ljava/lang/String;)Ljava/lang/StringBuilder;
    //   336: ldc 75
    //   338: invokevirtual 66	java/lang/StringBuilder:append	(Ljava/lang/String;)Ljava/lang/StringBuilder;
    //   341: pop
    //   342: invokestatic 80	net/youmi/android/a/h/c/b/a:a	()Lnet/youmi/android/a/h/c/b/a;
    //   345: aload_0
    //   346: getfield 34	net/youmi/android/a/h/c/b/d:f	Ljava/lang/String;
    //   349: aload 5
    //   351: invokevirtual 81	java/lang/StringBuilder:toString	()Ljava/lang/String;
    //   354: invokevirtual 84	net/youmi/android/a/h/c/b/a:a	(Ljava/lang/String;Ljava/lang/String;)V
    //   357: return
    //   358: astore 4
    //   360: return
    //   361: aload_0
    //   362: getfield 26	net/youmi/android/a/h/c/b/d:a	Landroid/content/Context;
    //   365: aload_0
    //   366: getfield 36	net/youmi/android/a/h/c/b/d:g	Lnet/youmi/android/a/h/e;
    //   369: aload_0
    //   370: getfield 28	net/youmi/android/a/h/c/b/d:c	Ljava/util/ArrayList;
    //   373: invokestatic 94	net/youmi/android/a/a/e:a	(Landroid/content/Context;Lnet/youmi/android/a/h/e;Ljava/util/List;)V
    //   376: aload_0
    //   377: getfield 30	net/youmi/android/a/h/c/b/d:d	Ljava/lang/String;
    //   380: astore 4
    //   382: aload 4
    //   384: ifnonnull +113 -> 497
    //   387: aload_0
    //   388: getfield 30	net/youmi/android/a/h/c/b/d:d	Ljava/lang/String;
    //   391: ifnull -274 -> 117
    //   394: aload_0
    //   395: getfield 42	net/youmi/android/a/h/c/b/d:b	Lorg/json/JSONArray;
    //   398: ifnull -281 -> 117
    //   401: aload_0
    //   402: getfield 42	net/youmi/android/a/h/c/b/d:b	Lorg/json/JSONArray;
    //   405: invokevirtual 48	org/json/JSONArray:length	()I
    //   408: ifle -291 -> 117
    //   411: aload_0
    //   412: getfield 42	net/youmi/android/a/h/c/b/d:b	Lorg/json/JSONArray;
    //   415: invokevirtual 52	org/json/JSONArray:toString	()Ljava/lang/String;
    //   418: astore 4
    //   420: new 54	java/lang/StringBuilder
    //   423: dup
    //   424: aload 4
    //   426: invokevirtual 57	java/lang/String:length	()I
    //   429: iconst_2
    //   430: imul
    //   431: invokespecial 60	java/lang/StringBuilder:<init>	(I)V
    //   434: astore 5
    //   436: aload 5
    //   438: ldc 62
    //   440: invokevirtual 66	java/lang/StringBuilder:append	(Ljava/lang/String;)Ljava/lang/StringBuilder;
    //   443: aload_0
    //   444: getfield 30	net/youmi/android/a/h/c/b/d:d	Ljava/lang/String;
    //   447: invokevirtual 66	java/lang/StringBuilder:append	(Ljava/lang/String;)Ljava/lang/StringBuilder;
    //   450: ldc 68
    //   452: invokevirtual 66	java/lang/StringBuilder:append	(Ljava/lang/String;)Ljava/lang/StringBuilder;
    //   455: aload_0
    //   456: getfield 32	net/youmi/android/a/h/c/b/d:e	J
    //   459: invokevirtual 71	java/lang/StringBuilder:append	(J)Ljava/lang/StringBuilder;
    //   462: ldc 73
    //   464: invokevirtual 66	java/lang/StringBuilder:append	(Ljava/lang/String;)Ljava/lang/StringBuilder;
    //   467: aload 4
    //   469: invokevirtual 66	java/lang/StringBuilder:append	(Ljava/lang/String;)Ljava/lang/StringBuilder;
    //   472: ldc 75
    //   474: invokevirtual 66	java/lang/StringBuilder:append	(Ljava/lang/String;)Ljava/lang/StringBuilder;
    //   477: pop
    //   478: invokestatic 80	net/youmi/android/a/h/c/b/a:a	()Lnet/youmi/android/a/h/c/b/a;
    //   481: aload_0
    //   482: getfield 34	net/youmi/android/a/h/c/b/d:f	Ljava/lang/String;
    //   485: aload 5
    //   487: invokevirtual 81	java/lang/StringBuilder:toString	()Ljava/lang/String;
    //   490: invokevirtual 84	net/youmi/android/a/h/c/b/a:a	(Ljava/lang/String;Ljava/lang/String;)V
    //   493: return
    //   494: astore 4
    //   496: return
    //   497: aload_0
    //   498: getfield 28	net/youmi/android/a/h/c/b/d:c	Ljava/util/ArrayList;
    //   501: invokevirtual 89	java/util/ArrayList:size	()I
    //   504: istore_3
    //   505: iconst_0
    //   506: istore_1
    //   507: iload_1
    //   508: iload_3
    //   509: if_icmpge +242 -> 751
    //   512: aload_0
    //   513: getfield 28	net/youmi/android/a/h/c/b/d:c	Ljava/util/ArrayList;
    //   516: iload_1
    //   517: invokevirtual 98	java/util/ArrayList:get	(I)Ljava/lang/Object;
    //   520: checkcast 100	net/youmi/android/a/a/a/a
    //   523: astore 4
    //   525: aload 4
    //   527: ifnonnull +10 -> 537
    //   530: iload_1
    //   531: iconst_1
    //   532: iadd
    //   533: istore_1
    //   534: goto -27 -> 507
    //   537: aload 4
    //   539: invokevirtual 103	net/youmi/android/a/a/a/a:g	()Lnet/youmi/android/a/a/a/g;
    //   542: ifnull -12 -> 530
    //   545: aload 4
    //   547: invokevirtual 103	net/youmi/android/a/a/a/a:g	()Lnet/youmi/android/a/a/a/g;
    //   550: invokevirtual 107	net/youmi/android/a/a/a/g:c	()Ljava/lang/String;
    //   553: ifnull -23 -> 530
    //   556: aload 4
    //   558: invokevirtual 110	net/youmi/android/a/a/a/a:e	()Lnet/youmi/android/a/a/a/f;
    //   561: ifnonnull +15 -> 576
    //   564: aload 4
    //   566: new 112	net/youmi/android/a/a/a/f
    //   569: dup
    //   570: invokespecial 113	net/youmi/android/a/a/a/f:<init>	()V
    //   573: invokevirtual 116	net/youmi/android/a/a/a/a:a	(Lnet/youmi/android/a/a/a/f;)V
    //   576: aload_0
    //   577: getfield 30	net/youmi/android/a/h/c/b/d:d	Ljava/lang/String;
    //   580: ifnull -50 -> 530
    //   583: aload_0
    //   584: getfield 42	net/youmi/android/a/h/c/b/d:b	Lorg/json/JSONArray;
    //   587: ifnonnull +14 -> 601
    //   590: aload_0
    //   591: new 44	org/json/JSONArray
    //   594: dup
    //   595: invokespecial 117	org/json/JSONArray:<init>	()V
    //   598: putfield 42	net/youmi/android/a/h/c/b/d:b	Lorg/json/JSONArray;
    //   601: new 119	org/json/JSONObject
    //   604: dup
    //   605: invokespecial 120	org/json/JSONObject:<init>	()V
    //   608: astore 5
    //   610: aload 5
    //   612: ldc 121
    //   614: aload 4
    //   616: invokevirtual 103	net/youmi/android/a/a/a/a:g	()Lnet/youmi/android/a/a/a/g;
    //   619: invokevirtual 107	net/youmi/android/a/a/a/g:c	()Ljava/lang/String;
    //   622: invokevirtual 125	org/json/JSONObject:put	(Ljava/lang/String;Ljava/lang/Object;)Lorg/json/JSONObject;
    //   625: pop
    //   626: aload 5
    //   628: ldc 126
    //   630: aload 4
    //   632: invokevirtual 128	net/youmi/android/a/a/a/a:a	()I
    //   635: invokevirtual 131	org/json/JSONObject:put	(Ljava/lang/String;I)Lorg/json/JSONObject;
    //   638: pop
    //   639: aload 4
    //   641: invokevirtual 110	net/youmi/android/a/a/a/a:e	()Lnet/youmi/android/a/a/a/f;
    //   644: invokevirtual 134	net/youmi/android/a/a/a/f:b	()Z
    //   647: ifeq +94 -> 741
    //   650: iconst_1
    //   651: istore_2
    //   652: aload 5
    //   654: ldc 135
    //   656: iload_2
    //   657: invokevirtual 131	org/json/JSONObject:put	(Ljava/lang/String;I)Lorg/json/JSONObject;
    //   660: pop
    //   661: aload 4
    //   663: invokevirtual 110	net/youmi/android/a/a/a/a:e	()Lnet/youmi/android/a/a/a/f;
    //   666: invokevirtual 137	net/youmi/android/a/a/a/f:a	()Z
    //   669: ifeq +77 -> 746
    //   672: iconst_1
    //   673: istore_2
    //   674: aload 5
    //   676: ldc 138
    //   678: iload_2
    //   679: invokevirtual 131	org/json/JSONObject:put	(Ljava/lang/String;I)Lorg/json/JSONObject;
    //   682: pop
    //   683: aload 5
    //   685: ldc 139
    //   687: aload 4
    //   689: invokevirtual 110	net/youmi/android/a/a/a/a:e	()Lnet/youmi/android/a/a/a/f;
    //   692: invokevirtual 141	net/youmi/android/a/a/a/f:c	()I
    //   695: invokevirtual 131	org/json/JSONObject:put	(Ljava/lang/String;I)Lorg/json/JSONObject;
    //   698: pop
    //   699: aload 4
    //   701: invokevirtual 145	net/youmi/android/a/a/a/a:l	()Lnet/youmi/android/a/a/a/d;
    //   704: ifnull +19 -> 723
    //   707: aload 5
    //   709: ldc 146
    //   711: aload 4
    //   713: invokevirtual 145	net/youmi/android/a/a/a/a:l	()Lnet/youmi/android/a/a/a/d;
    //   716: invokevirtual 150	net/youmi/android/a/a/a/d:b	()I
    //   719: invokevirtual 131	org/json/JSONObject:put	(Ljava/lang/String;I)Lorg/json/JSONObject;
    //   722: pop
    //   723: aload_0
    //   724: getfield 42	net/youmi/android/a/h/c/b/d:b	Lorg/json/JSONArray;
    //   727: aload 5
    //   729: invokevirtual 153	org/json/JSONArray:put	(Ljava/lang/Object;)Lorg/json/JSONArray;
    //   732: pop
    //   733: goto -203 -> 530
    //   736: astore 4
    //   738: goto -208 -> 530
    //   741: iconst_0
    //   742: istore_2
    //   743: goto -91 -> 652
    //   746: iconst_0
    //   747: istore_2
    //   748: goto -74 -> 674
    //   751: aload_0
    //   752: getfield 30	net/youmi/android/a/h/c/b/d:d	Ljava/lang/String;
    //   755: ifnull -638 -> 117
    //   758: aload_0
    //   759: getfield 42	net/youmi/android/a/h/c/b/d:b	Lorg/json/JSONArray;
    //   762: ifnull -645 -> 117
    //   765: aload_0
    //   766: getfield 42	net/youmi/android/a/h/c/b/d:b	Lorg/json/JSONArray;
    //   769: invokevirtual 48	org/json/JSONArray:length	()I
    //   772: ifle -655 -> 117
    //   775: aload_0
    //   776: getfield 42	net/youmi/android/a/h/c/b/d:b	Lorg/json/JSONArray;
    //   779: invokevirtual 52	org/json/JSONArray:toString	()Ljava/lang/String;
    //   782: astore 4
    //   784: new 54	java/lang/StringBuilder
    //   787: dup
    //   788: aload 4
    //   790: invokevirtual 57	java/lang/String:length	()I
    //   793: iconst_2
    //   794: imul
    //   795: invokespecial 60	java/lang/StringBuilder:<init>	(I)V
    //   798: astore 5
    //   800: aload 5
    //   802: ldc 62
    //   804: invokevirtual 66	java/lang/StringBuilder:append	(Ljava/lang/String;)Ljava/lang/StringBuilder;
    //   807: aload_0
    //   808: getfield 30	net/youmi/android/a/h/c/b/d:d	Ljava/lang/String;
    //   811: invokevirtual 66	java/lang/StringBuilder:append	(Ljava/lang/String;)Ljava/lang/StringBuilder;
    //   814: ldc 68
    //   816: invokevirtual 66	java/lang/StringBuilder:append	(Ljava/lang/String;)Ljava/lang/StringBuilder;
    //   819: aload_0
    //   820: getfield 32	net/youmi/android/a/h/c/b/d:e	J
    //   823: invokevirtual 71	java/lang/StringBuilder:append	(J)Ljava/lang/StringBuilder;
    //   826: ldc 73
    //   828: invokevirtual 66	java/lang/StringBuilder:append	(Ljava/lang/String;)Ljava/lang/StringBuilder;
    //   831: aload 4
    //   833: invokevirtual 66	java/lang/StringBuilder:append	(Ljava/lang/String;)Ljava/lang/StringBuilder;
    //   836: ldc 75
    //   838: invokevirtual 66	java/lang/StringBuilder:append	(Ljava/lang/String;)Ljava/lang/StringBuilder;
    //   841: pop
    //   842: invokestatic 80	net/youmi/android/a/h/c/b/a:a	()Lnet/youmi/android/a/h/c/b/a;
    //   845: aload_0
    //   846: getfield 34	net/youmi/android/a/h/c/b/d:f	Ljava/lang/String;
    //   849: aload 5
    //   851: invokevirtual 81	java/lang/StringBuilder:toString	()Ljava/lang/String;
    //   854: invokevirtual 84	net/youmi/android/a/h/c/b/a:a	(Ljava/lang/String;Ljava/lang/String;)V
    //   857: return
    //   858: astore 4
    //   860: return
    //   861: astore 4
    //   863: aload_0
    //   864: getfield 30	net/youmi/android/a/h/c/b/d:d	Ljava/lang/String;
    //   867: ifnull -750 -> 117
    //   870: aload_0
    //   871: getfield 42	net/youmi/android/a/h/c/b/d:b	Lorg/json/JSONArray;
    //   874: ifnull -757 -> 117
    //   877: aload_0
    //   878: getfield 42	net/youmi/android/a/h/c/b/d:b	Lorg/json/JSONArray;
    //   881: invokevirtual 48	org/json/JSONArray:length	()I
    //   884: ifle -767 -> 117
    //   887: aload_0
    //   888: getfield 42	net/youmi/android/a/h/c/b/d:b	Lorg/json/JSONArray;
    //   891: invokevirtual 52	org/json/JSONArray:toString	()Ljava/lang/String;
    //   894: astore 4
    //   896: new 54	java/lang/StringBuilder
    //   899: dup
    //   900: aload 4
    //   902: invokevirtual 57	java/lang/String:length	()I
    //   905: iconst_2
    //   906: imul
    //   907: invokespecial 60	java/lang/StringBuilder:<init>	(I)V
    //   910: astore 5
    //   912: aload 5
    //   914: ldc 62
    //   916: invokevirtual 66	java/lang/StringBuilder:append	(Ljava/lang/String;)Ljava/lang/StringBuilder;
    //   919: aload_0
    //   920: getfield 30	net/youmi/android/a/h/c/b/d:d	Ljava/lang/String;
    //   923: invokevirtual 66	java/lang/StringBuilder:append	(Ljava/lang/String;)Ljava/lang/StringBuilder;
    //   926: ldc 68
    //   928: invokevirtual 66	java/lang/StringBuilder:append	(Ljava/lang/String;)Ljava/lang/StringBuilder;
    //   931: aload_0
    //   932: getfield 32	net/youmi/android/a/h/c/b/d:e	J
    //   935: invokevirtual 71	java/lang/StringBuilder:append	(J)Ljava/lang/StringBuilder;
    //   938: ldc 73
    //   940: invokevirtual 66	java/lang/StringBuilder:append	(Ljava/lang/String;)Ljava/lang/StringBuilder;
    //   943: aload 4
    //   945: invokevirtual 66	java/lang/StringBuilder:append	(Ljava/lang/String;)Ljava/lang/StringBuilder;
    //   948: ldc 75
    //   950: invokevirtual 66	java/lang/StringBuilder:append	(Ljava/lang/String;)Ljava/lang/StringBuilder;
    //   953: pop
    //   954: invokestatic 80	net/youmi/android/a/h/c/b/a:a	()Lnet/youmi/android/a/h/c/b/a;
    //   957: aload_0
    //   958: getfield 34	net/youmi/android/a/h/c/b/d:f	Ljava/lang/String;
    //   961: aload 5
    //   963: invokevirtual 81	java/lang/StringBuilder:toString	()Ljava/lang/String;
    //   966: invokevirtual 84	net/youmi/android/a/h/c/b/a:a	(Ljava/lang/String;Ljava/lang/String;)V
    //   969: return
    //   970: astore 4
    //   972: return
    //   973: astore 4
    //   975: aload_0
    //   976: getfield 30	net/youmi/android/a/h/c/b/d:d	Ljava/lang/String;
    //   979: ifnull +102 -> 1081
    //   982: aload_0
    //   983: getfield 42	net/youmi/android/a/h/c/b/d:b	Lorg/json/JSONArray;
    //   986: ifnull +95 -> 1081
    //   989: aload_0
    //   990: getfield 42	net/youmi/android/a/h/c/b/d:b	Lorg/json/JSONArray;
    //   993: invokevirtual 48	org/json/JSONArray:length	()I
    //   996: ifle +85 -> 1081
    //   999: aload_0
    //   1000: getfield 42	net/youmi/android/a/h/c/b/d:b	Lorg/json/JSONArray;
    //   1003: invokevirtual 52	org/json/JSONArray:toString	()Ljava/lang/String;
    //   1006: astore 5
    //   1008: new 54	java/lang/StringBuilder
    //   1011: dup
    //   1012: aload 5
    //   1014: invokevirtual 57	java/lang/String:length	()I
    //   1017: iconst_2
    //   1018: imul
    //   1019: invokespecial 60	java/lang/StringBuilder:<init>	(I)V
    //   1022: astore 6
    //   1024: aload 6
    //   1026: ldc 62
    //   1028: invokevirtual 66	java/lang/StringBuilder:append	(Ljava/lang/String;)Ljava/lang/StringBuilder;
    //   1031: aload_0
    //   1032: getfield 30	net/youmi/android/a/h/c/b/d:d	Ljava/lang/String;
    //   1035: invokevirtual 66	java/lang/StringBuilder:append	(Ljava/lang/String;)Ljava/lang/StringBuilder;
    //   1038: ldc 68
    //   1040: invokevirtual 66	java/lang/StringBuilder:append	(Ljava/lang/String;)Ljava/lang/StringBuilder;
    //   1043: aload_0
    //   1044: getfield 32	net/youmi/android/a/h/c/b/d:e	J
    //   1047: invokevirtual 71	java/lang/StringBuilder:append	(J)Ljava/lang/StringBuilder;
    //   1050: ldc 73
    //   1052: invokevirtual 66	java/lang/StringBuilder:append	(Ljava/lang/String;)Ljava/lang/StringBuilder;
    //   1055: aload 5
    //   1057: invokevirtual 66	java/lang/StringBuilder:append	(Ljava/lang/String;)Ljava/lang/StringBuilder;
    //   1060: ldc 75
    //   1062: invokevirtual 66	java/lang/StringBuilder:append	(Ljava/lang/String;)Ljava/lang/StringBuilder;
    //   1065: pop
    //   1066: invokestatic 80	net/youmi/android/a/h/c/b/a:a	()Lnet/youmi/android/a/h/c/b/a;
    //   1069: aload_0
    //   1070: getfield 34	net/youmi/android/a/h/c/b/d:f	Ljava/lang/String;
    //   1073: aload 6
    //   1075: invokevirtual 81	java/lang/StringBuilder:toString	()Ljava/lang/String;
    //   1078: invokevirtual 84	net/youmi/android/a/h/c/b/a:a	(Ljava/lang/String;Ljava/lang/String;)V
    //   1081: aload 4
    //   1083: athrow
    //   1084: astore 5
    //   1086: goto -5 -> 1081
    //   1089: astore 5
    //   1091: goto -515 -> 576
    //   1094: astore 4
    //   1096: return
    // Local variable table:
    //   start	length	slot	name	signature
    //   0	1097	0	this	d
    //   246	288	1	i	int
    //   651	97	2	j	int
    //   504	6	3	k	int
    //   4	206	4	localObject1	Object
    //   236	1	4	localThrowable1	java.lang.Throwable
    //   282	50	4	str1	String
    //   358	1	4	localThrowable2	java.lang.Throwable
    //   380	88	4	str2	String
    //   494	1	4	localThrowable3	java.lang.Throwable
    //   523	189	4	locala	net.youmi.android.a.a.a.a
    //   736	1	4	localThrowable4	java.lang.Throwable
    //   782	50	4	str3	String
    //   858	1	4	localThrowable5	java.lang.Throwable
    //   861	1	4	localThrowable6	java.lang.Throwable
    //   894	50	4	str4	String
    //   970	1	4	localThrowable7	java.lang.Throwable
    //   973	109	4	localObject2	Object
    //   1094	1	4	localThrowable8	java.lang.Throwable
    //   58	998	5	localObject3	Object
    //   1084	1	5	localThrowable9	java.lang.Throwable
    //   1089	1	5	localThrowable10	java.lang.Throwable
    //   1022	52	6	localStringBuilder	java.lang.StringBuilder
    // Exception table:
    //   from	to	target	type
    //   129	235	236	java/lang/Throwable
    //   251	357	358	java/lang/Throwable
    //   387	493	494	java/lang/Throwable
    //   576	601	736	java/lang/Throwable
    //   601	650	736	java/lang/Throwable
    //   652	672	736	java/lang/Throwable
    //   674	723	736	java/lang/Throwable
    //   723	733	736	java/lang/Throwable
    //   751	857	858	java/lang/Throwable
    //   0	6	861	java/lang/Throwable
    //   118	124	861	java/lang/Throwable
    //   239	247	861	java/lang/Throwable
    //   361	382	861	java/lang/Throwable
    //   497	505	861	java/lang/Throwable
    //   512	525	861	java/lang/Throwable
    //   863	969	970	java/lang/Throwable
    //   0	6	973	finally
    //   118	124	973	finally
    //   239	247	973	finally
    //   361	382	973	finally
    //   497	505	973	finally
    //   512	525	973	finally
    //   537	576	973	finally
    //   576	601	973	finally
    //   601	650	973	finally
    //   652	672	973	finally
    //   674	723	973	finally
    //   723	733	973	finally
    //   975	1081	1084	java/lang/Throwable
    //   537	576	1089	java/lang/Throwable
    //   11	117	1094	java/lang/Throwable
  }
}


/* Location:           C:\Users\guanghui\Desktop\软件安全\37\classes-dex2jar.jar
 * Qualified Name:     net.youmi.android.a.h.c.b.d
 * JD-Core Version:    0.7.0.1
 */