package net.youmi.android.e.a;

public class c
{
  /* Error */
  public static byte[] a(byte[] paramArrayOfByte, java.lang.String paramString)
  {
    // Byte code:
    //   0: aload_0
    //   1: ifnonnull +5 -> 6
    //   4: aconst_null
    //   5: areturn
    //   6: aload_0
    //   7: arraylength
    //   8: ifeq -4 -> 4
    //   11: invokestatic 14	java/lang/System:currentTimeMillis	()J
    //   14: pop2
    //   15: aload_0
    //   16: arraylength
    //   17: istore_2
    //   18: invokestatic 14	java/lang/System:currentTimeMillis	()J
    //   21: pop2
    //   22: new 16	java/io/ByteArrayOutputStream
    //   25: dup
    //   26: invokespecial 20	java/io/ByteArrayOutputStream:<init>	()V
    //   29: astore_3
    //   30: new 22	java/util/zip/GZIPOutputStream
    //   33: dup
    //   34: aload_3
    //   35: invokespecial 25	java/util/zip/GZIPOutputStream:<init>	(Ljava/io/OutputStream;)V
    //   38: astore 4
    //   40: aload 4
    //   42: aload_0
    //   43: invokevirtual 29	java/util/zip/GZIPOutputStream:write	([B)V
    //   46: aload 4
    //   48: invokevirtual 32	java/util/zip/GZIPOutputStream:flush	()V
    //   51: aload 4
    //   53: invokevirtual 35	java/util/zip/GZIPOutputStream:close	()V
    //   56: aload_3
    //   57: invokevirtual 39	java/io/ByteArrayOutputStream:size	()I
    //   60: pop
    //   61: invokestatic 14	java/lang/System:currentTimeMillis	()J
    //   64: pop2
    //   65: invokestatic 44	net/youmi/android/c/c/f:a	()[B
    //   68: astore_0
    //   69: aload_3
    //   70: invokevirtual 47	java/io/ByteArrayOutputStream:toByteArray	()[B
    //   73: aload_1
    //   74: aload_0
    //   75: invokestatic 50	net/youmi/android/c/c/f:a	([BLjava/lang/String;[B)[B
    //   78: astore_1
    //   79: new 16	java/io/ByteArrayOutputStream
    //   82: dup
    //   83: invokespecial 20	java/io/ByteArrayOutputStream:<init>	()V
    //   86: astore 4
    //   88: aload 4
    //   90: aload_0
    //   91: invokevirtual 51	java/io/ByteArrayOutputStream:write	([B)V
    //   94: aload 4
    //   96: invokevirtual 52	java/io/ByteArrayOutputStream:flush	()V
    //   99: aload 4
    //   101: aload_1
    //   102: invokevirtual 51	java/io/ByteArrayOutputStream:write	([B)V
    //   105: aload 4
    //   107: invokevirtual 52	java/io/ByteArrayOutputStream:flush	()V
    //   110: invokestatic 14	java/lang/System:currentTimeMillis	()J
    //   113: pop2
    //   114: aload 4
    //   116: invokevirtual 39	java/io/ByteArrayOutputStream:size	()I
    //   119: pop
    //   120: aload 4
    //   122: invokevirtual 47	java/io/ByteArrayOutputStream:toByteArray	()[B
    //   125: astore_0
    //   126: aload 4
    //   128: ifnull +8 -> 136
    //   131: aload 4
    //   133: invokevirtual 53	java/io/ByteArrayOutputStream:close	()V
    //   136: aload_3
    //   137: ifnull +7 -> 144
    //   140: aload_3
    //   141: invokevirtual 53	java/io/ByteArrayOutputStream:close	()V
    //   144: iconst_0
    //   145: ifeq +11 -> 156
    //   148: new 55	java/lang/NullPointerException
    //   151: dup
    //   152: invokespecial 56	java/lang/NullPointerException:<init>	()V
    //   155: athrow
    //   156: aload_0
    //   157: areturn
    //   158: astore_0
    //   159: aconst_null
    //   160: astore_0
    //   161: aconst_null
    //   162: astore_3
    //   163: aconst_null
    //   164: astore_1
    //   165: aload_3
    //   166: ifnull +7 -> 173
    //   169: aload_3
    //   170: invokevirtual 53	java/io/ByteArrayOutputStream:close	()V
    //   173: aload_0
    //   174: ifnull +7 -> 181
    //   177: aload_0
    //   178: invokevirtual 53	java/io/ByteArrayOutputStream:close	()V
    //   181: aload_1
    //   182: ifnull -178 -> 4
    //   185: aload_1
    //   186: invokevirtual 35	java/util/zip/GZIPOutputStream:close	()V
    //   189: aconst_null
    //   190: areturn
    //   191: astore_0
    //   192: aconst_null
    //   193: areturn
    //   194: astore_0
    //   195: aconst_null
    //   196: astore 5
    //   198: aconst_null
    //   199: astore_3
    //   200: aconst_null
    //   201: astore_1
    //   202: aload_3
    //   203: ifnull +7 -> 210
    //   206: aload_3
    //   207: invokevirtual 53	java/io/ByteArrayOutputStream:close	()V
    //   210: aload 5
    //   212: ifnull +8 -> 220
    //   215: aload 5
    //   217: invokevirtual 53	java/io/ByteArrayOutputStream:close	()V
    //   220: aload_1
    //   221: ifnull +7 -> 228
    //   224: aload_1
    //   225: invokevirtual 35	java/util/zip/GZIPOutputStream:close	()V
    //   228: aload_0
    //   229: athrow
    //   230: astore_1
    //   231: goto -95 -> 136
    //   234: astore_1
    //   235: goto -91 -> 144
    //   238: astore_1
    //   239: goto -83 -> 156
    //   242: astore_3
    //   243: goto -70 -> 173
    //   246: astore_0
    //   247: goto -66 -> 181
    //   250: astore_3
    //   251: goto -41 -> 210
    //   254: astore_3
    //   255: goto -35 -> 220
    //   258: astore_1
    //   259: goto -31 -> 228
    //   262: astore_0
    //   263: aconst_null
    //   264: astore 4
    //   266: aconst_null
    //   267: astore_1
    //   268: aload_3
    //   269: astore 5
    //   271: aload 4
    //   273: astore_3
    //   274: goto -72 -> 202
    //   277: astore_0
    //   278: aconst_null
    //   279: astore 6
    //   281: aload 4
    //   283: astore_1
    //   284: aload_3
    //   285: astore 5
    //   287: aload 6
    //   289: astore_3
    //   290: goto -88 -> 202
    //   293: astore_0
    //   294: aconst_null
    //   295: astore_1
    //   296: aload_3
    //   297: astore 5
    //   299: aload 4
    //   301: astore_3
    //   302: goto -100 -> 202
    //   305: astore_0
    //   306: aload_3
    //   307: astore_0
    //   308: aconst_null
    //   309: astore_1
    //   310: aconst_null
    //   311: astore_3
    //   312: goto -147 -> 165
    //   315: astore_0
    //   316: aload 4
    //   318: astore_1
    //   319: aload_3
    //   320: astore_0
    //   321: aconst_null
    //   322: astore_3
    //   323: goto -158 -> 165
    //   326: astore_0
    //   327: aload_3
    //   328: astore_0
    //   329: aload 4
    //   331: astore_3
    //   332: aconst_null
    //   333: astore_1
    //   334: goto -169 -> 165
    // Local variable table:
    //   start	length	slot	name	signature
    //   0	337	0	paramArrayOfByte	byte[]
    //   0	337	1	paramString	java.lang.String
    //   17	1	2	i	int
    //   29	178	3	localByteArrayOutputStream	java.io.ByteArrayOutputStream
    //   242	1	3	localThrowable1	java.lang.Throwable
    //   250	1	3	localThrowable2	java.lang.Throwable
    //   254	15	3	localThrowable3	java.lang.Throwable
    //   273	59	3	localObject1	Object
    //   38	292	4	localObject2	Object
    //   196	102	5	localObject3	Object
    //   279	9	6	localObject4	Object
    // Exception table:
    //   from	to	target	type
    //   18	30	158	java/lang/Throwable
    //   185	189	191	java/lang/Throwable
    //   18	30	194	finally
    //   131	136	230	java/lang/Throwable
    //   140	144	234	java/lang/Throwable
    //   148	156	238	java/lang/Throwable
    //   169	173	242	java/lang/Throwable
    //   177	181	246	java/lang/Throwable
    //   206	210	250	java/lang/Throwable
    //   215	220	254	java/lang/Throwable
    //   224	228	258	java/lang/Throwable
    //   30	40	262	finally
    //   56	88	262	finally
    //   40	56	277	finally
    //   88	126	293	finally
    //   30	40	305	java/lang/Throwable
    //   56	88	305	java/lang/Throwable
    //   40	56	315	java/lang/Throwable
    //   88	126	326	java/lang/Throwable
  }
  
  /* Error */
  public static byte[] b(byte[] paramArrayOfByte, java.lang.String paramString)
  {
    // Byte code:
    //   0: aconst_null
    //   1: astore 8
    //   3: aload_0
    //   4: ifnonnull +8 -> 12
    //   7: aload 8
    //   9: astore_3
    //   10: aload_3
    //   11: areturn
    //   12: aload 8
    //   14: astore_3
    //   15: aload_0
    //   16: arraylength
    //   17: ifeq -7 -> 10
    //   20: invokestatic 14	java/lang/System:currentTimeMillis	()J
    //   23: pop2
    //   24: aload_0
    //   25: arraylength
    //   26: istore_2
    //   27: new 60	java/io/ByteArrayInputStream
    //   30: dup
    //   31: aload_0
    //   32: invokespecial 62	java/io/ByteArrayInputStream:<init>	([B)V
    //   35: astore_3
    //   36: bipush 8
    //   38: newarray byte
    //   40: astore 5
    //   42: aload_0
    //   43: arraylength
    //   44: bipush 8
    //   46: isub
    //   47: newarray byte
    //   49: astore_0
    //   50: aload_3
    //   51: aload 5
    //   53: iconst_0
    //   54: bipush 8
    //   56: invokevirtual 66	java/io/ByteArrayInputStream:read	([BII)I
    //   59: pop
    //   60: aload_3
    //   61: aload_0
    //   62: invokevirtual 69	java/io/ByteArrayInputStream:read	([B)I
    //   65: pop
    //   66: aload_3
    //   67: invokevirtual 70	java/io/ByteArrayInputStream:close	()V
    //   70: aconst_null
    //   71: astore 4
    //   73: invokestatic 14	java/lang/System:currentTimeMillis	()J
    //   76: pop2
    //   77: aload_0
    //   78: aload_1
    //   79: aload 5
    //   81: invokestatic 72	net/youmi/android/c/c/f:b	([BLjava/lang/String;[B)[B
    //   84: astore_0
    //   85: aload_0
    //   86: arraylength
    //   87: istore_2
    //   88: invokestatic 14	java/lang/System:currentTimeMillis	()J
    //   91: pop2
    //   92: new 60	java/io/ByteArrayInputStream
    //   95: dup
    //   96: aload_0
    //   97: invokespecial 62	java/io/ByteArrayInputStream:<init>	([B)V
    //   100: astore 6
    //   102: new 74	java/util/zip/GZIPInputStream
    //   105: dup
    //   106: aload 6
    //   108: invokespecial 77	java/util/zip/GZIPInputStream:<init>	(Ljava/io/InputStream;)V
    //   111: astore_3
    //   112: new 16	java/io/ByteArrayOutputStream
    //   115: dup
    //   116: invokespecial 20	java/io/ByteArrayOutputStream:<init>	()V
    //   119: astore 7
    //   121: aload_3
    //   122: astore_1
    //   123: aload_3
    //   124: astore 5
    //   126: sipush 1024
    //   129: newarray byte
    //   131: astore_0
    //   132: aload_3
    //   133: astore_1
    //   134: aload_3
    //   135: astore 5
    //   137: aload_3
    //   138: aload_0
    //   139: invokevirtual 78	java/util/zip/GZIPInputStream:read	([B)I
    //   142: istore_2
    //   143: iload_2
    //   144: ifle +76 -> 220
    //   147: aload_3
    //   148: astore_1
    //   149: aload_3
    //   150: astore 5
    //   152: aload 7
    //   154: aload_0
    //   155: iconst_0
    //   156: iload_2
    //   157: invokevirtual 81	java/io/ByteArrayOutputStream:write	([BII)V
    //   160: goto -28 -> 132
    //   163: astore_0
    //   164: aload 6
    //   166: astore_3
    //   167: aload 7
    //   169: astore_0
    //   170: aload_0
    //   171: ifnull +7 -> 178
    //   174: aload_0
    //   175: invokevirtual 53	java/io/ByteArrayOutputStream:close	()V
    //   178: aload_1
    //   179: ifnull +7 -> 186
    //   182: aload_1
    //   183: invokevirtual 82	java/util/zip/GZIPInputStream:close	()V
    //   186: aload_3
    //   187: ifnull +7 -> 194
    //   190: aload_3
    //   191: invokevirtual 70	java/io/ByteArrayInputStream:close	()V
    //   194: aload 8
    //   196: astore_3
    //   197: aload 4
    //   199: ifnull -189 -> 10
    //   202: aload 4
    //   204: invokevirtual 70	java/io/ByteArrayInputStream:close	()V
    //   207: aconst_null
    //   208: areturn
    //   209: astore_0
    //   210: aconst_null
    //   211: areturn
    //   212: astore 4
    //   214: aload_3
    //   215: astore 4
    //   217: goto -144 -> 73
    //   220: aload_3
    //   221: astore_1
    //   222: aload_3
    //   223: astore 5
    //   225: aload 7
    //   227: invokevirtual 52	java/io/ByteArrayOutputStream:flush	()V
    //   230: aload_3
    //   231: astore 5
    //   233: aload_3
    //   234: invokevirtual 82	java/util/zip/GZIPInputStream:close	()V
    //   237: aconst_null
    //   238: astore_3
    //   239: aload_3
    //   240: astore_1
    //   241: aload_3
    //   242: astore 5
    //   244: aload 7
    //   246: invokevirtual 39	java/io/ByteArrayOutputStream:size	()I
    //   249: pop
    //   250: aload_3
    //   251: astore_1
    //   252: aload_3
    //   253: astore 5
    //   255: invokestatic 14	java/lang/System:currentTimeMillis	()J
    //   258: pop2
    //   259: aload_3
    //   260: astore_1
    //   261: aload_3
    //   262: astore 5
    //   264: aload 7
    //   266: invokevirtual 47	java/io/ByteArrayOutputStream:toByteArray	()[B
    //   269: astore_0
    //   270: aload 7
    //   272: ifnull +8 -> 280
    //   275: aload 7
    //   277: invokevirtual 53	java/io/ByteArrayOutputStream:close	()V
    //   280: aload_3
    //   281: ifnull +7 -> 288
    //   284: aload_3
    //   285: invokevirtual 82	java/util/zip/GZIPInputStream:close	()V
    //   288: aload 6
    //   290: ifnull +8 -> 298
    //   293: aload 6
    //   295: invokevirtual 70	java/io/ByteArrayInputStream:close	()V
    //   298: aload_0
    //   299: astore_3
    //   300: aload 4
    //   302: ifnull -292 -> 10
    //   305: aload 4
    //   307: invokevirtual 70	java/io/ByteArrayInputStream:close	()V
    //   310: aload_0
    //   311: areturn
    //   312: astore_1
    //   313: aload_0
    //   314: areturn
    //   315: astore_0
    //   316: aconst_null
    //   317: astore_3
    //   318: aconst_null
    //   319: astore 5
    //   321: aconst_null
    //   322: astore 4
    //   324: aconst_null
    //   325: astore_1
    //   326: aload_1
    //   327: ifnull +7 -> 334
    //   330: aload_1
    //   331: invokevirtual 53	java/io/ByteArrayOutputStream:close	()V
    //   334: aload_3
    //   335: ifnull +7 -> 342
    //   338: aload_3
    //   339: invokevirtual 82	java/util/zip/GZIPInputStream:close	()V
    //   342: aload 5
    //   344: ifnull +8 -> 352
    //   347: aload 5
    //   349: invokevirtual 70	java/io/ByteArrayInputStream:close	()V
    //   352: aload 4
    //   354: ifnull +8 -> 362
    //   357: aload 4
    //   359: invokevirtual 70	java/io/ByteArrayInputStream:close	()V
    //   362: aload_0
    //   363: athrow
    //   364: astore_0
    //   365: goto -126 -> 239
    //   368: astore_1
    //   369: goto -89 -> 280
    //   372: astore_1
    //   373: goto -85 -> 288
    //   376: astore_1
    //   377: goto -79 -> 298
    //   380: astore_0
    //   381: goto -203 -> 178
    //   384: astore_0
    //   385: goto -199 -> 186
    //   388: astore_0
    //   389: goto -195 -> 194
    //   392: astore_1
    //   393: goto -59 -> 334
    //   396: astore_1
    //   397: goto -55 -> 342
    //   400: astore_1
    //   401: goto -49 -> 352
    //   404: astore_1
    //   405: goto -43 -> 362
    //   408: astore_0
    //   409: aconst_null
    //   410: astore 5
    //   412: aload_3
    //   413: astore 4
    //   415: aconst_null
    //   416: astore_1
    //   417: aconst_null
    //   418: astore_3
    //   419: goto -93 -> 326
    //   422: astore_0
    //   423: aconst_null
    //   424: astore_3
    //   425: aconst_null
    //   426: astore 5
    //   428: aconst_null
    //   429: astore_1
    //   430: goto -104 -> 326
    //   433: astore_0
    //   434: aconst_null
    //   435: astore_3
    //   436: aconst_null
    //   437: astore_1
    //   438: aload 6
    //   440: astore 5
    //   442: goto -116 -> 326
    //   445: astore_0
    //   446: aconst_null
    //   447: astore_1
    //   448: aload 6
    //   450: astore 5
    //   452: goto -126 -> 326
    //   455: astore_0
    //   456: aload 7
    //   458: astore_1
    //   459: aload 5
    //   461: astore_3
    //   462: aload 6
    //   464: astore 5
    //   466: goto -140 -> 326
    //   469: astore_0
    //   470: aconst_null
    //   471: astore_0
    //   472: aconst_null
    //   473: astore_1
    //   474: aconst_null
    //   475: astore_3
    //   476: aconst_null
    //   477: astore 4
    //   479: goto -309 -> 170
    //   482: astore_0
    //   483: aconst_null
    //   484: astore_1
    //   485: aconst_null
    //   486: astore 5
    //   488: aload_3
    //   489: astore 4
    //   491: aconst_null
    //   492: astore_0
    //   493: aload 5
    //   495: astore_3
    //   496: goto -326 -> 170
    //   499: astore_0
    //   500: aconst_null
    //   501: astore_0
    //   502: aconst_null
    //   503: astore_1
    //   504: aconst_null
    //   505: astore_3
    //   506: goto -336 -> 170
    //   509: astore_0
    //   510: aconst_null
    //   511: astore_0
    //   512: aconst_null
    //   513: astore_1
    //   514: aload 6
    //   516: astore_3
    //   517: goto -347 -> 170
    //   520: astore_0
    //   521: aconst_null
    //   522: astore_0
    //   523: aload_3
    //   524: astore_1
    //   525: aload 6
    //   527: astore_3
    //   528: goto -358 -> 170
    // Local variable table:
    //   start	length	slot	name	signature
    //   0	531	0	paramArrayOfByte	byte[]
    //   0	531	1	paramString	java.lang.String
    //   26	131	2	i	int
    //   9	519	3	localObject1	Object
    //   71	132	4	localObject2	Object
    //   212	1	4	localThrowable	java.lang.Throwable
    //   215	275	4	localObject3	Object
    //   40	454	5	localObject4	Object
    //   100	426	6	localByteArrayInputStream	java.io.ByteArrayInputStream
    //   119	338	7	localByteArrayOutputStream	java.io.ByteArrayOutputStream
    //   1	194	8	localObject5	Object
    // Exception table:
    //   from	to	target	type
    //   126	132	163	java/lang/Throwable
    //   137	143	163	java/lang/Throwable
    //   152	160	163	java/lang/Throwable
    //   225	230	163	java/lang/Throwable
    //   244	250	163	java/lang/Throwable
    //   255	259	163	java/lang/Throwable
    //   264	270	163	java/lang/Throwable
    //   202	207	209	java/lang/Throwable
    //   66	70	212	java/lang/Throwable
    //   305	310	312	java/lang/Throwable
    //   27	36	315	finally
    //   233	237	364	java/lang/Throwable
    //   275	280	368	java/lang/Throwable
    //   284	288	372	java/lang/Throwable
    //   293	298	376	java/lang/Throwable
    //   174	178	380	java/lang/Throwable
    //   182	186	384	java/lang/Throwable
    //   190	194	388	java/lang/Throwable
    //   330	334	392	java/lang/Throwable
    //   338	342	396	java/lang/Throwable
    //   347	352	400	java/lang/Throwable
    //   357	362	404	java/lang/Throwable
    //   36	66	408	finally
    //   66	70	408	finally
    //   73	102	422	finally
    //   102	112	433	finally
    //   112	121	445	finally
    //   126	132	455	finally
    //   137	143	455	finally
    //   152	160	455	finally
    //   225	230	455	finally
    //   233	237	455	finally
    //   244	250	455	finally
    //   255	259	455	finally
    //   264	270	455	finally
    //   27	36	469	java/lang/Throwable
    //   36	66	482	java/lang/Throwable
    //   73	102	499	java/lang/Throwable
    //   102	112	509	java/lang/Throwable
    //   112	121	520	java/lang/Throwable
  }
}


/* Location:           C:\Users\guanghui\Desktop\软件安全\37\classes-dex2jar.jar
 * Qualified Name:     net.youmi.android.e.a.c
 * JD-Core Version:    0.7.0.1
 */