package net.youmi.android.a.d;

import net.youmi.android.e.a.d;

public class a
  extends d
{
  private static d a;
  private static d b;
  private static d c;
  
  /* Error */
  public static d a(android.content.Context paramContext)
  {
    // Byte code:
    //   0: ldc 2
    //   2: monitorenter
    //   3: getstatic 13	net/youmi/android/a/d/a:a	Lnet/youmi/android/e/a/d;
    //   6: ifnonnull +20 -> 26
    //   9: new 4	net/youmi/android/e/a/d
    //   12: dup
    //   13: aload_0
    //   14: invokevirtual 19	android/content/Context:getApplicationContext	()Landroid/content/Context;
    //   17: ldc 21
    //   19: iconst_1
    //   20: invokespecial 25	net/youmi/android/e/a/d:<init>	(Landroid/content/Context;Ljava/lang/String;I)V
    //   23: putstatic 13	net/youmi/android/a/d/a:a	Lnet/youmi/android/e/a/d;
    //   26: getstatic 13	net/youmi/android/a/d/a:a	Lnet/youmi/android/e/a/d;
    //   29: astore_0
    //   30: ldc 2
    //   32: monitorexit
    //   33: aload_0
    //   34: areturn
    //   35: astore_0
    //   36: ldc 2
    //   38: monitorexit
    //   39: aload_0
    //   40: athrow
    //   41: astore_0
    //   42: goto -16 -> 26
    // Local variable table:
    //   start	length	slot	name	signature
    //   0	45	0	paramContext	android.content.Context
    // Exception table:
    //   from	to	target	type
    //   3	26	35	finally
    //   26	30	35	finally
    //   3	26	41	java/lang/Throwable
  }
  
  /* Error */
  public static d b(android.content.Context paramContext)
  {
    // Byte code:
    //   0: ldc 2
    //   2: monitorenter
    //   3: getstatic 28	net/youmi/android/a/d/a:b	Lnet/youmi/android/e/a/d;
    //   6: ifnonnull +20 -> 26
    //   9: new 4	net/youmi/android/e/a/d
    //   12: dup
    //   13: aload_0
    //   14: invokevirtual 19	android/content/Context:getApplicationContext	()Landroid/content/Context;
    //   17: ldc 30
    //   19: iconst_5
    //   20: invokespecial 25	net/youmi/android/e/a/d:<init>	(Landroid/content/Context;Ljava/lang/String;I)V
    //   23: putstatic 28	net/youmi/android/a/d/a:b	Lnet/youmi/android/e/a/d;
    //   26: getstatic 28	net/youmi/android/a/d/a:b	Lnet/youmi/android/e/a/d;
    //   29: astore_0
    //   30: ldc 2
    //   32: monitorexit
    //   33: aload_0
    //   34: areturn
    //   35: astore_0
    //   36: ldc 2
    //   38: monitorexit
    //   39: aload_0
    //   40: athrow
    //   41: astore_0
    //   42: goto -16 -> 26
    // Local variable table:
    //   start	length	slot	name	signature
    //   0	45	0	paramContext	android.content.Context
    // Exception table:
    //   from	to	target	type
    //   3	26	35	finally
    //   26	30	35	finally
    //   3	26	41	java/lang/Throwable
  }
  
  /* Error */
  public static d c(android.content.Context paramContext)
  {
    // Byte code:
    //   0: ldc 2
    //   2: monitorenter
    //   3: getstatic 32	net/youmi/android/a/d/a:c	Lnet/youmi/android/e/a/d;
    //   6: ifnonnull +20 -> 26
    //   9: new 4	net/youmi/android/e/a/d
    //   12: dup
    //   13: aload_0
    //   14: invokevirtual 19	android/content/Context:getApplicationContext	()Landroid/content/Context;
    //   17: ldc 34
    //   19: iconst_1
    //   20: invokespecial 25	net/youmi/android/e/a/d:<init>	(Landroid/content/Context;Ljava/lang/String;I)V
    //   23: putstatic 32	net/youmi/android/a/d/a:c	Lnet/youmi/android/e/a/d;
    //   26: getstatic 32	net/youmi/android/a/d/a:c	Lnet/youmi/android/e/a/d;
    //   29: astore_0
    //   30: ldc 2
    //   32: monitorexit
    //   33: aload_0
    //   34: areturn
    //   35: astore_0
    //   36: ldc 2
    //   38: monitorexit
    //   39: aload_0
    //   40: athrow
    //   41: astore_0
    //   42: goto -16 -> 26
    // Local variable table:
    //   start	length	slot	name	signature
    //   0	45	0	paramContext	android.content.Context
    // Exception table:
    //   from	to	target	type
    //   3	26	35	finally
    //   26	30	35	finally
    //   3	26	41	java/lang/Throwable
  }
}


/* Location:           C:\Users\guanghui\Desktop\软件安全\361\classes-dex2jar.jar
 * Qualified Name:     net.youmi.android.a.d.a
 * JD-Core Version:    0.7.0.1
 */